Workbook

Sheet Anleitung
A1: Finanzmodell Cruizy — Anleitung
A2: Aufgabe A-13 · erstellt 27.07.2026 · Rolle: Finanzmodellierer · Fenster V1 · Grundlage: Handbuch B, Teile II–V · fortgeschrieben 21.09.2026 (A-52: Beschlüsse vom 19. und 21.09.2026)
A4: DIESES MODELL RECHNET. ES ENTSCHEIDET NICHT. Jede Zahl darin ist eine Annahme mit Herkunft — nachlesbar auf dem Blatt „Herkunft & Widersprüche". Wer eine Annahme ändert, sieht die Wirkung sofort bis in die Kennzahlen. Genau dafür ist es gebaut.
A6: Farben
A7: BLAU = Stellhebel. Hier wird geändert. Alles andere rechnet sich daraus.
A8: GELB = von Menschen auszufüllen. Ist-Werte, Entscheidungen, bestätigte Angaben.
A9: WEISS mit Formel = Ergebnis. Nicht überschreiben, sonst bricht die Kette.
A10: BERNSTEIN = Hinweis oder Widerspruch, der bewusst stehen bleibt.
A12: Die Blätter, in der Reihenfolge, in der man sie liest
A13: Blatt | B13: Was darin steht | C13: Wer es anfasst
A14: Annahmen | B14: Sämtliche Stellhebel: Nutzerentwicklung, Monetarisierung mit der Erlöskette je Zahler (2a), weitere Erlösquellen, Kostenstaffel, JMStV-Schalter, Einmalkosten, CSD-Auftritte, laufende Kosten aus Beschlüssen (7a), Kapitalbedarf und Lebenshaltung.
A15: Pessimistisch / Realistisch / Optimistisch | B15: 36 Monatsspalten je Szenario: Nutzer, Zahler, fünf Erlösquellen, Kostenblöcke, Ergebnis, kumulierte Liquidität; nachrichtlich Krankenversicherung und Lebenshaltung. Reine Formeln.
A16: Kennzahlen | B16: Tiefpunkt, Break-even, Kapitalbedarf je Szenario und der Gesamtbedarf mit Lebenshaltung (Nr. 38). Darunter der Abgleich gegen Handbuch B, die vier Prüfwege, die Empfindlichkeit und wie viele Zahler es braucht.
A17: Finanzierungswege | B17: Sechs durchgerechnete Wege, wie die Lücke geschlossen werden könnte, samt Wirkung auf Verwässerung, persönliches Risiko und Handlungsfreiheit.
A18: Ist-Werte | B18: Leer. Ab dem ersten realen Monat werden hier die tatsächlichen Zahlen eingetragen; das Blatt vergleicht automatisch mit dem Plan.
A19: Herkunft & Widersprüche | B19: Für jede Annahme die Quelle — und die fünf Stellen, an denen Handbuch B sich selbst widerspricht. Seit A-52 dazu die Liste aller Änderungen mit ihrer Wirkung.
A21: Was dieses Modell bewusst nicht tut
A22: Es zahlt in keinem Szenario ein Gründergehalt. Handbuch B tut das im optimistischen Fall ab Monat 16 — hier nicht, weil ein Gehalt eine Entscheidung ist und keine Rechengröße. Wer es einplanen will, trägt es als eigene Kostenzeile ein und sieht sofort, was es kostet. Die Lebenshaltung beider Gründer rechnet es seit A-52 mit — nicht als Gehalt, sondern als privaten Bedarf neben der Firma (Blatt „Kennzahlen“, Gesamtbedarf). Es empfiehlt keinen Finanzierungsweg. Das Blatt „Finanzierungswege" stellt sechs Wege nebeneinander und benennt bei jedem, was er mit den Gründern macht — nicht nur, was er einbringt. Die Auswahl ist eine Lebensentscheidung und keine Rechenaufgabe. Es behauptet keine Genauigkeit, die es nicht hat. Der Start liegt frühestens im Sommer 2028; geplant wird ein Jahr später (Nr. 45). Bis dahin ändern sich Preise, Anbieter und Recht. Der Wert dieses Modells liegt nicht in den Zahlen, sondern darin, dass die Größe sichtbar wird, auf die es ankommt.

Sheet Annahmen
A1: Annahmen — alle Stellhebel an einem Ort
A2: Blaue Felder ändern. Alles Weitere rechnet sich daraus. Spalte F nennt die Herkunft jeder Zahl. Fortgeschrieben am 21.09.2026 (A-52): neu die Abschnitte 2a und 7a, geändert 3, 6, 7 und 8.
A4: 1 · Nutzerentwicklung
A5: Größe | B5: Pessimistisch | C5: Realistisch | D5: Optimistisch | F5: Herkunft
A6: MAU Ende Jahr 1 | B6: 4000 | C6: 7500 | D6: 14000 | F6: Handbuch B, Szenarienvergleich
A7: MAU Ende Jahr 2 | B7: 14000 | C7: 24000 | D7: 60000 | F7: Handbuch B, Szenarienvergleich
A8: MAU Ende Jahr 3 | B8: 30000 | C8: 62000 | D8: 150000 | F8: Handbuch B, Szenarienvergleich
A9: Startmonat (erster Monat mit Nutzern) | B9: 2 | C9: 2 | D9: 2 | F9: KALIBRIERT auf die Jahresmittel aus Handbuch B. Entspricht einer geschlossenen Erprobung ab Monat 2.
A10: Rampenexponent Jahr 1 | B10: 1.2 | C10: 1.38 | D10: 1.34 | F10: KALIBRIERT. Wert über 1 = langsamer Start, beschleunigend. Unter 1 = schneller Start, abflachend.
A11: Rampenexponent Jahr 2–3 | B11: 1.34 | C11: 1.28 | D11: 1.26 | F11: KALIBRIERT auf die Jahresmittel aus Handbuch B.
A12: Städte Ende Jahr 1 | B12: 1 | C12: 1 | D12: 1 | F12: Handbuch B: Start in Köln, Dichte vor Fläche
A13: Städte Ende Jahr 2 | B13: 2 | C13: 2 | D13: 3 | F13: abgeleitet aus „Städte Ende Jahr 3" in Handbuch B
A14: Städte Ende Jahr 3 | B14: 2 | C14: 4 | D14: 6 | F14: Handbuch B, Szenarienvergleich
A15: Monatliche Nutzerabwanderung | B15: 0.1 | C15: 0.08 | D15: 0.07 | F15: ANNAHME. Gegenstück zur 30-Tage-Wiederkehr (15/24/30 %) aus Handbuch B. Bestimmt die Zahl der Neuregistrierungen und damit die Prüfkosten.
A16: Rückkehrerquote — Anteil der Abwanderer, der zurückkommt | B16: 0.3 | C16: 0.3 | D16: 0.3 | F16: ANNAHME. Entscheidend für die Prüfkosten: Wer zurückkommt, ist nach dem AVS-Raster der KJM BEREITS identifiziert und muss sich nur noch authentifizieren. Nur echte Neuzugänge kosten Geld.
A17: 30-Tage-Wiederkehr (nachrichtlich) | B17: 0.15 | C17: 0.24 | D17: 0.3 | F17: Handbuch B, Szenarienvergleich — hier nur zur Einordnung, nicht rechenwirksam
A18: Eintrittswahrscheinlichkeit (Schätzung) | B18: 0.4 | C18: 0.35 | D18: 0.1 | F18: Handbuch B. Restliche 15 %: Abbruch vor Monat 24.
A20: 2 · Monetarisierung
A21: Größe | B21: Pessimistisch | C21: Realistisch | D21: Optimistisch | F21: Herkunft
A22: Monetarisierungsstart (Monat) | B22: 18 | C22: 14 | D22: 11 | F22: Handbuch B, Szenarienvergleich
A23: Zielkonversion Jahr 3 | B23: 0.022 | C23: 0.036 | D23: 0.042 | F23: Handbuch B, Szenarienvergleich
A24: Anfangsanteil der Zielkonversion | B24: 0.05 | C24: 0.48 | D24: 0.52 | F24: KALIBRIERT auf die Zahler-Jahresmittel aus Handbuch B (Jahre 2 und 3)
A25: Rampendauer bis Zielkonversion (Monate) | B25: 3 | C25: 22 | D25: 22 | F25: KALIBRIERT
A26: Nettoerlös je Zahler und Monat | B26: =$B$51 -> 7.5593776 | C26: =$B$51 -> 7.5593776 | D26: =$B$51 -> 7.5593776 | F26: Rechnet sich seit A-52 aus der Erlöskette in Abschnitt 2a (Zeile 51) — vorher fest 7,38 € aus Handbuch B. Mit den Werten aus Handbuch B ergibt die Kette dieselben 7,38 € (Probe in Zeile 52).
A28: 2a · Erlöskette je Zahler — zwei Abostufen, Web und Store (Nr. 48, 50, 67 · A-51, A-53)
A29: WAS HIER NEU IST: Bis zum 21.09.2026 stand in Zeile 26 eine feste Zahl aus Handbuch B (7,38 €). Jetzt rechnet sie sich aus Preisen, Laufzeiten, Stufenanteil und Zahlungsweg. Eingeflossen sind drei Beschlüsse und zwei Recherchen: zwei Abostufen plus Unterstützerbeitrag (Nr. 67), Inkognito und Travel im Abo (Nr. 48), Jahresabo vorausgewählt (Nr. 50), die Web-Fassung zuerst und vollständig (A-51) und die tatsächliche Gebühr eines europäischen Zahlungsdienstes statt pauschal 4 Prozent (A-53). Mit den Werten aus Handbuch B ergibt die Kette dieselben 7,38 € — die Probe steht in Zeile 52.
A30: Laufzeit | B30: PLUS, brutto | C30: PRO, brutto | D30: Anteil der Käufe | E30: Monate | F30: Herkunft
A31: 1 Monat | B31: 9 | C31: 17 | D31: 0.45 | E31: 1 | F31: Handbuch B, Preisliste und „Abwanderung nach Laufzeit“: Bruttopreise und Anteil der Käufe je Laufzeit.
A32: 3 Monate | B32: 23 | C32: 43 | D32: 0.2 | E32: 3 | F32: Handbuch B · Nachlass 15 %
A33: 6 Monate | B33: 40 | C33: 76 | D33: 0.15 | E33: 6 | F33: Handbuch B · Nachlass 26 %
A34: 12 Monate | B34: 70 | C34: 132 | D34: 0.2 | E34: 12 | F34: Handbuch B · Nachlass 35 %. Nr. 50: Das Jahresabo ist vorausgewählt, alle Laufzeiten stehen gleich deutlich da — Handbuch B setzt die Vorauswahl bei diesen Anteilen bereits voraus.
A35: Größe | B35: Wert | F35: Herkunft
A36: Anteil PRO an den Zahlern | B36: 0.3 | F36: Handbuch B: 70 % PLUS, 30 % PRO. ENTSCHIEDEN am 26.09.2026 (Nr. 67, Teil 3) nach Nr. 48 und 67: PLUS = Komfort und Inkognito, PRO = alles aus PLUS und dazu Travel — umsehen und schreiben in einer anderen Region (Nr. 77), die Reiseankündigung nur, wenn Nr. 85 so entschieden wird. Ob dann noch 30 % die teurere Stufe wählen, ist die unsicherste Zahl dieses Blocks — Wirkung in der Tabelle ab Zeile 54. — NACHGERECHNET 26.09.2026: 20 % statt 30 % kosten 4.673 € Firmenbedarf und 9.873 € Gesamtbedarf, Break-even Monat 30; 15 % kosten 7.558 € bzw. 15.358 €, Break-even Monat 31. Der PRO-Anteil ist ab dem Monetarisierungsstart beobachtete Kennzahl; zwei Monate unter 20 % lösen eine Neubewertung des Zuschnitts aus (nicht eine Preissenkung).
A37: Umsatzsteuer | B37: 0.19 | F37: Handbuch B: Die Kleinunternehmerregelung greift bei einer GmbH nicht. Österreich 20 %, Schweiz 8,1 % (Skalierungs-Playbook) — für eine Auslandsstadt hier ändern.
A38: Provision der Stores | B38: 0.15 | F38: Handbuch B: 15 % mit dem Small-Business-Programm (muss beantragt werden), sonst 30 %. Sonderbedingungen in der EU nach dem Digital Markets Act sind nicht eingerechnet.
A39: Web-Zahlungsdienst, prozentualer Teil | B39: 0.018 | F39: A-53: Mollie (Amsterdam, lizenziert bei der niederländischen Zentralbank), 1,80 % + 0,25 € je Zahlung mit EWR-Karte, keine Monatsgebühr — abgerufen 20.09.2026. Welcher Dienst es wird, ist noch offen (eu-alternativen-stack.md, Punkt 6).
A40: Web-Zahlungsdienst, fester Teil je Zahlung | B40: 0.25 | F40: A-53, wie oben
A41: Anteil der Zahlungen über das Web | B41: 0.6 | F41: ANNAHME A-52. Handbuch B: 40 %. Höher angesetzt, weil die Web-Fassung zuerst und vollständig erscheint (A-51), Codes nur auf der Webseite eingelöst werden (Nr. 60) und Apple Käufe über das Web in der App anerkennt, sofern sie dort auch als In-App-Kauf angeboten werden (Richtlinie 3.1.3(b), geprüft 21.09.2026). Handbuch B nennt die Verschiebung zum Web ausdrücklich als Hebel.
A42: Ergebnis der Kette | B42: je Zahler und Monat | F42: Probe und Herkunft
A43: Gemischter Monatswert PLUS | B43: =SUMPRODUCT($D$31:$D$34,$B$31:$B$34/$E$31:$E$34) -> 7.75 | F43: über alle Laufzeiten gewichtet
A44: Gemischter Monatswert PRO | B44: =SUMPRODUCT($D$31:$D$34,$C$31:$C$34/$E$31:$E$34) -> 14.616667 | F44: über alle Laufzeiten gewichtet
A45: Gemischter Bruttopreis | B45: =(1-$B$36)*$B$43+$B$36*$B$44 -> 9.81 | F45: Handbuch B: 9,82 €
A46: nach Umsatzsteuer | B46: =$B$45/(1+$B$37) -> 8.2436975 | F46: Handbuch B: 8,25 €
A47: Zahlungsvorgänge je Zahler und Monat | B47: =SUMPRODUCT($D$31:$D$34,1/$E$31:$E$34) -> 0.55833333 | F47: Ein Monatsabo zahlt jeden Monat, ein Jahresabo einmal im Jahr. Wichtig für den festen Teil der Web-Gebühr.
A48: Gebühr des Web-Zahlungsdienstes | B48: =$B$39*$B$45+$B$40*$B$47 -> 0.31616333 | F48: prozentualer Teil auf den Bruttopreis plus fester Teil je Zahlungsvorgang. Handbuch B rechnete pauschal mit rund 4 %.
A49: Nettoerlös bei Zahlung über das Web | B49: =$B$46-$B$48 -> 7.9275341 | F49: Handbuch B: 7,93 €
A50: Nettoerlös bei Zahlung über einen Store | B50: =$B$46*(1-$B$38) -> 7.0071429 | F50: Handbuch B: 7,01 €
A51: NETTOERLÖS JE ZAHLER UND MONAT | B51: =$B$41*$B$49+(1-$B$41)*$B$50 -> 7.5593776 | F51: geht in Zeile 26 und damit in alle drei Szenarien
A52: Probe: dieselbe Kette mit den Werten aus Handbuch B (30 % PRO, 40 % Web) | B52: =0.4*((0.7*$B$43+0.3*$B$44)/(1+$B$37)-($B$39*(0.7*$B$43+0.3*$B$44)+$B$40*$B$47))+0.6*(0.7*$B$43+0.3*$B$44)/(1+$B$37)*(1-$B$38) -> 7.3752994 | F52: muss 7,38 € ergeben
A54: Nettoerlös je Zahler — Anteil PRO (Zeile) gegen Anteil Web (Spalte) | B54: 0.4 | C54: 0.6 | D54: 0.8 | F54: Lesehilfe
A55: 0.1 | B55: =B$54*(((1-$A55)*$B$43+$A55*$B$44)/(1+$B$37)-($B$39*((1-$A55)*$B$43+$A55*$B$44)+$B$40*$B$47))+(1-B$54)*((1-$A55)*$B$43+$A55*$B$44)/(1+$B$37)*(1-$B$38) -> 6.3349913 | C55: =C$54*(((1-$A55)*$B$43+$A55*$B$44)/(1+$B$37)-($B$39*((1-$A55)*$B$43+$A55*$B$44)+$B$40*$B$47))+(1-C$54)*((1-$A55)*$B$43+$A55*$B$44)/(1+$B$37)*(1-$B$38) -> 6.4893917 | D55: =D$54*(((1-$A55)*$B$43+$A55*$B$44)/(1+$B$37)-($B$39*((1-$A55)*$B$43+$A55*$B$44)+$B$40*$B$47))+(1-D$54)*((1-$A55)*$B$43+$A55*$B$44)/(1+$B$37)*(1-$B$38) -> 6.6437921 | F55: Jede Zelle ist die vollständige Kette mit anderem Stufenanteil und Web-Anteil; grün ist die Voreinstellung. Zehn Prozentpunkte weniger PRO kosten rund 0,53 € je Zahler, zwanzig Punkte mehr Web bringen rund 0,18 €. Die Stufenfrage wiegt also rund dreimal so schwer wie der Zahlungsweg — und sie ist die unsicherere. Im Kapitalbedarf der Firma (realistisch): 20 % PRO statt 30 % kosten rund 4.700 €, 10 % PRO rund 10.900 €.
A56: 0.2 | B56: =B$54*(((1-$A56)*$B$43+$A56*$B$44)/(1+$B$37)-($B$39*((1-$A56)*$B$43+$A56*$B$44)+$B$40*$B$47))+(1-B$54)*((1-$A56)*$B$43+$A56*$B$44)/(1+$B$37)*(1-$B$38) -> 6.8551453 | C56: =C$54*(((1-$A56)*$B$43+$A56*$B$44)/(1+$B$37)-($B$39*((1-$A56)*$B$43+$A56*$B$44)+$B$40*$B$47))+(1-C$54)*((1-$A56)*$B$43+$A56*$B$44)/(1+$B$37)*(1-$B$38) -> 7.0243847 | D56: =D$54*(((1-$A56)*$B$43+$A56*$B$44)/(1+$B$37)-($B$39*((1-$A56)*$B$43+$A56*$B$44)+$B$40*$B$47))+(1-D$54)*((1-$A56)*$B$43+$A56*$B$44)/(1+$B$37)*(1-$B$38) -> 7.193624
A57: 0.3 | B57: =B$54*(((1-$A57)*$B$43+$A57*$B$44)/(1+$B$37)-($B$39*((1-$A57)*$B$43+$A57*$B$44)+$B$40*$B$47))+(1-B$54)*((1-$A57)*$B$43+$A57*$B$44)/(1+$B$37)*(1-$B$38) -> 7.3752994 | C57: =C$54*(((1-$A57)*$B$43+$A57*$B$44)/(1+$B$37)-($B$39*((1-$A57)*$B$43+$A57*$B$44)+$B$40*$B$47))+(1-C$54)*((1-$A57)*$B$43+$A57*$B$44)/(1+$B$37)*(1-$B$38) -> 7.5593776 | D57: =D$54*(((1-$A57)*$B$43+$A57*$B$44)/(1+$B$37)-($B$39*((1-$A57)*$B$43+$A57*$B$44)+$B$40*$B$47))+(1-D$54)*((1-$A57)*$B$43+$A57*$B$44)/(1+$B$37)*(1-$B$38) -> 7.7434559
A58: 0.4 | B58: =B$54*(((1-$A58)*$B$43+$A58*$B$44)/(1+$B$37)-($B$39*((1-$A58)*$B$43+$A58*$B$44)+$B$40*$B$47))+(1-B$54)*((1-$A58)*$B$43+$A58*$B$44)/(1+$B$37)*(1-$B$38) -> 7.8954534 | C58: =C$54*(((1-$A58)*$B$43+$A58*$B$44)/(1+$B$37)-($B$39*((1-$A58)*$B$43+$A58*$B$44)+$B$40*$B$47))+(1-C$54)*((1-$A58)*$B$43+$A58*$B$44)/(1+$B$37)*(1-$B$38) -> 8.0943706 | D58: =D$54*(((1-$A58)*$B$43+$A58*$B$44)/(1+$B$37)-($B$39*((1-$A58)*$B$43+$A58*$B$44)+$B$40*$B$47))+(1-D$54)*((1-$A58)*$B$43+$A58*$B$44)/(1+$B$37)*(1-$B$38) -> 8.2932878
A60: 3 · Weitere Erlösquellen — nach Nr. 65, 74 und 78 neu geschnitten
A61: Größe | B61: Pessimistisch | C61: Realistisch | D61: Optimistisch | F61: Herkunft
A62: Werkzeugabo für Orte und Veranstalter — Startmonat | B62: 13 | C62: 13 | D62: 13 | F62: ANNAHME A-52: ab dem zweiten Jahr (Veranstaltungskonzept, Abschnitt 5a). Ersetzt die Ortspartnerschaften aus Handbuch B, die Hervorhebung und Vorabplatzierung verkauften — nach Nr. 65 ausgeschlossen. BESTÄTIGT 26.09.2026 (Nr. 87): Business-Konten kosten ab dem zweiten Jahr Geld; was ein zahlendes Konto einträgt, gilt als bezahlt und wird gekennzeichnet (§ 5a Abs. 4 UWG, Art. 26 DSA). Kostenloses Eintragen durch uns bleibt möglich — das Abo kauft Werkzeuge, nicht Sichtbarkeit (Nr. 96, W-31).
A63: Werkzeugabo — MAU-Schwelle | B63: 8000 | C63: 8000 | D63: 8000 | F63: Handbuch B: Premiumstufen ab 8.000 MAU — als Vorsicht übernommen. Werkzeug lohnt sich für Veranstalter erst, wenn über Cruizy genug Menschen kommen.
A64: Werkzeugabo — zahlende Konten je Stadt | B64: 5 | C64: 5 | D64: 5 | F64: ANNAHME A-55 (Veranstaltungskonzept 5a). Handbuch B rechnete im Reifezustand mit rund zehn Partnern je Stadt — für Sichtbarkeit, nicht für Werkzeug.
A65: Werkzeugabo — Preis je Konto und Monat, netto | B65: 29 | C65: 29 | D65: 29 | F65: ANNAHME A-55: 19 bis 39 € im Monat, hier die Mitte. Einlass per Code, Serien, Kontingente, anonyme Summen, mehrere Verantwortliche. Die Grundfunktionen bleiben kostenlos.
A66: Ticketanteil — Startmonat | B66: 13 | C66: 13 | D66: 13 | F66: ANNAHME A-52: zweites Jahr (Veranstaltungskonzept 5a). Handbuch B: Monat 18.
A67: Ticketanteil — MAU-Schwelle | B67: 20000 | C67: 20000 | D67: 20000 | F67: Handbuch B: Auslöser 20.000 MAU — als Vorsicht übernommen. Ein Anteil fließt nur, wenn über Cruizy tatsächlich Tickets verkauft werden, und das braucht Reichweite.
A68: Ticketanteil — Veranstaltungen mit Ticket je Stadt und Monat | B68: 8 | C68: 8 | D68: 8 | F68: ANNAHME A-55. Handbuch B: 40 Ereignisse im Monat, davon 30 % mit Ticketverkauf, also 12.
A69: Ticketanteil — Tickets je Veranstaltung | B69: 80 | C69: 80 | D69: 80 | F69: Handbuch B und A-55: 80
A70: Ticketanteil — Ticketpreis, brutto | B70: 12 | C70: 12 | D70: 12 | F70: Handbuch B und A-55: 12 €
A71: Ticketanteil — Anteil für Cruizy | B71: 0.03 | C71: 0.03 | D71: 0.03 | F71: Vorschlag A-55: 3 %, gedeckelt — unter Eventbrite (5,5 %) und nahe pretix (2,5 %, höchstens 15 € je Ticket), beide abgerufen 21.09.2026. Handbuch B: 6 %. Vereinfacht als Nettoerlös gerechnet. Auflage aus Handbuch B: nicht selbst abwickeln (Anwaltsfrage V12).
A72: Unterstützer — Startmonat | B72: 14 | C72: 14 | D72: 14 | F72: Handbuch B: Auslöser Monat 14. Nr. 67: jederzeit möglich, schaltet nichts frei; Codes nach Nr. 60 für Unterstützer ab einem Betrag (Codesystem, Art U). ENTSCHIEDEN 26.09.2026 (Nr. 67): frei wählbarer Betrag ab 3 €, OHNE Abzeichen und ohne Listeneintrag (Handbuch B: 5 € mit Abzeichen). Abweichung bewusst — ein Abzeichen ist gekaufte Sichtbarkeit in klein (Nr. 65).
A73: Unterstützer — € je MAU und Monat | B73: 0.015 | C73: 0.015 | D73: 0.015 | F73: ABGELEITET: 600 € bei 40.000 MAU NACHGERECHNET 26.09.2026: 0,010 € kosten 1.565 € Gesamtbedarf, 0,008 € kosten 4.836 € und einen Monat Break-even. Der Verzicht auf das Abzeichen ist damit wirtschaftlich billig.
... A75: Gesundheit — € je Stadt und Monat | B75: 267 | C75: 267 | D75: 267 | F75: ABGELEITET: 800 € bei 3 Städten
A76: NICHT ANGESETZT — mit Absicht: Werbung (Nr. 78: keine), bezahlte Hervorhebung von Orten oder Veranstaltungen (Nr. 65: keine), Kontingente der Veranstalter (sie bringen Plätze, kein Geld) und ihr freiwilliger Zuschuss (nicht schätzbar), Crowdfunding (Finanzierung, kein Erlös — Blatt „Finanzierungswege“). Handbuch B rechnete an dieser Stelle im Reifezustand mit 1.600 € Ortspartnerschaften und 2.100 € Ticketing im Monat. Was davon nach Nr. 65 und A-55 bleibt, steht auf dem Blatt „Herkunft & Widersprüche“, Abschnitt 5.
A78: 4 · Kostenstaffel nach Nutzerzahl (Handbuch B, monatlich)
A79: Position | B79: 0 MAU | C79: 5.000 | D79: 12.000 | E79: 20.000 | F79: 50.000 MAU
A80: MAU-Stützstelle | B80: 0 | C80: 5000 | D80: 12000 | E80: 20000 | F80: 50000
A81: Externer Datenschutzbeauftragter | B81: 250 | C81: 250 | D81: 300 | E81: 350 | F81: 450
A82: Jugendschutzbeauftragter | B82: 100 | C82: 100 | D82: 120 | E82: 140 | F82: 180
A83: Rechtsberatung, Rückstellung | B83: 300 | C83: 300 | D83: 350 | E83: 400 | F83: 600
A84: Cyber- und Betriebshaftpflicht | B84: 200 | C84: 220 | D84: 250 | E84: 300 | F84: 450
A85: Buchhaltung, Steuerberatung | B85: 150 | C85: 180 | D85: 220 | E85: 280 | F85: 420
A86: Hash-Abgleich, Moderations-KI | B86: 0 | C86: 250 | D86: 380 | E86: 520 | F86: 1100
A87: Hosting, Infrastruktur | B87: 80 | C87: 180 | D87: 280 | E87: 420 | F87: 900
A88: Werkzeuge, Entwicklerzugänge | B88: 90 | C88: 90 | D88: 110 | E88: 130 | F88: 200
A89: KI-Werkzeuge Entwicklung | B89: 100 | C89: 100 | D89: 120 | E89: 120 | F89: 150
A90: Zahlungsabwicklung, Grundgebühren | B90: 0 | C90: 40 | D90: 50 | E90: 60 | F90: 100
A91: Altersprüfung (nur Vergleichswert — wird gerechnet) | B91: 0 | C91: 300 | D91: 520 | E91: 780 | F91: 1600
... A93: Marketing: Druck, Material, Reise, Werkzeuge | B93: 150 | C93: 250 | D93: 400 | E93: 600 | F93: 1200
A94: Block Pflichtpositionen (nicht kürzbar) | B94: =B81+B82+B83+B84+B85+B86 -> 1000 | C94: =C81+C82+C83+C84+C85+C86 -> 1300 | D94: =D81+D82+D83+D84+D85+D86 -> 1620 | E94: =E81+E82+E83+E84+E85+E86 -> 1990 | F94: =F81+F82+F83+F84+F85+F86 -> 3200
A95: Block Betrieb (ohne Altersprüfung) | B95: =B87+B88+B89+B90 -> 270 | C95: =C87+C88+C89+C90 -> 410 | D95: =D87+D88+D89+D90 -> 560 | E95: =E87+E88+E89+E90 -> 730 | F95: =F87+F88+F89+F90 -> 1350
A96: Block Personal (Moderation) | B96: =B92 -> 0 | C96: =C92 -> 0 | D96: =D92 -> 0 | E96: =E92 -> 1700 | F96: =F92 -> 3400
A97: Block Marketing (Barmittel) | B97: =B93 -> 150 | C97: =C93 -> 250 | D97: =D93 -> 400 | E97: =E93 -> 600 | F97: =F93 -> 1200
A98: Spaltensumme aller Positionen | B98: =B81+B82+B83+B84+B85+B86+B87+B88+B89+B90+B92+B93+B91 -> 1420 | C98: =C81+C82+C83+C84+C85+C86+C87+C88+C89+C90+C92+C93+C91 -> 2260 | D98: =D81+D82+D83+D84+D85+D86+D87+D88+D89+D90+D92+D93+D91 -> 3100 | E98: =E81+E82+E83+E84+E85+E86+E87+E88+E89+E90+E92+E93+E91 -> 5800 | F98: =F81+F82+F83+F84+F85+F86+F87+F88+F89+F90+F92+F93+F91 -> 10750
A99: Handbuch B nennt als Spaltensumme | B99: 1420 | C99: 2260 | D99: 3100 | E99: 5800 | F99: 12150
A100: Differenz (Spaltensumme minus Handbuch B) | B100: =B98-B99 -> 0 | C100: =C98-C99 -> 0 | D100: =D98-D99 -> 0 | E100: =E98-E99 -> 0 | F100: =F98-F99 -> -1400
A101: WIDERSPRUCH 1 IN HANDBUCH B: Vier der fünf Spalten summieren sich exakt auf die genannte Summe. Die Spalte „50.000 MAU" nicht — dort fehlen 1.400 €. Die naheliegende Erklärung: Bei 50.000 MAU ist eine einzelne Moderationskraft in Teilzeit nicht mehr plausibel (A-37 rechnet bei 40.000 MAU mit 37–73 Bildern täglich in der menschlichen Warteschlange). Mit 4.800 € statt 3.400 € für Moderation ginge die Rechnung auf. Dieses Modell rechnet mit den EINZELPOSITIONEN, nicht mit der genannten Summe — wer der anderen Lesart folgen will, trägt oben 4.800 € ein und sieht die Wirkung sofort.
A103: 5 · Altersprüfung — der teuerste Schalter im Modell
A104: Weg | B104: Preis je Prüfung | F104: Herkunft und Belastbarkeit
A105: Stufe 1 — Altersschätzung für alle Nutzer | B105: 0.22 | F105: ABGELEITET aus der Staffelzeile „Altersprüfung" in Handbuch B ÷ Neuregistrierungen ⇒ 0,22 €. Bemerkenswert nah an der einzigen öffentlichen Preisangabe aus A-07 (Didit: 0,20 $ White-Label-Verifizierung, Marketingangabe).
A106: Stufe 2, Weg A — EUDI-Wallet, in Deutschland „d-you“ (ab 02.01.2027) | B106: 0.15 | F106: SCHÄTZUNG. Die staatliche Brieftasche ist ab 02.01.2027 für alle in Deutschland kostenlos verfügbar und enthält einen Altersnachweis; der Dienst erfährt nur „Altersgrenze erfüllt“ (A-53). Zum geplanten Start (Nr. 45) ist sie rund zweieinhalb Jahre im Feld. KEIN öffentlicher Preis bekannt — Schätzung.
A107: Stufe 2, Weg B — eID des Personalausweises | B107: 1 | F107: SCHÄTZUNG. Das AVS-Raster der KJM nennt die eID-Funktion ausdrücklich als zulässigen Weg der persönlichen Identifizierung. Branchenaussagen: vollautomatisiert, in Sekunden, „deutlich günstiger als Post- und VideoIdent". Kein öffentlicher Stückpreis auffindbar — im Gespräch mit AusweisIDent zu klären.
A108: Stufe 2, Weg C — VideoIdent / AutoIdent | B108: 3.5 | F108: MARKTSPANNE 2–5 €. Belegt: Banken zahlen derzeit rund 7–8 € je VideoIdent-Vorgang, erwartet wird ein Rückgang auf etwa 2 €. In A-07 nennt KEIN Anbieter öffentliche Preise.
A109: SCHALTER Stufe 2 — 0 = nicht erforderlich · 1 = EUDI-Wallet · 2 = eID · 3 = VideoIdent | B109: 2 | F109: GELBES FELD — hier entscheidet sich mehr Geld als an jeder anderen Stelle des Modells. Voreinstellung 2 (eID), weil das AVS-Raster der KJM diesen Weg ausdrücklich zulässt und er der günstigste heute schon verfügbare ist. Stand 21.09.2026: bleibt auf 2, bis Nr. 40 entschieden ist — nach A-53 dürfte das obere Ende fallen, weil die KJM die Altersschätzung als Identifizierungsmodul anerkennt.
...

Sheet Pessimistisch
A1: Szenario A — Pessimistisch
A2: 36 Monate ab T0 — dem Start in der CSD-Saison; geplant wird ein Jahr nach dem Bestfall Sommer 2028 (Nr. 45). Alles rechnet sich aus dem Blatt „Annahmen“. Kein Gründergehalt in keinem Monat.
A4: Position | B4: M1 | C4: M2 | D4: M3 | E4: M4 | F4: M5 | G4: M6 | H4: M7 | I4: M8 | J4: M9 | K4: M10 | L4: M11 | M4: M12 | N4: M13 | O4: M14 | P4: M15 | Q4: M16 | R4: M17 | S4: M18 | T4: M19 | U4: M20 | V4: M21 | W4: M22 | X4: M23 | Y4: M24 | Z4: M25 | AA4: M26 | AB4: M27 | AC4: M28 | AD4: M29 | AE4: M30 | AF4: M31 | AG4: M32 | AH4: M33 | AI4: M34 | AJ4: M35 | AK4: M36
A5: Monat | B5: 1 | C5: 2 | D5: 3 | E5: 4 | F5: 5 | G5: 6 | H5: 7 | I5: 8 | J5: 9 | K5: 10 | L5: 11 | M5: 12 | N5: 13 | O5: 14 | P5: 15 | Q5: 16 | R5: 17 | S5: 18 | T5: 19 | U5: 20 | V5: 21 | W5: 22 | X5: 23 | Y5: 24 | Z5: 25 | AA5: 26 | AB5: 27 | AC5: 28 | AD5: 29 | AE5: 30 | AF5: 31 | AG5: 32 | AH5: 33 | AI5: 34 | AJ5: 35 | AK5: 36
A6: Jahr | B6: =ROUNDUP(B5/12,0) -> 1 | C6: =ROUNDUP(C5/12,0) -> 1 | D6: =ROUNDUP(D5/12,0) -> 1 | E6: =ROUNDUP(E5/12,0) -> 1 | F6: =ROUNDUP(F5/12,0) -> 1 | G6: =ROUNDUP(G5/12,0) -> 1 | H6: =ROUNDUP(H5/12,0) -> 1 | I6: =ROUNDUP(I5/12,0) -> 1 | ... AK6: =ROUNDUP(AK5/12,0) -> 3
A7: Aktive Nutzer im Monat (MAU) | B7: =IF(B5<Annahmen!$B$9,0,IF(B5<=12,Annahmen!$B$6*((B5-Annahmen!$B$9+1)/(12-Annahmen!$B$9+1))^Annahmen!$B$10,IF(B5<=24,Annahmen!$B$6+(Annahmen!$B$7-Annahmen!$B$6)*((B5-12)/12)^Annahmen!$B$11,Annahmen!$B$7+(Annahmen!$B$8-Annahmen!$B$7)*((B5-24)/12)^Annahmen!$B$11))) -> 0 | C7: =IF(C5<Annahmen!$B$9,0,IF(C5<=12,Annahmen!$B$6*((C5-Annahmen!$B$9+1)/(12-Annahmen!$B$9+1))^Annahmen!$B$10,IF(C5<=24,Annahmen!$B$6+(Annahmen!$B$7-Annahmen!$B$6)*((C5-12)/12)^Annahmen!$B$11,Annahmen!$B$7+(Annahmen!$B$8-Annahmen!$B$7)*((C5-24)/12)^Annahmen!$B$11))) -> 225.10688 | D7: =IF(D5<Annahmen!$B$9,0,IF(D5<=12,Annahmen!$B$6*((D5-Annahmen!$B$9+1)/(12-Annahmen!$B$9+1))^Annahmen!$B$10,IF(D5<=24,Annahmen!$B$6+(Annahmen!$B$7-Annahmen!$B$6)*((D5-12)/12)^Annahmen!$B$11,Annahmen!$B$7+(Annahmen!$B$8-Annahmen!$B$7)*((D5-24)/12)^Annahmen!$B$11))) -> 517.15981 | E7: =IF(E5<Annahmen!$B$9,0,IF(E5<=12,Annahmen!$B$6*((E5-Annahmen!$B$9+1)/(12-Annahmen!$B$9+1))^Annahmen!$B$10,IF(E5<=24,Annahmen!$B$6+(Annahmen!$B$7-Annahmen!$B$6)*((E5-12)/12)^Annahmen!$B$11,Annahmen!$B$7+(Annahmen!$B$8-Annahmen!$B$7)*((E5-24)/12)^Annahmen!$B$11))) -> 841.26782 | F7: =IF(F5<Annahmen!$B$9,0,IF(F5<=12,Annahmen!$B$6*((F5-Annahmen!$B$9+1)/(12-Annahmen!$B$9+1))^Annahmen!$B$10,IF(F5<=24,Annahmen!$B$6+(Annahmen!$B$7-Annahmen!$B$6)*((F5-12)/12)^Annahmen!$B$11,Annahmen!$B$7+(Annahmen!$B$8-Annahmen!$B$7)*((F5-24)/12)^Annahmen!$B$11))) -> 1188.1212 | G7: =IF(G5<Annahmen!$B$9,0,IF(G5<=12,Annahmen!$B$6*((G5-Annahmen!$B$9+1)/(12-Annahmen!$B$9+1))^Annahmen!$B$10,IF(G5<=24,Annahmen!$B$6+(Annahmen!$B$7-Annahmen!$B$6)*((G5-12)/12)^Annahmen!$B$11,Annahmen!$B$7+(Annahmen!$B$8-Annahmen!$B$7)*((G5-24)/12)^Annahmen!$B$11))) -> 1552.9332 | H7: =IF(H5<Annahmen!$B$9,0,IF(H5<=12,Annahmen!$B$6*((H5-Annahmen!$B$9+1)/(12-Annahmen!$B$9+1))^Annahmen!$B$10,IF(H5<=24,Annahmen!$B$6+(Annahmen!$B$7-Annahmen!$B$6)*((H5-12)/12)^Annahmen!$B$11,Annahmen!$B$7+(Annahmen!$B$8-Annahmen!$B$7)*((H5-24)/12)^Annahmen!$B$11))) -> 1932.7259 | I7: =IF(I5<Annahmen!$B$9,0,IF(I5<=12,Annahmen!$B$6*((I5-Annahmen!$B$9+1)/(12-Annahmen!$B$9+1))^Annahmen!$B$10,IF(I5<=24,Annahmen!$B$6+(Annahmen!$B$7-Annahmen!$B$6)*((I5-12)/12)^Annahmen!$B$11,Annahmen!$B$7+(Annahmen!$B$8-Annahmen!$B$7)*((I5-24)/12)^Annahmen!$B$11))) -> 2325.4468 | ... AK7: =IF(AK5<Annahmen!$B$9,0,IF(AK5<=12,Annahmen!$B$6*((AK5-Annahmen!$B$9+1)/(12-Annahmen!$B$9+1))^Annahmen!$B$10,IF(AK5<=24,Annahmen!$B$6+(Annahmen!$B$7-Annahmen!$B$6)*((AK5-12)/12)^Annahmen!$B$11,Annahmen!$B$7+(Annahmen!$B$8-Annahmen!$B$7)*((AK5-24)/12)^Annahmen!$B$11))) -> 30000
A8: Städte | B8: =IF(B5<=12,Annahmen!$B$12,IF(B5<=24,Annahmen!$B$13,Annahmen!$B$14)) -> 1 | C8: =IF(C5<=12,Annahmen!$B$12,IF(C5<=24,Annahmen!$B$13,Annahmen!$B$14)) -> 1 | D8: =IF(D5<=12,Annahmen!$B$12,IF(D5<=24,Annahmen!$B$13,Annahmen!$B$14)) -> 1 | E8: =IF(E5<=12,Annahmen!$B$12,IF(E5<=24,Annahmen!$B$13,Annahmen!$B$14)) -> 1 | F8: =IF(F5<=12,Annahmen!$B$12,IF(F5<=24,Annahmen!$B$13,Annahmen!$B$14)) -> 1 | G8: =IF(G5<=12,Annahmen!$B$12,IF(G5<=24,Annahmen!$B$13,Annahmen!$B$14)) -> 1 | H8: =IF(H5<=12,Annahmen!$B$12,IF(H5<=24,Annahmen!$B$13,Annahmen!$B$14)) -> 1 | I8: =IF(I5<=12,Annahmen!$B$12,IF(I5<=24,Annahmen!$B$13,Annahmen!$B$14)) -> 1 | ... AK8: =IF(AK5<=12,Annahmen!$B$12,IF(AK5<=24,Annahmen!$B$13,Annahmen!$B$14)) -> 2
A9: Neuregistrierungen (Treiber der Prüfkosten) | B9: =MAX(0,B7-0)+B7*Annahmen!$B$15*(1-Annahmen!$B$16) -> 0 | C9: =MAX(0,C7-B7)+C7*Annahmen!$B$15*(1-Annahmen!$B$16) -> 240.86436 | D9: =MAX(0,D7-C7)+D7*Annahmen!$B$15*(1-Annahmen!$B$16) -> 328.25411 | E9: =MAX(0,E7-D7)+E7*Annahmen!$B$15*(1-Annahmen!$B$16) -> 382.99676 | F9: =MAX(0,F7-E7)+F7*Annahmen!$B$15*(1-Annahmen!$B$16) -> 430.02191 | G9: =MAX(0,G7-F7)+G7*Annahmen!$B$15*(1-Annahmen!$B$16) -> 473.51729 | H9: =MAX(0,H7-G7)+H7*Annahmen!$B$15*(1-Annahmen!$B$16) -> 515.08353 | I9: =MAX(0,I7-H7)+I7*Annahmen!$B$15*(1-Annahmen!$B$16) -> 555.50221 | J9: =MAX(0,J7-I7)+J7*Annahmen!$B$15*(1-Annahmen!$B$16) -> 595.20998 | ... AK9: =MAX(0,AK7-AJ7)+AK7*Annahmen!$B$15*(1-Annahmen!$B$16) -> 3860.8747
A10: Konversion zu Zahlern | B10: =IF(B5<Annahmen!$B$22,0,Annahmen!$B$23*(Annahmen!$B$24+(1-Annahmen!$B$24)*MIN(1,(B5-Annahmen!$B$22+1)/Annahmen!$B$25))) -> 0 | C10: =IF(C5<Annahmen!$B$22,0,Annahmen!$B$23*(Annahmen!$B$24+(1-Annahmen!$B$24)*MIN(1,(C5-Annahmen!$B$22+1)/Annahmen!$B$25))) -> 0 | D10: =IF(D5<Annahmen!$B$22,0,Annahmen!$B$23*(Annahmen!$B$24+(1-Annahmen!$B$24)*MIN(1,(D5-Annahmen!$B$22+1)/Annahmen!$B$25))) -> 0 | E10: =IF(E5<Annahmen!$B$22,0,Annahmen!$B$23*(Annahmen!$B$24+(1-Annahmen!$B$24)*MIN(1,(E5-Annahmen!$B$22+1)/Annahmen!$B$25))) -> 0 | F10: =IF(F5<Annahmen!$B$22,0,Annahmen!$B$23*(Annahmen!$B$24+(1-Annahmen!$B$24)*MIN(1,(F5-Annahmen!$B$22+1)/Annahmen!$B$25))) -> 0 | G10: =IF(G5<Annahmen!$B$22,0,Annahmen!$B$23*(Annahmen!$B$24+(1-Annahmen!$B$24)*MIN(1,(G5-Annahmen!$B$22+1)/Annahmen!$B$25))) -> 0 | H10: =IF(H5<Annahmen!$B$22,0,Annahmen!$B$23*(Annahmen!$B$24+(1-Annahmen!$B$24)*MIN(1,(H5-Annahmen!$B$22+1)/Annahmen!$B$25))) -> 0 | I10: =IF(I5<Annahmen!$B$22,0,Annahmen!$B$23*(Annahmen!$B$24+(1-Annahmen!$B$24)*MIN(1,(I5-Annahmen!$B$22+1)/Annahmen!$B$25))) -> 0 | ... AK10: =IF(AK5<Annahmen!$B$22,0,Annahmen!$B$23*(Annahmen!$B$24+(1-Annahmen!$B$24)*MIN(1,(AK5-Annahmen!$B$22+1)/Annahmen!$B$25))) -> 0.022
A11: Zahlende Nutzer | B11: =B7*B10 -> 0 | C11: =C7*C10 -> 0 | D11: =D7*D10 -> 0 | E11: =E7*E10 -> 0 | F11: =F7*F10 -> 0 | G11: =G7*G10 -> 0 | H11: =H7*H10 -> 0 | I11: =I7*I10 -> 0 | ... AK11: =AK7*AK10 -> 660
A12: Staffel-Stützstelle (Hilfsgröße) | B12: =MIN(MATCH(B7,Annahmen!$B$80:$F$80,1),4) -> 1 | C12: =MIN(MATCH(C7,Annahmen!$B$80:$F$80,1),4) -> 1 | D12: =MIN(MATCH(D7,Annahmen!$B$80:$F$80,1),4) -> 1 | E12: =MIN(MATCH(E7,Annahmen!$B$80:$F$80,1),4) -> 1 | F12: =MIN(MATCH(F7,Annahmen!$B$80:$F$80,1),4) -> 1 | G12: =MIN(MATCH(G7,Annahmen!$B$80:$F$80,1),4) -> 1 | H12: =MIN(MATCH(H7,Annahmen!$B$80:$F$80,1),4) -> 1 | I12: =MIN(MATCH(I7,Annahmen!$B$80:$F$80,1),4) -> 1 | ... AK12: =MIN(MATCH(AK7,Annahmen!$B$80:$F$80,1),4) -> 4
A13: ERLÖSE — fünf Quellen (Handbuch B, nach Nr. 65 und 74 neu geschnitten)
A14: Abonnements | B14: =B11*Annahmen!$B$26 -> 0 | C14: =C11*Annahmen!$B$26 -> 0 | D14: =D11*Annahmen!$B$26 -> 0 | E14: =E11*Annahmen!$B$26 -> 0 | F14: =F11*Annahmen!$B$26 -> 0 | G14: =G11*Annahmen!$B$26 -> 0 | H14: =H11*Annahmen!$B$26 -> 0 | I14: =I11*Annahmen!$B$26 -> 0 | ... AK14: =AK11*Annahmen!$B$26 -> 4989.1892
A15: Werkzeugabo für Orte und Veranstalter | B15: =IF(AND(B5>=Annahmen!$B$62,B7>=Annahmen!$B$63),B8*Annahmen!$B$64*Annahmen!$B$65,0) -> 0 | C15: =IF(AND(C5>=Annahmen!$B$62,C7>=Annahmen!$B$63),C8*Annahmen!$B$64*Annahmen!$B$65,0) -> 0 | D15: =IF(AND(D5>=Annahmen!$B$62,D7>=Annahmen!$B$63),D8*Annahmen!$B$64*Annahmen!$B$65,0) -> 0 | E15: =IF(AND(E5>=Annahmen!$B$62,E7>=Annahmen!$B$63),E8*Annahmen!$B$64*Annahmen!$B$65,0) -> 0 | F15: =IF(AND(F5>=Annahmen!$B$62,F7>=Annahmen!$B$63),F8*Annahmen!$B$64*Annahmen!$B$65,0) -> 0 | G15: =IF(AND(G5>=Annahmen!$B$62,G7>=Annahmen!$B$63),G8*Annahmen!$B$64*Annahmen!$B$65,0) -> 0 | H15: =IF(AND(H5>=Annahmen!$B$62,H7>=Annahmen!$B$63),H8*Annahmen!$B$64*Annahmen!$B$65,0) -> 0 | I15: =IF(AND(I5>=Annahmen!$B$62,I7>=Annahmen!$B$63),I8*Annahmen!$B$64*Annahmen!$B$65,0) -> 0 | ... AK15: =IF(AND(AK5>=Annahmen!$B$62,AK7>=Annahmen!$B$63),AK8*Annahmen!$B$64*Annahmen!$B$65,0) -> 290
A16: Veranstaltungen: Anteil an Tickets | B16: =IF(AND(B5>=Annahmen!$B$66,B7>=Annahmen!$B$67),B8*Annahmen!$B$68*Annahmen!$B$69*Annahmen!$B$70*Annahmen!$B$71,0) -> 0 | C16: =IF(AND(C5>=Annahmen!$B$66,C7>=Annahmen!$B$67),C8*Annahmen!$B$68*Annahmen!$B$69*Annahmen!$B$70*Annahmen!$B$71,0) -> 0 | D16: =IF(AND(D5>=Annahmen!$B$66,D7>=Annahmen!$B$67),D8*Annahmen!$B$68*Annahmen!$B$69*Annahmen!$B$70*Annahmen!$B$71,0) -> 0 | E16: =IF(AND(E5>=Annahmen!$B$66,E7>=Annahmen!$B$67),E8*Annahmen!$B$68*Annahmen!$B$69*Annahmen!$B$70*Annahmen!$B$71,0) -> 0 | F16: =IF(AND(F5>=Annahmen!$B$66,F7>=Annahmen!$B$67),F8*Annahmen!$B$68*Annahmen!$B$69*Annahmen!$B$70*Annahmen!$B$71,0) -> 0 | G16: =IF(AND(G5>=Annahmen!$B$66,G7>=Annahmen!$B$67),G8*Annahmen!$B$68*Annahmen!$B$69*Annahmen!$B$70*Annahmen!$B$71,0) -> 0 | H16: =IF(AND(H5>=Annahmen!$B$66,H7>=Annahmen!$B$67),H8*Annahmen!$B$68*Annahmen!$B$69*Annahmen!$B$70*Annahmen!$B$71,0) -> 0 | I16: =IF(AND(I5>=Annahmen!$B$66,I7>=Annahmen!$B$67),I8*Annahmen!$B$68*Annahmen!$B$69*Annahmen!$B$70*Annahmen!$B$71,0) -> 0 | ... AK16: =IF(AND(AK5>=Annahmen!$B$66,AK7>=Annahmen!$B$67),AK8*Annahmen!$B$68*Annahmen!$B$69*Annahmen!$B$70*Annahmen!$B$71,0) -> 460.8
A17: Unterstützerbeiträge | B17: =IF(B5>=Annahmen!$B$72,B7*Annahmen!$B$73,0) -> 0 | C17: =IF(C5>=Annahmen!$B$72,C7*Annahmen!$B$73,0) -> 0 | D17: =IF(D5>=Annahmen!$B$72,D7*Annahmen!$B$73,0) -> 0 | E17: =IF(E5>=Annahmen!$B$72,E7*Annahmen!$B$73,0) -> 0 | F17: =IF(F5>=Annahmen!$B$72,F7*Annahmen!$B$73,0) -> 0 | G17: =IF(G5>=Annahmen!$B$72,G7*Annahmen!$B$73,0) -> 0 | H17: =IF(H5>=Annahmen!$B$72,H7*Annahmen!$B$73,0) -> 0 | I17: =IF(I5>=Annahmen!$B$72,I7*Annahmen!$B$73,0) -> 0 | ... AK17: =IF(AK5>=Annahmen!$B$72,AK7*Annahmen!$B$73,0) -> 450
A18: Gesundheitspartnerschaft | B18: =IF(B5>=Annahmen!$B$74,B8*Annahmen!$B$75,0) -> 0 | C18: =IF(C5>=Annahmen!$B$74,C8*Annahmen!$B$75,0) -> 0 | D18: =IF(D5>=Annahmen!$B$74,D8*Annahmen!$B$75,0) -> 0 | E18: =IF(E5>=Annahmen!$B$74,E8*Annahmen!$B$75,0) -> 0 | F18: =IF(F5>=Annahmen!$B$74,F8*Annahmen!$B$75,0) -> 0 | G18: =IF(G5>=Annahmen!$B$74,G8*Annahmen!$B$75,0) -> 0 | H18: =IF(H5>=Annahmen!$B$74,H8*Annahmen!$B$75,0) -> 0 | I18: =IF(I5>=Annahmen!$B$74,I8*Annahmen!$B$75,0) -> 0 | ... AK18: =IF(AK5>=Annahmen!$B$74,AK8*Annahmen!$B$75,0) -> 534
A19: Erlöse gesamt | B19: =SUM(B14:B18) -> 0 | C19: =SUM(C14:C18) -> 0 | D19: =SUM(D14:D18) -> 0 | E19: =SUM(E14:E18) -> 0 | F19: =SUM(F14:F18) -> 0 | G19: =SUM(G14:G18) -> 0 | H19: =SUM(H14:H18) -> 0 | I19: =SUM(I14:I18) -> 0 | ... AK19: =SUM(AK14:AK18) -> 6723.9892
A21: KOSTEN
A22: Pflichtpositionen (nicht kürzbar) | B22: =INDEX(Annahmen!$B$94:$F$94,B$12)+(B$7-INDEX(Annahmen!$B$80:$F$80,B$12))*(INDEX(Annahmen!$B$94:$F$94,B$12+1)-INDEX(Annahmen!$B$94:$F$94,B$12))/(INDEX(Annahmen!$B$80:$F$80,B$12+1)-INDEX(Annahmen!$B$80:$F$80,B$12)) -> 1000 | C22: =INDEX(Annahmen!$B$94:$F$94,C$12)+(C$7-INDEX(Annahmen!$B$80:$F$80,C$12))*(INDEX(Annahmen!$B$94:$F$94,C$12+1)-INDEX(Annahmen!$B$94:$F$94,C$12))/(INDEX(Annahmen!$B$80:$F$80,C$12+1)-INDEX(Annahmen!$B$80:$F$80,C$12)) -> 1013.5064 | D22: =INDEX(Annahmen!$B$94:$F$94,D$12)+(D$7-INDEX(Annahmen!$B$80:$F$80,D$12))*(INDEX(Annahmen!$B$94:$F$94,D$12+1)-INDEX(Annahmen!$B$94:$F$94,D$12))/(INDEX(Annahmen!$B$80:$F$80,D$12+1)-INDEX(Annahmen!$B$80:$F$80,D$12)) -> 1031.0296 | E22: =INDEX(Annahmen!$B$94:$F$94,E$12)+(E$7-INDEX(Annahmen!$B$80:$F$80,E$12))*(INDEX(Annahmen!$B$94:$F$94,E$12+1)-INDEX(Annahmen!$B$94:$F$94,E$12))/(INDEX(Annahmen!$B$80:$F$80,E$12+1)-INDEX(Annahmen!$B$80:$F$80,E$12)) -> 1050.4761 | F22: =INDEX(Annahmen!$B$94:$F$94,F$12)+(F$7-INDEX(Annahmen!$B$80:$F$80,F$12))*(INDEX(Annahmen!$B$94:$F$94,F$12+1)-INDEX(Annahmen!$B$94:$F$94,F$12))/(INDEX(Annahmen!$B$80:$F$80,F$12+1)-INDEX(Annahmen!$B$80:$F$80,F$12)) -> 1071.2873 | G22: =INDEX(Annahmen!$B$94:$F$94,G$12)+(G$7-INDEX(Annahmen!$B$80:$F$80,G$12))*(INDEX(Annahmen!$B$94:$F$94,G$12+1)-INDEX(Annahmen!$B$94:$F$94,G$12))/(INDEX(Annahmen!$B$80:$F$80,G$12+1)-INDEX(Annahmen!$B$80:$F$80,G$12)) -> 1093.176 | H22: =INDEX(Annahmen!$B$94:$F$94,H$12)+(H$7-INDEX(Annahmen!$B$80:$F$80,H$12))*(INDEX(Annahmen!$B$94:$F$94,H$12+1)-INDEX(Annahmen!$B$94:$F$94,H$12))/(INDEX(Annahmen!$B$80:$F$80,H$12+1)-INDEX(Annahmen!$B$80:$F$80,H$12)) -> 1115.9636 | I22: =INDEX(Annahmen!$B$94:$F$94,I$12)+(I$7-INDEX(Annahmen!$B$80:$F$80,I$12))*(INDEX(Annahmen!$B$94:$F$94,I$12+1)-INDEX(Annahmen!$B$94:$F$94,I$12))/(INDEX(Annahmen!$B$80:$F$80,I$12+1)-INDEX(Annahmen!$B$80:$F$80,I$12)) -> 1139.5268 | ... AK22: =INDEX(Annahmen!$B$94:$F$94,AK$12)+(AK$7-INDEX(Annahmen!$B$80:$F$80,AK$12))*(INDEX(Annahmen!$B$94:$F$94,AK$12+1)-INDEX(Annahmen!$B$94:$F$94,AK$12))/(INDEX(Annahmen!$B$80:$F$80,AK$12+1)-INDEX(Annahmen!$B$80:$F$80,AK$12)) -> 2393.3333
A23: Betrieb (ohne Altersprüfung) | B23: =INDEX(Annahmen!$B$95:$F$95,B$12)+(B$7-INDEX(Annahmen!$B$80:$F$80,B$12))*(INDEX(Annahmen!$B$95:$F$95,B$12+1)-INDEX(Annahmen!$B$95:$F$95,B$12))/(INDEX(Annahmen!$B$80:$F$80,B$12+1)-INDEX(Annahmen!$B$80:$F$80,B$12)) -> 270 | C23: =INDEX(Annahmen!$B$95:$F$95,C$12)+(C$7-INDEX(Annahmen!$B$80:$F$80,C$12))*(INDEX(Annahmen!$B$95:$F$95,C$12+1)-INDEX(Annahmen!$B$95:$F$95,C$12))/(INDEX(Annahmen!$B$80:$F$80,C$12+1)-INDEX(Annahmen!$B$80:$F$80,C$12)) -> 276.30299 | D23: =INDEX(Annahmen!$B$95:$F$95,D$12)+(D$7-INDEX(Annahmen!$B$80:$F$80,D$12))*(INDEX(Annahmen!$B$95:$F$95,D$12+1)-INDEX(Annahmen!$B$95:$F$95,D$12))/(INDEX(Annahmen!$B$80:$F$80,D$12+1)-INDEX(Annahmen!$B$80:$F$80,D$12)) -> 284.48047 | E23: =INDEX(Annahmen!$B$95:$F$95,E$12)+(E$7-INDEX(Annahmen!$B$80:$F$80,E$12))*(INDEX(Annahmen!$B$95:$F$95,E$12+1)-INDEX(Annahmen!$B$95:$F$95,E$12))/(INDEX(Annahmen!$B$80:$F$80,E$12+1)-INDEX(Annahmen!$B$80:$F$80,E$12)) -> 293.5555 | F23: =INDEX(Annahmen!$B$95:$F$95,F$12)+(F$7-INDEX(Annahmen!$B$80:$F$80,F$12))*(INDEX(Annahmen!$B$95:$F$95,F$12+1)-INDEX(Annahmen!$B$95:$F$95,F$12))/(INDEX(Annahmen!$B$80:$F$80,F$12+1)-INDEX(Annahmen!$B$80:$F$80,F$12)) -> 303.26739 | G23: =INDEX(Annahmen!$B$95:$F$95,G$12)+(G$7-INDEX(Annahmen!$B$80:$F$80,G$12))*(INDEX(Annahmen!$B$95:$F$95,G$12+1)-INDEX(Annahmen!$B$95:$F$95,G$12))/(INDEX(Annahmen!$B$80:$F$80,G$12+1)-INDEX(Annahmen!$B$80:$F$80,G$12)) -> 313.48213 | H23: =INDEX(Annahmen!$B$95:$F$95,H$12)+(H$7-INDEX(Annahmen!$B$80:$F$80,H$12))*(INDEX(Annahmen!$B$95:$F$95,H$12+1)-INDEX(Annahmen!$B$95:$F$95,H$12))/(INDEX(Annahmen!$B$80:$F$80,H$12+1)-INDEX(Annahmen!$B$80:$F$80,H$12)) -> 324.11633 | I23: =INDEX(Annahmen!$B$95:$F$95,I$12)+(I$7-INDEX(Annahmen!$B$80:$F$80,I$12))*(INDEX(Annahmen!$B$95:$F$95,I$12+1)-INDEX(Annahmen!$B$95:$F$95,I$12))/(INDEX(Annahmen!$B$80:$F$80,I$12+1)-INDEX(Annahmen!$B$80:$F$80,I$12)) -> 335.11251 | ... AK23: =INDEX(Annahmen!$B$95:$F$95,AK$12)+(AK$7-INDEX(Annahmen!$B$80:$F$80,AK$12))*(INDEX(Annahmen!$B$95:$F$95,AK$12+1)-INDEX(Annahmen!$B$95:$F$95,AK$12))/(INDEX(Annahmen!$B$80:$F$80,AK$12+1)-INDEX(Annahmen!$B$80:$F$80,AK$12)) -> 936.66667
A24: Altersprüfung (Stufe 1 + Stufe 2) ⟵ Schalter | B24: =B9*Annahmen!$B$105+B9*Annahmen!$B$110*Annahmen!$B$111 -> 0 | C24: =C9*Annahmen!$B$105+C9*Annahmen!$B$110*Annahmen!$B$111 -> 137.29269 | D24: =D9*Annahmen!$B$105+D9*Annahmen!$B$110*Annahmen!$B$111 -> 187.10484 | E24: =E9*Annahmen!$B$105+E9*Annahmen!$B$110*Annahmen!$B$111 -> 218.30815 | F24: =F9*Annahmen!$B$105+F9*Annahmen!$B$110*Annahmen!$B$111 -> 245.11249 | G24: =G9*Annahmen!$B$105+G9*Annahmen!$B$110*Annahmen!$B$111 -> 269.90485 | H24: =H9*Annahmen!$B$105+H9*Annahmen!$B$110*Annahmen!$B$111 -> 293.59761 | I24: =I9*Annahmen!$B$105+I9*Annahmen!$B$110*Annahmen!$B$111 -> 316.63626 | ... AK24: =AK9*Annahmen!$B$105+AK9*Annahmen!$B$110*Annahmen!$B$111 -> 2200.6986
A25: SMS-Versand (Z-10) | B25: =B9*Annahmen!$B$146*Annahmen!$B$147*Annahmen!$B$148 -> 0 | C25: =C9*Annahmen!$B$146*Annahmen!$B$147*Annahmen!$B$148 -> 11.272452 | D25: =D9*Annahmen!$B$146*Annahmen!$B$147*Annahmen!$B$148 -> 15.362292 | E25: =E9*Annahmen!$B$146*Annahmen!$B$147*Annahmen!$B$148 -> 17.924248 | F25: =F9*Annahmen!$B$146*Annahmen!$B$147*Annahmen!$B$148 -> 20.125025 | G25: =G9*Annahmen!$B$146*Annahmen!$B$147*Annahmen!$B$148 -> 22.160609 | H25: =H9*Annahmen!$B$146*Annahmen!$B$147*Annahmen!$B$148 -> 24.105909 | I25: =I9*Annahmen!$B$146*Annahmen!$B$147*Annahmen!$B$148 -> 25.997504 | ... AK25: =AK9*Annahmen!$B$146*Annahmen!$B$147*Annahmen!$B$148 -> 180.68894
A26: Personal: Moderation | B26: =INDEX(Annahmen!$B$96:$F$96,B$12)+(B$7-INDEX(Annahmen!$B$80:$F$80,B$12))*(INDEX(Annahmen!$B$96:$F$96,B$12+1)-INDEX(Annahmen!$B$96:$F$96,B$12))/(INDEX(Annahmen!$B$80:$F$80,B$12+1)-INDEX(Annahmen!$B$80:$F$80,B$12)) -> 0 | C26: =INDEX(Annahmen!$B$96:$F$96,C$12)+(C$7-INDEX(Annahmen!$B$80:$F$80,C$12))*(INDEX(Annahmen!$B$96:$F$96,C$12+1)-INDEX(Annahmen!$B$96:$F$96,C$12))/(INDEX(Annahmen!$B$80:$F$80,C$12+1)-INDEX(Annahmen!$B$80:$F$80,C$12)) -> 0 | D26: =INDEX(Annahmen!$B$96:$F$96,D$12)+(D$7-INDEX(Annahmen!$B$80:$F$80,D$12))*(INDEX(Annahmen!$B$96:$F$96,D$12+1)-INDEX(Annahmen!$B$96:$F$96,D$12))/(INDEX(Annahmen!$B$80:$F$80,D$12+1)-INDEX(Annahmen!$B$80:$F$80,D$12)) -> 0 | E26: =INDEX(Annahmen!$B$96:$F$96,E$12)+(E$7-INDEX(Annahmen!$B$80:$F$80,E$12))*(INDEX(Annahmen!$B$96:$F$96,E$12+1)-INDEX(Annahmen!$B$96:$F$96,E$12))/(INDEX(Annahmen!$B$80:$F$80,E$12+1)-INDEX(Annahmen!$B$80:$F$80,E$12)) -> 0 | F26: =INDEX(Annahmen!$B$96:$F$96,F$12)+(F$7-INDEX(Annahmen!$B$80:$F$80,F$12))*(INDEX(Annahmen!$B$96:$F$96,F$12+1)-INDEX(Annahmen!$B$96:$F$96,F$12))/(INDEX(Annahmen!$B$80:$F$80,F$12+1)-INDEX(Annahmen!$B$80:$F$80,F$12)) -> 0 | G26: =INDEX(Annahmen!$B$96:$F$96,G$12)+(G$7-INDEX(Annahmen!$B$80:$F$80,G$12))*(INDEX(Annahmen!$B$96:$F$96,G$12+1)-INDEX(Annahmen!$B$96:$F$96,G$12))/(INDEX(Annahmen!$B$80:$F$80,G$12+1)-INDEX(Annahmen!$B$80:$F$80,G$12)) -> 0 | H26: =INDEX(Annahmen!$B$96:$F$96,H$12)+(H$7-INDEX(Annahmen!$B$80:$F$80,H$12))*(INDEX(Annahmen!$B$96:$F$96,H$12+1)-INDEX(Annahmen!$B$96:$F$96,H$12))/(INDEX(Annahmen!$B$80:$F$80,H$12+1)-INDEX(Annahmen!$B$80:$F$80,H$12)) -> 0 | I26: =INDEX(Annahmen!$B$96:$F$96,I$12)+(I$7-INDEX(Annahmen!$B$80:$F$80,I$12))*(INDEX(Annahmen!$B$96:$F$96,I$12+1)-INDEX(Annahmen!$B$96:$F$96,I$12))/(INDEX(Annahmen!$B$80:$F$80,I$12+1)-INDEX(Annahmen!$B$80:$F$80,I$12)) -> 0 | ... AK26: =INDEX(Annahmen!$B$96:$F$96,AK$12)+(AK$7-INDEX(Annahmen!$B$80:$F$80,AK$12))*(INDEX(Annahmen!$B$96:$F$96,AK$12+1)-INDEX(Annahmen!$B$96:$F$96,AK$12))/(INDEX(Annahmen!$B$80:$F$80,AK$12+1)-INDEX(Annahmen!$B$80:$F$80,AK$12)) -> 2266.6667
A27: Marketing (Barmittel) | B27: =INDEX(Annahmen!$B$97:$F$97,B$12)+(B$7-INDEX(Annahmen!$B$80:$F$80,B$12))*(INDEX(Annahmen!$B$97:$F$97,B$12+1)-INDEX(Annahmen!$B$97:$F$97,B$12))/(INDEX(Annahmen!$B$80:$F$80,B$12+1)-INDEX(Annahmen!$B$80:$F$80,B$12)) -> 150 | C27: =INDEX(Annahmen!$B$97:$F$97,C$12)+(C$7-INDEX(Annahmen!$B$80:$F$80,C$12))*(INDEX(Annahmen!$B$97:$F$97,C$12+1)-INDEX(Annahmen!$B$97:$F$97,C$12))/(INDEX(Annahmen!$B$80:$F$80,C$12+1)-INDEX(Annahmen!$B$80:$F$80,C$12)) -> 154.50214 | D27: =INDEX(Annahmen!$B$97:$F$97,D$12)+(D$7-INDEX(Annahmen!$B$80:$F$80,D$12))*(INDEX(Annahmen!$B$97:$F$97,D$12+1)-INDEX(Annahmen!$B$97:$F$97,D$12))/(INDEX(Annahmen!$B$80:$F$80,D$12+1)-INDEX(Annahmen!$B$80:$F$80,D$12)) -> 160.3432 | E27: =INDEX(Annahmen!$B$97:$F$97,E$12)+(E$7-INDEX(Annahmen!$B$80:$F$80,E$12))*(INDEX(Annahmen!$B$97:$F$97,E$12+1)-INDEX(Annahmen!$B$97:$F$97,E$12))/(INDEX(Annahmen!$B$80:$F$80,E$12+1)-INDEX(Annahmen!$B$80:$F$80,E$12)) -> 166.82536 | F27: =INDEX(Annahmen!$B$97:$F$97,F$12)+(F$7-INDEX(Annahmen!$B$80:$F$80,F$12))*(INDEX(Annahmen!$B$97:$F$97,F$12+1)-INDEX(Annahmen!$B$97:$F$97,F$12))/(INDEX(Annahmen!$B$80:$F$80,F$12+1)-INDEX(Annahmen!$B$80:$F$80,F$12)) -> 173.76242 | G27: =INDEX(Annahmen!$B$97:$F$97,G$12)+(G$7-INDEX(Annahmen!$B$80:$F$80,G$12))*(INDEX(Annahmen!$B$97:$F$97,G$12+1)-INDEX(Annahmen!$B$97:$F$97,G$12))/(INDEX(Annahmen!$B$80:$F$80,G$12+1)-INDEX(Annahmen!$B$80:$F$80,G$12)) -> 181.05866 | H27: =INDEX(Annahmen!$B$97:$F$97,H$12)+(H$7-INDEX(Annahmen!$B$80:$F$80,H$12))*(INDEX(Annahmen!$B$97:$F$97,H$12+1)-INDEX(Annahmen!$B$97:$F$97,H$12))/(INDEX(Annahmen!$B$80:$F$80,H$12+1)-INDEX(Annahmen!$B$80:$F$80,H$12)) -> 188.65452 | I27: =INDEX(Annahmen!$B$97:$F$97,I$12)+(I$7-INDEX(Annahmen!$B$80:$F$80,I$12))*(INDEX(Annahmen!$B$97:$F$97,I$12+1)-INDEX(Annahmen!$B$97:$F$97,I$12))/(INDEX(Annahmen!$B$80:$F$80,I$12+1)-INDEX(Annahmen!$B$80:$F$80,I$12)) -> 196.50894 | ... AK27: =INDEX(Annahmen!$B$97:$F$97,AK$12)+(AK$7-INDEX(Annahmen!$B$80:$F$80,AK$12))*(INDEX(Annahmen!$B$97:$F$97,AK$12+1)-INDEX(Annahmen!$B$97:$F$97,AK$12))/(INDEX(Annahmen!$B$80:$F$80,AK$12+1)-INDEX(Annahmen!$B$80:$F$80,AK$12)) -> 800
A28: Eigene Veranstaltungen (Nr. 74) | B28: =IF(B5>=Annahmen!$B$145,B8*Annahmen!$B$144/12,0) -> 166.66667 | C28: =IF(C5>=Annahmen!$B$145,C8*Annahmen!$B$144/12,0) -> 166.66667 | D28: =IF(D5>=Annahmen!$B$145,D8*Annahmen!$B$144/12,0) -> 166.66667 | E28: =IF(E5>=Annahmen!$B$145,E8*Annahmen!$B$144/12,0) -> 166.66667 | F28: =IF(F5>=Annahmen!$B$145,F8*Annahmen!$B$144/12,0) -> 166.66667 | G28: =IF(G5>=Annahmen!$B$145,G8*Annahmen!$B$144/12,0) -> 166.66667 | H28: =IF(H5>=Annahmen!$B$145,H8*Annahmen!$B$144/12,0) -> 166.66667 | I28: =IF(I5>=Annahmen!$B$145,I8*Annahmen!$B$144/12,0) -> 166.66667 | ... AK28: =IF(AK5>=Annahmen!$B$145,AK8*Annahmen!$B$144/12,0) -> 333.33333
A29: CSD-Auftritte (zum Start und Folgejahre) | B29: =IF(B5=Annahmen!$B$136,Annahmen!$B$135,0)+IF(B5=Annahmen!$B$138,Annahmen!$B$137,0)+IF(B5=Annahmen!$B$140,Annahmen!$B$139,0) -> 10000 | C29: =IF(C5=Annahmen!$B$136,Annahmen!$B$135,0)+IF(C5=Annahmen!$B$138,Annahmen!$B$137,0)+IF(C5=Annahmen!$B$140,Annahmen!$B$139,0) -> 0 | D29: =IF(D5=Annahmen!$B$136,Annahmen!$B$135,0)+IF(D5=Annahmen!$B$138,Annahmen!$B$137,0)+IF(D5=Annahmen!$B$140,Annahmen!$B$139,0) -> 0 | E29: =IF(E5=Annahmen!$B$136,Annahmen!$B$135,0)+IF(E5=Annahmen!$B$138,Annahmen!$B$137,0)+IF(E5=Annahmen!$B$140,Annahmen!$B$139,0) -> 0 | F29: =IF(F5=Annahmen!$B$136,Annahmen!$B$135,0)+IF(F5=Annahmen!$B$138,Annahmen!$B$137,0)+IF(F5=Annahmen!$B$140,Annahmen!$B$139,0) -> 0 | G29: =IF(G5=Annahmen!$B$136,Annahmen!$B$135,0)+IF(G5=Annahmen!$B$138,Annahmen!$B$137,0)+IF(G5=Annahmen!$B$140,Annahmen!$B$139,0) -> 0 | H29: =IF(H5=Annahmen!$B$136,Annahmen!$B$135,0)+IF(H5=Annahmen!$B$138,Annahmen!$B$137,0)+IF(H5=Annahmen!$B$140,Annahmen!$B$139,0) -> 0 | I29: =IF(I5=Annahmen!$B$136,Annahmen!$B$135,0)+IF(I5=Annahmen!$B$138,Annahmen!$B$137,0)+IF(I5=Annahmen!$B$140,Annahmen!$B$139,0) -> 0 | ... AK29: =IF(AK5=Annahmen!$B$136,Annahmen!$B$135,0)+IF(AK5=Annahmen!$B$138,Annahmen!$B$137,0)+IF(AK5=Annahmen!$B$140,Annahmen!$B$139,0) -> 0
A30: Einmalkosten | B30: =SUMIF(Annahmen!$C$116:$C$129,B5,Annahmen!$B$116:$B$129) -> 26700 | C30: =SUMIF(Annahmen!$C$116:$C$129,C5,Annahmen!$B$116:$B$129) -> 2700 | D30: =SUMIF(Annahmen!$C$116:$C$129,D5,Annahmen!$B$116:$B$129) -> 11500 | E30: =SUMIF(Annahmen!$C$116:$C$129,E5,Annahmen!$B$116:$B$129) -> 4500 | F30: =SUMIF(Annahmen!$C$116:$C$129,F5,Annahmen!$B$116:$B$129) -> 3000 | G30: =SUMIF(Annahmen!$C$116:$C$129,G5,Annahmen!$B$116:$B$129) -> 2000 | H30: =SUMIF(Annahmen!$C$116:$C$129,H5,Annahmen!$B$116:$B$129) -> 0 | I30: =SUMIF(Annahmen!$C$116:$C$129,I5,Annahmen!$B$116:$B$129) -> 5500 | ... AK30: =SUMIF(Annahmen!$C$116:$C$129,AK5,Annahmen!$B$116:$B$129) -> 0
A31: Kosten gesamt | B31: =SUM(B22:B30) -> 38286.667 | C31: =SUM(C22:C30) -> 4459.5433 | D31: =SUM(D22:D30) -> 13344.987 | E31: =SUM(E22:E30) -> 6413.756 | F31: =SUM(F22:F30) -> 4980.2213 | G31: =SUM(G22:G30) -> 4046.4489 | H31: =SUM(H22:H30) -> 2113.1046 | I31: =SUM(I22:I30) -> 7680.4487 | ... AK31: =SUM(AK22:AK30) -> 9111.3875
A33: Ergebnis je Monat | B33: =B19-B31 -> -38286.667 | C33: =C19-C31 -> -4459.5433 | D33: =D19-D31 -> -13344.987 | E33: =E19-E31 -> -6413.756 | F33: =F19-F31 -> -4980.2213 | G33: =G19-G31 -> -4046.4489 | H33: =H19-H31 -> -2113.1046 | I33: =I19-I31 -> -7680.4487 | ... AK33: =AK19-AK31 -> -2387.3983
A34: Kumulierte Liquidität | B34: =B33 -> -38286.667 | C34: =B34+C33 -> -42746.21 | D34: =C34+D33 -> -56091.197 | E34: =D34+E33 -> -62504.953 | F34: =E34+F33 -> -67485.174 | G34: =F34+G33 -> -71531.623 | H34: =G34+H33 -> -73644.728 | I34: =H34+I33 -> -81325.177 | J34: =I34+J33 -> -83573.764 | ... AK34: =AJ34+AK33 -> -145217.21
A36: nachrichtlich: Krankenversicherung privat, kumuliert | B36: =Annahmen!$B$154*Annahmen!$B$155 -> 400 | C36: =B36+Annahmen!$B$154*Annahmen!$B$155 -> 800 | D36: =C36+Annahmen!$B$154*Annahmen!$B$155 -> 1200 | E36: =D36+Annahmen!$B$154*Annahmen!$B$155 -> 1600 | F36: =E36+Annahmen!$B$154*Annahmen!$B$155 -> 2000 | G36: =F36+Annahmen!$B$154*Annahmen!$B$155 -> 2400 | H36: =G36+Annahmen!$B$154*Annahmen!$B$155 -> 2800 | I36: =H36+Annahmen!$B$154*Annahmen!$B$155 -> 3200 | J36: =I36+Annahmen!$B$154*Annahmen!$B$155 -> 3600 | ... AK36: =AJ36+Annahmen!$B$154*Annahmen!$B$155 -> 14400
A37: nachrichtlich: Lebenshaltung beider Gründer, kumuliert | B37: =Annahmen!$B$156*Annahmen!$B$155 -> 2200 | C37: =B37+Annahmen!$B$156*Annahmen!$B$155 -> 4400 | D37: =C37+Annahmen!$B$156*Annahmen!$B$155 -> 6600 | E37: =D37+Annahmen!$B$156*Annahmen!$B$155 -> 8800 | F37: =E37+Annahmen!$B$156*Annahmen!$B$155 -> 11000 | G37: =F37+Annahmen!$B$156*Annahmen!$B$155 -> 13200 | H37: =G37+Annahmen!$B$156*Annahmen!$B$155 -> 15400 | I37: =H37+Annahmen!$B$156*Annahmen!$B$155 -> 17600 | J37: =I37+Annahmen!$B$156*Annahmen!$B$155 -> 19800 | ... AK37: =AJ37+Annahmen!$B$156*Annahmen!$B$155 -> 79200
A39: Jahressummen (rechnen sich)
A40: Größe | B40: Jahr 1 | C40: Jahr 2 | D40: Jahr 3 | E40: 36 Monate
A41: MAU im Jahresmittel | B41: =AVERAGE(B7:M7) -> 1835.3359 | C41: =AVERAGE(N7:Y7) -> 8696.7502 | D41: =AVERAGE(Z7:AK7) -> 21514.8 | E41: =AVERAGE(B7:AK7) -> 10682.296
A42: Zahlende Nutzer im Mittel | B42: =AVERAGE(B11:M11) -> 0 | C42: =AVERAGE(N11:Y11) -> 125.23178 | D42: =AVERAGE(Z11:AK11) -> 473.32561 | E42: =AVERAGE(B11:AK11) -> 199.51913
A43: Erlöse gesamt | B43: =SUM(B19:M19) -> 0 | C43: =SUM(N19:Y19) -> 17270.137 | D43: =SUM(Z19:AK19) -> 59922.828 | E43: =SUM(B19:AK19) -> 77192.965
A44: Kosten gesamt | B44: =SUM(B31:M31) -> 90736.705 | C44: =SUM(N31:Y31) -> 42736.239 | D44: =SUM(Z31:AK31) -> 88937.234 | E44: =SUM(B31:AK31) -> 222410.18
A45: Ergebnis | B45: =SUM(B33:M33) -> -90736.705 | C45: =SUM(N33:Y33) -> -25466.103 | D45: =SUM(Z33:AK33) -> -29014.406 | E45: =SUM(B33:AK33) -> -145217.21

Sheet Realistisch
A1: Szenario B — Realistisch
A2: 36 Monate ab T0 — dem Start in der CSD-Saison; geplant wird ein Jahr nach dem Bestfall Sommer 2028 (Nr. 45). Alles rechnet sich aus dem Blatt „Annahmen“. Kein Gründergehalt in keinem Monat.
A4: Position | B4: M1 | C4: M2 | D4: M3 | E4: M4 | F4: M5 | G4: M6 | H4: M7 | I4: M8 | J4: M9 | K4: M10 | L4: M11 | M4: M12 | N4: M13 | O4: M14 | P4: M15 | Q4: M16 | R4: M17 | S4: M18 | T4: M19 | U4: M20 | V4: M21 | W4: M22 | X4: M23 | Y4: M24 | Z4: M25 | AA4: M26 | AB4: M27 | AC4: M28 | AD4: M29 | AE4: M30 | AF4: M31 | AG4: M32 | AH4: M33 | AI4: M34 | AJ4: M35 | AK4: M36
A5: Monat | B5: 1 | C5: 2 | D5: 3 | E5: 4 | F5: 5 | G5: 6 | H5: 7 | I5: 8 | J5: 9 | K5: 10 | L5: 11 | M5: 12 | N5: 13 | O5: 14 | P5: 15 | Q5: 16 | R5: 17 | S5: 18 | T5: 19 | U5: 20 | V5: 21 | W5: 22 | X5: 23 | Y5: 24 | Z5: 25 | AA5: 26 | AB5: 27 | AC5: 28 | AD5: 29 | AE5: 30 | AF5: 31 | AG5: 32 | AH5: 33 | AI5: 34 | AJ5: 35 | AK5: 36
A6: Jahr | B6: =ROUNDUP(B5/12,0) -> 1 | C6: =ROUNDUP(C5/12,0) -> 1 | D6: =ROUNDUP(D5/12,0) -> 1 | E6: =ROUNDUP(E5/12,0) -> 1 | F6: =ROUNDUP(F5/12,0) -> 1 | G6: =ROUNDUP(G5/12,0) -> 1 | H6: =ROUNDUP(H5/12,0) -> 1 | I6: =ROUNDUP(I5/12,0) -> 1 | ... AK6: =ROUNDUP(AK5/12,0) -> 3
A7: Aktive Nutzer im Monat (MAU) | B7: =IF(B5<Annahmen!$C$9,0,IF(B5<=12,Annahmen!$C$6*((B5-Annahmen!$C$9+1)/(12-Annahmen!$C$9+1))^Annahmen!$C$10,IF(B5<=24,Annahmen!$C$6+(Annahmen!$C$7-Annahmen!$C$6)*((B5-12)/12)^Annahmen!$C$11,Annahmen!$C$7+(Annahmen!$C$8-Annahmen!$C$7)*((B5-24)/12)^Annahmen!$C$11))) -> 0 | C7: =IF(C5<Annahmen!$C$9,0,IF(C5<=12,Annahmen!$C$6*((C5-Annahmen!$C$9+1)/(12-Annahmen!$C$9+1))^Annahmen!$C$10,IF(C5<=24,Annahmen!$C$6+(Annahmen!$C$7-Annahmen!$C$6)*((C5-12)/12)^Annahmen!$C$11,Annahmen!$C$7+(Annahmen!$C$8-Annahmen!$C$7)*((C5-24)/12)^Annahmen!$C$11))) -> 274.11914 | D7: =IF(D5<Annahmen!$C$9,0,IF(D5<=12,Annahmen!$C$6*((D5-Annahmen!$C$9+1)/(12-Annahmen!$C$9+1))^Annahmen!$C$10,IF(D5<=24,Annahmen!$C$6+(Annahmen!$C$7-Annahmen!$C$6)*((D5-12)/12)^Annahmen!$C$11,Annahmen!$C$7+(Annahmen!$C$8-Annahmen!$C$7)*((D5-24)/12)^Annahmen!$C$11))) -> 713.44542 | E7: =IF(E5<Annahmen!$C$9,0,IF(E5<=12,Annahmen!$C$6*((E5-Annahmen!$C$9+1)/(12-Annahmen!$C$9+1))^Annahmen!$C$10,IF(E5<=24,Annahmen!$C$6+(Annahmen!$C$7-Annahmen!$C$6)*((E5-12)/12)^Annahmen!$C$11,Annahmen!$C$7+(Annahmen!$C$8-Annahmen!$C$7)*((E5-24)/12)^Annahmen!$C$11))) -> 1248.4372 | F7: =IF(F5<Annahmen!$C$9,0,IF(F5<=12,Annahmen!$C$6*((F5-Annahmen!$C$9+1)/(12-Annahmen!$C$9+1))^Annahmen!$C$10,IF(F5<=24,Annahmen!$C$6+(Annahmen!$C$7-Annahmen!$C$6)*((F5-12)/12)^Annahmen!$C$11,Annahmen!$C$7+(Annahmen!$C$8-Annahmen!$C$7)*((F5-24)/12)^Annahmen!$C$11))) -> 1856.8728 | G7: =IF(G5<Annahmen!$C$9,0,IF(G5<=12,Annahmen!$C$6*((G5-Annahmen!$C$9+1)/(12-Annahmen!$C$9+1))^Annahmen!$C$10,IF(G5<=24,Annahmen!$C$6+(Annahmen!$C$7-Annahmen!$C$6)*((G5-12)/12)^Annahmen!$C$11,Annahmen!$C$7+(Annahmen!$C$8-Annahmen!$C$7)*((G5-24)/12)^Annahmen!$C$11))) -> 2526.4922 | H7: =IF(H5<Annahmen!$C$9,0,IF(H5<=12,Annahmen!$C$6*((H5-Annahmen!$C$9+1)/(12-Annahmen!$C$9+1))^Annahmen!$C$10,IF(H5<=24,Annahmen!$C$6+(Annahmen!$C$7-Annahmen!$C$6)*((H5-12)/12)^Annahmen!$C$11,Annahmen!$C$7+(Annahmen!$C$8-Annahmen!$C$7)*((H5-24)/12)^Annahmen!$C$11))) -> 3249.2871 | I7: =IF(I5<Annahmen!$C$9,0,IF(I5<=12,Annahmen!$C$6*((I5-Annahmen!$C$9+1)/(12-Annahmen!$C$9+1))^Annahmen!$C$10,IF(I5<=24,Annahmen!$C$6+(Annahmen!$C$7-Annahmen!$C$6)*((I5-12)/12)^Annahmen!$C$11,Annahmen!$C$7+(Annahmen!$C$8-Annahmen!$C$7)*((I5-24)/12)^Annahmen!$C$11))) -> 4019.5242 | ... AK7: =IF(AK5<Annahmen!$C$9,0,IF(AK5<=12,Annahmen!$C$6*((AK5-Annahmen!$C$9+1)/(12-Annahmen!$C$9+1))^Annahmen!$C$10,IF(AK5<=24,Annahmen!$C$6+(Annahmen!$C$7-Annahmen!$C$6)*((AK5-12)/12)^Annahmen!$C$11,Annahmen!$C$7+(Annahmen!$C$8-Annahmen!$C$7)*((AK5-24)/12)^Annahmen!$C$11))) -> 62000
A8: Städte | B8: =IF(B5<=12,Annahmen!$C$12,IF(B5<=24,Annahmen!$C$13,Annahmen!$C$14)) -> 1 | C8: =IF(C5<=12,Annahmen!$C$12,IF(C5<=24,Annahmen!$C$13,Annahmen!$C$14)) -> 1 | D8: =IF(D5<=12,Annahmen!$C$12,IF(D5<=24,Annahmen!$C$13,Annahmen!$C$14)) -> 1 | E8: =IF(E5<=12,Annahmen!$C$12,IF(E5<=24,Annahmen!$C$13,Annahmen!$C$14)) -> 1 | F8: =IF(F5<=12,Annahmen!$C$12,IF(F5<=24,Annahmen!$C$13,Annahmen!$C$14)) -> 1 | G8: =IF(G5<=12,Annahmen!$C$12,IF(G5<=24,Annahmen!$C$13,Annahmen!$C$14)) -> 1 | H8: =IF(H5<=12,Annahmen!$C$12,IF(H5<=24,Annahmen!$C$13,Annahmen!$C$14)) -> 1 | I8: =IF(I5<=12,Annahmen!$C$12,IF(I5<=24,Annahmen!$C$13,Annahmen!$C$14)) -> 1 | ... AK8: =IF(AK5<=12,Annahmen!$C$12,IF(AK5<=24,Annahmen!$C$13,Annahmen!$C$14)) -> 4
A9: Neuregistrierungen (Treiber der Prüfkosten) | B9: =MAX(0,B7-0)+B7*Annahmen!$C$15*(1-Annahmen!$C$16) -> 0 | C9: =MAX(0,C7-B7)+C7*Annahmen!$C$15*(1-Annahmen!$C$16) -> 289.46981 | D9: =MAX(0,D7-C7)+D7*Annahmen!$C$15*(1-Annahmen!$C$16) -> 479.27922 | E9: =MAX(0,E7-D7)+E7*Annahmen!$C$15*(1-Annahmen!$C$16) -> 604.90423 | F9: =MAX(0,F7-E7)+F7*Annahmen!$C$15*(1-Annahmen!$C$16) -> 712.42047 | G9: =MAX(0,G7-F7)+G7*Annahmen!$C$15*(1-Annahmen!$C$16) -> 811.10301 | H9: =MAX(0,H7-G7)+H7*Annahmen!$C$15*(1-Annahmen!$C$16) -> 904.75494 | I9: =MAX(0,I7-H7)+I7*Annahmen!$C$15*(1-Annahmen!$C$16) -> 995.33053 | J9: =MAX(0,J7-I7)+J7*Annahmen!$C$15*(1-Annahmen!$C$16) -> 1083.968 | ... AK9: =MAX(0,AK7-AJ7)+AK7*Annahmen!$C$15*(1-Annahmen!$C$16) -> 7477.0632
A10: Konversion zu Zahlern | B10: =IF(B5<Annahmen!$C$22,0,Annahmen!$C$23*(Annahmen!$C$24+(1-Annahmen!$C$24)*MIN(1,(B5-Annahmen!$C$22+1)/Annahmen!$C$25))) -> 0 | C10: =IF(C5<Annahmen!$C$22,0,Annahmen!$C$23*(Annahmen!$C$24+(1-Annahmen!$C$24)*MIN(1,(C5-Annahmen!$C$22+1)/Annahmen!$C$25))) -> 0 | D10: =IF(D5<Annahmen!$C$22,0,Annahmen!$C$23*(Annahmen!$C$24+(1-Annahmen!$C$24)*MIN(1,(D5-Annahmen!$C$22+1)/Annahmen!$C$25))) -> 0 | E10: =IF(E5<Annahmen!$C$22,0,Annahmen!$C$23*(Annahmen!$C$24+(1-Annahmen!$C$24)*MIN(1,(E5-Annahmen!$C$22+1)/Annahmen!$C$25))) -> 0 | F10: =IF(F5<Annahmen!$C$22,0,Annahmen!$C$23*(Annahmen!$C$24+(1-Annahmen!$C$24)*MIN(1,(F5-Annahmen!$C$22+1)/Annahmen!$C$25))) -> 0 | G10: =IF(G5<Annahmen!$C$22,0,Annahmen!$C$23*(Annahmen!$C$24+(1-Annahmen!$C$24)*MIN(1,(G5-Annahmen!$C$22+1)/Annahmen!$C$25))) -> 0 | H10: =IF(H5<Annahmen!$C$22,0,Annahmen!$C$23*(Annahmen!$C$24+(1-Annahmen!$C$24)*MIN(1,(H5-Annahmen!$C$22+1)/Annahmen!$C$25))) -> 0 | I10: =IF(I5<Annahmen!$C$22,0,Annahmen!$C$23*(Annahmen!$C$24+(1-Annahmen!$C$24)*MIN(1,(I5-Annahmen!$C$22+1)/Annahmen!$C$25))) -> 0 | ... AK10: =IF(AK5<Annahmen!$C$22,0,Annahmen!$C$23*(Annahmen!$C$24+(1-Annahmen!$C$24)*MIN(1,(AK5-Annahmen!$C$22+1)/Annahmen!$C$25))) -> 0.036
A11: Zahlende Nutzer | B11: =B7*B10 -> 0 | C11: =C7*C10 -> 0 | D11: =D7*D10 -> 0 | E11: =E7*E10 -> 0 | F11: =F7*F10 -> 0 | G11: =G7*G10 -> 0 | H11: =H7*H10 -> 0 | I11: =I7*I10 -> 0 | ... AK11: =AK7*AK10 -> 2232
A12: Staffel-Stützstelle (Hilfsgröße) | B12: =MIN(MATCH(B7,Annahmen!$B$80:$F$80,1),4) -> 1 | C12: =MIN(MATCH(C7,Annahmen!$B$80:$F$80,1),4) -> 1 | D12: =MIN(MATCH(D7,Annahmen!$B$80:$F$80,1),4) -> 1 | E12: =MIN(MATCH(E7,Annahmen!$B$80:$F$80,1),4) -> 1 | F12: =MIN(MATCH(F7,Annahmen!$B$80:$F$80,1),4) -> 1 | G12: =MIN(MATCH(G7,Annahmen!$B$80:$F$80,1),4) -> 1 | H12: =MIN(MATCH(H7,Annahmen!$B$80:$F$80,1),4) -> 1 | I12: =MIN(MATCH(I7,Annahmen!$B$80:$F$80,1),4) -> 1 | ... AK12: =MIN(MATCH(AK7,Annahmen!$B$80:$F$80,1),4) -> 4
A13: ERLÖSE — fünf Quellen (Handbuch B, nach Nr. 65 und 74 neu geschnitten)
A14: Abonnements | B14: =B11*Annahmen!$C$26 -> 0 | C14: =C11*Annahmen!$C$26 -> 0 | D14: =D11*Annahmen!$C$26 -> 0 | E14: =E11*Annahmen!$C$26 -> 0 | F14: =F11*Annahmen!$C$26 -> 0 | G14: =G11*Annahmen!$C$26 -> 0 | H14: =H11*Annahmen!$C$26 -> 0 | I14: =I11*Annahmen!$C$26 -> 0 | ... AK14: =AK11*Annahmen!$C$26 -> 16872.531
A15: Werkzeugabo für Orte und Veranstalter | B15: =IF(AND(B5>=Annahmen!$C$62,B7>=Annahmen!$C$63),B8*Annahmen!$C$64*Annahmen!$C$65,0) -> 0 | C15: =IF(AND(C5>=Annahmen!$C$62,C7>=Annahmen!$C$63),C8*Annahmen!$C$64*Annahmen!$C$65,0) -> 0 | D15: =IF(AND(D5>=Annahmen!$C$62,D7>=Annahmen!$C$63),D8*Annahmen!$C$64*Annahmen!$C$65,0) -> 0 | E15: =IF(AND(E5>=Annahmen!$C$62,E7>=Annahmen!$C$63),E8*Annahmen!$C$64*Annahmen!$C$65,0) -> 0 | F15: =IF(AND(F5>=Annahmen!$C$62,F7>=Annahmen!$C$63),F8*Annahmen!$C$64*Annahmen!$C$65,0) -> 0 | G15: =IF(AND(G5>=Annahmen!$C$62,G7>=Annahmen!$C$63),G8*Annahmen!$C$64*Annahmen!$C$65,0) -> 0 | H15: =IF(AND(H5>=Annahmen!$C$62,H7>=Annahmen!$C$63),H8*Annahmen!$C$64*Annahmen!$C$65,0) -> 0 | I15: =IF(AND(I5>=Annahmen!$C$62,I7>=Annahmen!$C$63),I8*Annahmen!$C$64*Annahmen!$C$65,0) -> 0 | ... AK15: =IF(AND(AK5>=Annahmen!$C$62,AK7>=Annahmen!$C$63),AK8*Annahmen!$C$64*Annahmen!$C$65,0) -> 580
A16: Veranstaltungen: Anteil an Tickets | B16: =IF(AND(B5>=Annahmen!$C$66,B7>=Annahmen!$C$67),B8*Annahmen!$C$68*Annahmen!$C$69*Annahmen!$C$70*Annahmen!$C$71,0) -> 0 | C16: =IF(AND(C5>=Annahmen!$C$66,C7>=Annahmen!$C$67),C8*Annahmen!$C$68*Annahmen!$C$69*Annahmen!$C$70*Annahmen!$C$71,0) -> 0 | D16: =IF(AND(D5>=Annahmen!$C$66,D7>=Annahmen!$C$67),D8*Annahmen!$C$68*Annahmen!$C$69*Annahmen!$C$70*Annahmen!$C$71,0) -> 0 | E16: =IF(AND(E5>=Annahmen!$C$66,E7>=Annahmen!$C$67),E8*Annahmen!$C$68*Annahmen!$C$69*Annahmen!$C$70*Annahmen!$C$71,0) -> 0 | F16: =IF(AND(F5>=Annahmen!$C$66,F7>=Annahmen!$C$67),F8*Annahmen!$C$68*Annahmen!$C$69*Annahmen!$C$70*Annahmen!$C$71,0) -> 0 | G16: =IF(AND(G5>=Annahmen!$C$66,G7>=Annahmen!$C$67),G8*Annahmen!$C$68*Annahmen!$C$69*Annahmen!$C$70*Annahmen!$C$71,0) -> 0 | H16: =IF(AND(H5>=Annahmen!$C$66,H7>=Annahmen!$C$67),H8*Annahmen!$C$68*Annahmen!$C$69*Annahmen!$C$70*Annahmen!$C$71,0) -> 0 | I16: =IF(AND(I5>=Annahmen!$C$66,I7>=Annahmen!$C$67),I8*Annahmen!$C$68*Annahmen!$C$69*Annahmen!$C$70*Annahmen!$C$71,0) -> 0 | ... AK16: =IF(AND(AK5>=Annahmen!$C$66,AK7>=Annahmen!$C$67),AK8*Annahmen!$C$68*Annahmen!$C$69*Annahmen!$C$70*Annahmen!$C$71,0) -> 921.6
A17: Unterstützerbeiträge | B17: =IF(B5>=Annahmen!$C$72,B7*Annahmen!$C$73,0) -> 0 | C17: =IF(C5>=Annahmen!$C$72,C7*Annahmen!$C$73,0) -> 0 | D17: =IF(D5>=Annahmen!$C$72,D7*Annahmen!$C$73,0) -> 0 | E17: =IF(E5>=Annahmen!$C$72,E7*Annahmen!$C$73,0) -> 0 | F17: =IF(F5>=Annahmen!$C$72,F7*Annahmen!$C$73,0) -> 0 | G17: =IF(G5>=Annahmen!$C$72,G7*Annahmen!$C$73,0) -> 0 | H17: =IF(H5>=Annahmen!$C$72,H7*Annahmen!$C$73,0) -> 0 | I17: =IF(I5>=Annahmen!$C$72,I7*Annahmen!$C$73,0) -> 0 | ... AK17: =IF(AK5>=Annahmen!$C$72,AK7*Annahmen!$C$73,0) -> 930
A18: Gesundheitspartnerschaft | B18: =IF(B5>=Annahmen!$C$74,B8*Annahmen!$C$75,0) -> 0 | C18: =IF(C5>=Annahmen!$C$74,C8*Annahmen!$C$75,0) -> 0 | D18: =IF(D5>=Annahmen!$C$74,D8*Annahmen!$C$75,0) -> 0 | E18: =IF(E5>=Annahmen!$C$74,E8*Annahmen!$C$75,0) -> 0 | F18: =IF(F5>=Annahmen!$C$74,F8*Annahmen!$C$75,0) -> 0 | G18: =IF(G5>=Annahmen!$C$74,G8*Annahmen!$C$75,0) -> 0 | H18: =IF(H5>=Annahmen!$C$74,H8*Annahmen!$C$75,0) -> 0 | I18: =IF(I5>=Annahmen!$C$74,I8*Annahmen!$C$75,0) -> 0 | ... AK18: =IF(AK5>=Annahmen!$C$74,AK8*Annahmen!$C$75,0) -> 1068
A19: Erlöse gesamt | B19: =SUM(B14:B18) -> 0 | C19: =SUM(C14:C18) -> 0 | D19: =SUM(D14:D18) -> 0 | E19: =SUM(E14:E18) -> 0 | F19: =SUM(F14:F18) -> 0 | G19: =SUM(G14:G18) -> 0 | H19: =SUM(H14:H18) -> 0 | I19: =SUM(I14:I18) -> 0 | ... AK19: =SUM(AK14:AK18) -> 20372.131
A21: KOSTEN
A22: Pflichtpositionen (nicht kürzbar) | B22: =INDEX(Annahmen!$B$94:$F$94,B$12)+(B$7-INDEX(Annahmen!$B$80:$F$80,B$12))*(INDEX(Annahmen!$B$94:$F$94,B$12+1)-INDEX(Annahmen!$B$94:$F$94,B$12))/(INDEX(Annahmen!$B$80:$F$80,B$12+1)-INDEX(Annahmen!$B$80:$F$80,B$12)) -> 1000 | C22: =INDEX(Annahmen!$B$94:$F$94,C$12)+(C$7-INDEX(Annahmen!$B$80:$F$80,C$12))*(INDEX(Annahmen!$B$94:$F$94,C$12+1)-INDEX(Annahmen!$B$94:$F$94,C$12))/(INDEX(Annahmen!$B$80:$F$80,C$12+1)-INDEX(Annahmen!$B$80:$F$80,C$12)) -> 1016.4471 | D22: =INDEX(Annahmen!$B$94:$F$94,D$12)+(D$7-INDEX(Annahmen!$B$80:$F$80,D$12))*(INDEX(Annahmen!$B$94:$F$94,D$12+1)-INDEX(Annahmen!$B$94:$F$94,D$12))/(INDEX(Annahmen!$B$80:$F$80,D$12+1)-INDEX(Annahmen!$B$80:$F$80,D$12)) -> 1042.8067 | E22: =INDEX(Annahmen!$B$94:$F$94,E$12)+(E$7-INDEX(Annahmen!$B$80:$F$80,E$12))*(INDEX(Annahmen!$B$94:$F$94,E$12+1)-INDEX(Annahmen!$B$94:$F$94,E$12))/(INDEX(Annahmen!$B$80:$F$80,E$12+1)-INDEX(Annahmen!$B$80:$F$80,E$12)) -> 1074.9062 | F22: =INDEX(Annahmen!$B$94:$F$94,F$12)+(F$7-INDEX(Annahmen!$B$80:$F$80,F$12))*(INDEX(Annahmen!$B$94:$F$94,F$12+1)-INDEX(Annahmen!$B$94:$F$94,F$12))/(INDEX(Annahmen!$B$80:$F$80,F$12+1)-INDEX(Annahmen!$B$80:$F$80,F$12)) -> 1111.4124 | G22: =INDEX(Annahmen!$B$94:$F$94,G$12)+(G$7-INDEX(Annahmen!$B$80:$F$80,G$12))*(INDEX(Annahmen!$B$94:$F$94,G$12+1)-INDEX(Annahmen!$B$94:$F$94,G$12))/(INDEX(Annahmen!$B$80:$F$80,G$12+1)-INDEX(Annahmen!$B$80:$F$80,G$12)) -> 1151.5895 | H22: =INDEX(Annahmen!$B$94:$F$94,H$12)+(H$7-INDEX(Annahmen!$B$80:$F$80,H$12))*(INDEX(Annahmen!$B$94:$F$94,H$12+1)-INDEX(Annahmen!$B$94:$F$94,H$12))/(INDEX(Annahmen!$B$80:$F$80,H$12+1)-INDEX(Annahmen!$B$80:$F$80,H$12)) -> 1194.9572 | I22: =INDEX(Annahmen!$B$94:$F$94,I$12)+(I$7-INDEX(Annahmen!$B$80:$F$80,I$12))*(INDEX(Annahmen!$B$94:$F$94,I$12+1)-INDEX(Annahmen!$B$94:$F$94,I$12))/(INDEX(Annahmen!$B$80:$F$80,I$12+1)-INDEX(Annahmen!$B$80:$F$80,I$12)) -> 1241.1715 | ... AK22: =INDEX(Annahmen!$B$94:$F$94,AK$12)+(AK$7-INDEX(Annahmen!$B$80:$F$80,AK$12))*(INDEX(Annahmen!$B$94:$F$94,AK$12+1)-INDEX(Annahmen!$B$94:$F$94,AK$12))/(INDEX(Annahmen!$B$80:$F$80,AK$12+1)-INDEX(Annahmen!$B$80:$F$80,AK$12)) -> 3684
A23: Betrieb (ohne Altersprüfung) | B23: =INDEX(Annahmen!$B$95:$F$95,B$12)+(B$7-INDEX(Annahmen!$B$80:$F$80,B$12))*(INDEX(Annahmen!$B$95:$F$95,B$12+1)-INDEX(Annahmen!$B$95:$F$95,B$12))/(INDEX(Annahmen!$B$80:$F$80,B$12+1)-INDEX(Annahmen!$B$80:$F$80,B$12)) -> 270 | C23: =INDEX(Annahmen!$B$95:$F$95,C$12)+(C$7-INDEX(Annahmen!$B$80:$F$80,C$12))*(INDEX(Annahmen!$B$95:$F$95,C$12+1)-INDEX(Annahmen!$B$95:$F$95,C$12))/(INDEX(Annahmen!$B$80:$F$80,C$12+1)-INDEX(Annahmen!$B$80:$F$80,C$12)) -> 277.67534 | D23: =INDEX(Annahmen!$B$95:$F$95,D$12)+(D$7-INDEX(Annahmen!$B$80:$F$80,D$12))*(INDEX(Annahmen!$B$95:$F$95,D$12+1)-INDEX(Annahmen!$B$95:$F$95,D$12))/(INDEX(Annahmen!$B$80:$F$80,D$12+1)-INDEX(Annahmen!$B$80:$F$80,D$12)) -> 289.97647 | E23: =INDEX(Annahmen!$B$95:$F$95,E$12)+(E$7-INDEX(Annahmen!$B$80:$F$80,E$12))*(INDEX(Annahmen!$B$95:$F$95,E$12+1)-INDEX(Annahmen!$B$95:$F$95,E$12))/(INDEX(Annahmen!$B$80:$F$80,E$12+1)-INDEX(Annahmen!$B$80:$F$80,E$12)) -> 304.95624 | F23: =INDEX(Annahmen!$B$95:$F$95,F$12)+(F$7-INDEX(Annahmen!$B$80:$F$80,F$12))*(INDEX(Annahmen!$B$95:$F$95,F$12+1)-INDEX(Annahmen!$B$95:$F$95,F$12))/(INDEX(Annahmen!$B$80:$F$80,F$12+1)-INDEX(Annahmen!$B$80:$F$80,F$12)) -> 321.99244 | G23: =INDEX(Annahmen!$B$95:$F$95,G$12)+(G$7-INDEX(Annahmen!$B$80:$F$80,G$12))*(INDEX(Annahmen!$B$95:$F$95,G$12+1)-INDEX(Annahmen!$B$95:$F$95,G$12))/(INDEX(Annahmen!$B$80:$F$80,G$12+1)-INDEX(Annahmen!$B$80:$F$80,G$12)) -> 340.74178 | H23: =INDEX(Annahmen!$B$95:$F$95,H$12)+(H$7-INDEX(Annahmen!$B$80:$F$80,H$12))*(INDEX(Annahmen!$B$95:$F$95,H$12+1)-INDEX(Annahmen!$B$95:$F$95,H$12))/(INDEX(Annahmen!$B$80:$F$80,H$12+1)-INDEX(Annahmen!$B$80:$F$80,H$12)) -> 360.98004 | I23: =INDEX(Annahmen!$B$95:$F$95,I$12)+(I$7-INDEX(Annahmen!$B$80:$F$80,I$12))*(INDEX(Annahmen!$B$95:$F$95,I$12+1)-INDEX(Annahmen!$B$95:$F$95,I$12))/(INDEX(Annahmen!$B$80:$F$80,I$12+1)-INDEX(Annahmen!$B$80:$F$80,I$12)) -> 382.54668 | ... AK23: =INDEX(Annahmen!$B$95:$F$95,AK$12)+(AK$7-INDEX(Annahmen!$B$80:$F$80,AK$12))*(INDEX(Annahmen!$B$95:$F$95,AK$12+1)-INDEX(Annahmen!$B$95:$F$95,AK$12))/(INDEX(Annahmen!$B$80:$F$80,AK$12+1)-INDEX(Annahmen!$B$80:$F$80,AK$12)) -> 1598
A24: Altersprüfung (Stufe 1 + Stufe 2) ⟵ Schalter | B24: =B9*Annahmen!$B$105+B9*Annahmen!$B$110*Annahmen!$B$111 -> 0 | C24: =C9*Annahmen!$B$105+C9*Annahmen!$B$110*Annahmen!$B$111 -> 164.99779 | D24: =D9*Annahmen!$B$105+D9*Annahmen!$B$110*Annahmen!$B$111 -> 273.18916 | E24: =E9*Annahmen!$B$105+E9*Annahmen!$B$110*Annahmen!$B$111 -> 344.79541 | F24: =F9*Annahmen!$B$105+F9*Annahmen!$B$110*Annahmen!$B$111 -> 406.07967 | G24: =G9*Annahmen!$B$105+G9*Annahmen!$B$110*Annahmen!$B$111 -> 462.32872 | H24: =H9*Annahmen!$B$105+H9*Annahmen!$B$110*Annahmen!$B$111 -> 515.71032 | I24: =I9*Annahmen!$B$105+I9*Annahmen!$B$110*Annahmen!$B$111 -> 567.3384 | ... AK24: =AK9*Annahmen!$B$105+AK9*Annahmen!$B$110*Annahmen!$B$111 -> 4261.926
A25: SMS-Versand (Z-10) | B25: =B9*Annahmen!$C$146*Annahmen!$C$147*Annahmen!$C$148 -> 0 | C25: =C9*Annahmen!$C$146*Annahmen!$C$147*Annahmen!$C$148 -> 13.547187 | D25: =D9*Annahmen!$C$146*Annahmen!$C$147*Annahmen!$C$148 -> 22.430268 | E25: =E9*Annahmen!$C$146*Annahmen!$C$147*Annahmen!$C$148 -> 28.309518 | F25: =F9*Annahmen!$C$146*Annahmen!$C$147*Annahmen!$C$148 -> 33.341278 | G25: =G9*Annahmen!$C$146*Annahmen!$C$147*Annahmen!$C$148 -> 37.959621 | H25: =H9*Annahmen!$C$146*Annahmen!$C$147*Annahmen!$C$148 -> 42.342531 | I25: =I9*Annahmen!$C$146*Annahmen!$C$147*Annahmen!$C$148 -> 46.581469 | ... AK25: =AK9*Annahmen!$C$146*Annahmen!$C$147*Annahmen!$C$148 -> 349.92656
A26: Personal: Moderation | B26: =INDEX(Annahmen!$B$96:$F$96,B$12)+(B$7-INDEX(Annahmen!$B$80:$F$80,B$12))*(INDEX(Annahmen!$B$96:$F$96,B$12+1)-INDEX(Annahmen!$B$96:$F$96,B$12))/(INDEX(Annahmen!$B$80:$F$80,B$12+1)-INDEX(Annahmen!$B$80:$F$80,B$12)) -> 0 | C26: =INDEX(Annahmen!$B$96:$F$96,C$12)+(C$7-INDEX(Annahmen!$B$80:$F$80,C$12))*(INDEX(Annahmen!$B$96:$F$96,C$12+1)-INDEX(Annahmen!$B$96:$F$96,C$12))/(INDEX(Annahmen!$B$80:$F$80,C$12+1)-INDEX(Annahmen!$B$80:$F$80,C$12)) -> 0 | D26: =INDEX(Annahmen!$B$96:$F$96,D$12)+(D$7-INDEX(Annahmen!$B$80:$F$80,D$12))*(INDEX(Annahmen!$B$96:$F$96,D$12+1)-INDEX(Annahmen!$B$96:$F$96,D$12))/(INDEX(Annahmen!$B$80:$F$80,D$12+1)-INDEX(Annahmen!$B$80:$F$80,D$12)) -> 0 | E26: =INDEX(Annahmen!$B$96:$F$96,E$12)+(E$7-INDEX(Annahmen!$B$80:$F$80,E$12))*(INDEX(Annahmen!$B$96:$F$96,E$12+1)-INDEX(Annahmen!$B$96:$F$96,E$12))/(INDEX(Annahmen!$B$80:$F$80,E$12+1)-INDEX(Annahmen!$B$80:$F$80,E$12)) -> 0 | F26: =INDEX(Annahmen!$B$96:$F$96,F$12)+(F$7-INDEX(Annahmen!$B$80:$F$80,F$12))*(INDEX(Annahmen!$B$96:$F$96,F$12+1)-INDEX(Annahmen!$B$96:$F$96,F$12))/(INDEX(Annahmen!$B$80:$F$80,F$12+1)-INDEX(Annahmen!$B$80:$F$80,F$12)) -> 0 | G26: =INDEX(Annahmen!$B$96:$F$96,G$12)+(G$7-INDEX(Annahmen!$B$80:$F$80,G$12))*(INDEX(Annahmen!$B$96:$F$96,G$12+1)-INDEX(Annahmen!$B$96:$F$96,G$12))/(INDEX(Annahmen!$B$80:$F$80,G$12+1)-INDEX(Annahmen!$B$80:$F$80,G$12)) -> 0 | H26: =INDEX(Annahmen!$B$96:$F$96,H$12)+(H$7-INDEX(Annahmen!$B$80:$F$80,H$12))*(INDEX(Annahmen!$B$96:$F$96,H$12+1)-INDEX(Annahmen!$B$96:$F$96,H$12))/(INDEX(Annahmen!$B$80:$F$80,H$12+1)-INDEX(Annahmen!$B$80:$F$80,H$12)) -> 0 | I26: =INDEX(Annahmen!$B$96:$F$96,I$12)+(I$7-INDEX(Annahmen!$B$80:$F$80,I$12))*(INDEX(Annahmen!$B$96:$F$96,I$12+1)-INDEX(Annahmen!$B$96:$F$96,I$12))/(INDEX(Annahmen!$B$80:$F$80,I$12+1)-INDEX(Annahmen!$B$80:$F$80,I$12)) -> 0 | ... AK26: =INDEX(Annahmen!$B$96:$F$96,AK$12)+(AK$7-INDEX(Annahmen!$B$80:$F$80,AK$12))*(INDEX(Annahmen!$B$96:$F$96,AK$12+1)-INDEX(Annahmen!$B$96:$F$96,AK$12))/(INDEX(Annahmen!$B$80:$F$80,AK$12+1)-INDEX(Annahmen!$B$80:$F$80,AK$12)) -> 4080
A27: Marketing (Barmittel) | B27: =INDEX(Annahmen!$B$97:$F$97,B$12)+(B$7-INDEX(Annahmen!$B$80:$F$80,B$12))*(INDEX(Annahmen!$B$97:$F$97,B$12+1)-INDEX(Annahmen!$B$97:$F$97,B$12))/(INDEX(Annahmen!$B$80:$F$80,B$12+1)-INDEX(Annahmen!$B$80:$F$80,B$12)) -> 150 | C27: =INDEX(Annahmen!$B$97:$F$97,C$12)+(C$7-INDEX(Annahmen!$B$80:$F$80,C$12))*(INDEX(Annahmen!$B$97:$F$97,C$12+1)-INDEX(Annahmen!$B$97:$F$97,C$12))/(INDEX(Annahmen!$B$80:$F$80,C$12+1)-INDEX(Annahmen!$B$80:$F$80,C$12)) -> 155.48238 | D27: =INDEX(Annahmen!$B$97:$F$97,D$12)+(D$7-INDEX(Annahmen!$B$80:$F$80,D$12))*(INDEX(Annahmen!$B$97:$F$97,D$12+1)-INDEX(Annahmen!$B$97:$F$97,D$12))/(INDEX(Annahmen!$B$80:$F$80,D$12+1)-INDEX(Annahmen!$B$80:$F$80,D$12)) -> 164.26891 | E27: =INDEX(Annahmen!$B$97:$F$97,E$12)+(E$7-INDEX(Annahmen!$B$80:$F$80,E$12))*(INDEX(Annahmen!$B$97:$F$97,E$12+1)-INDEX(Annahmen!$B$97:$F$97,E$12))/(INDEX(Annahmen!$B$80:$F$80,E$12+1)-INDEX(Annahmen!$B$80:$F$80,E$12)) -> 174.96874 | F27: =INDEX(Annahmen!$B$97:$F$97,F$12)+(F$7-INDEX(Annahmen!$B$80:$F$80,F$12))*(INDEX(Annahmen!$B$97:$F$97,F$12+1)-INDEX(Annahmen!$B$97:$F$97,F$12))/(INDEX(Annahmen!$B$80:$F$80,F$12+1)-INDEX(Annahmen!$B$80:$F$80,F$12)) -> 187.13746 | G27: =INDEX(Annahmen!$B$97:$F$97,G$12)+(G$7-INDEX(Annahmen!$B$80:$F$80,G$12))*(INDEX(Annahmen!$B$97:$F$97,G$12+1)-INDEX(Annahmen!$B$97:$F$97,G$12))/(INDEX(Annahmen!$B$80:$F$80,G$12+1)-INDEX(Annahmen!$B$80:$F$80,G$12)) -> 200.52984 | H27: =INDEX(Annahmen!$B$97:$F$97,H$12)+(H$7-INDEX(Annahmen!$B$80:$F$80,H$12))*(INDEX(Annahmen!$B$97:$F$97,H$12+1)-INDEX(Annahmen!$B$97:$F$97,H$12))/(INDEX(Annahmen!$B$80:$F$80,H$12+1)-INDEX(Annahmen!$B$80:$F$80,H$12)) -> 214.98574 | I27: =INDEX(Annahmen!$B$97:$F$97,I$12)+(I$7-INDEX(Annahmen!$B$80:$F$80,I$12))*(INDEX(Annahmen!$B$97:$F$97,I$12+1)-INDEX(Annahmen!$B$97:$F$97,I$12))/(INDEX(Annahmen!$B$80:$F$80,I$12+1)-INDEX(Annahmen!$B$80:$F$80,I$12)) -> 230.39048 | ... AK27: =INDEX(Annahmen!$B$97:$F$97,AK$12)+(AK$7-INDEX(Annahmen!$B$80:$F$80,AK$12))*(INDEX(Annahmen!$B$97:$F$97,AK$12+1)-INDEX(Annahmen!$B$97:$F$97,AK$12))/(INDEX(Annahmen!$B$80:$F$80,AK$12+1)-INDEX(Annahmen!$B$80:$F$80,AK$12)) -> 1440
A28: Eigene Veranstaltungen (Nr. 74) | B28: =IF(B5>=Annahmen!$C$145,B8*Annahmen!$C$144/12,0) -> 166.66667 | C28: =IF(C5>=Annahmen!$C$145,C8*Annahmen!$C$144/12,0) -> 166.66667 | D28: =IF(D5>=Annahmen!$C$145,D8*Annahmen!$C$144/12,0) -> 166.66667 | E28: =IF(E5>=Annahmen!$C$145,E8*Annahmen!$C$144/12,0) -> 166.66667 | F28: =IF(F5>=Annahmen!$C$145,F8*Annahmen!$C$144/12,0) -> 166.66667 | G28: =IF(G5>=Annahmen!$C$145,G8*Annahmen!$C$144/12,0) -> 166.66667 | H28: =IF(H5>=Annahmen!$C$145,H8*Annahmen!$C$144/12,0) -> 166.66667 | I28: =IF(I5>=Annahmen!$C$145,I8*Annahmen!$C$144/12,0) -> 166.66667 | ... AK28: =IF(AK5>=Annahmen!$C$145,AK8*Annahmen!$C$144/12,0) -> 666.66667
A29: CSD-Auftritte (zum Start und Folgejahre) | B29: =IF(B5=Annahmen!$C$136,Annahmen!$C$135,0)+IF(B5=Annahmen!$C$138,Annahmen!$C$137,0)+IF(B5=Annahmen!$C$140,Annahmen!$C$139,0) -> 6000 | C29: =IF(C5=Annahmen!$C$136,Annahmen!$C$135,0)+IF(C5=Annahmen!$C$138,Annahmen!$C$137,0)+IF(C5=Annahmen!$C$140,Annahmen!$C$139,0) -> 0 | D29: =IF(D5=Annahmen!$C$136,Annahmen!$C$135,0)+IF(D5=Annahmen!$C$138,Annahmen!$C$137,0)+IF(D5=Annahmen!$C$140,Annahmen!$C$139,0) -> 0 | E29: =IF(E5=Annahmen!$C$136,Annahmen!$C$135,0)+IF(E5=Annahmen!$C$138,Annahmen!$C$137,0)+IF(E5=Annahmen!$C$140,Annahmen!$C$139,0) -> 0 | F29: =IF(F5=Annahmen!$C$136,Annahmen!$C$135,0)+IF(F5=Annahmen!$C$138,Annahmen!$C$137,0)+IF(F5=Annahmen!$C$140,Annahmen!$C$139,0) -> 0 | G29: =IF(G5=Annahmen!$C$136,Annahmen!$C$135,0)+IF(G5=Annahmen!$C$138,Annahmen!$C$137,0)+IF(G5=Annahmen!$C$140,Annahmen!$C$139,0) -> 0 | H29: =IF(H5=Annahmen!$C$136,Annahmen!$C$135,0)+IF(H5=Annahmen!$C$138,Annahmen!$C$137,0)+IF(H5=Annahmen!$C$140,Annahmen!$C$139,0) -> 0 | I29: =IF(I5=Annahmen!$C$136,Annahmen!$C$135,0)+IF(I5=Annahmen!$C$138,Annahmen!$C$137,0)+IF(I5=Annahmen!$C$140,Annahmen!$C$139,0) -> 0 | ... AK29: =IF(AK5=Annahmen!$C$136,Annahmen!$C$135,0)+IF(AK5=Annahmen!$C$138,Annahmen!$C$137,0)+IF(AK5=Annahmen!$C$140,Annahmen!$C$139,0) -> 0
A30: Einmalkosten | B30: =SUMIF(Annahmen!$C$116:$C$129,B5,Annahmen!$B$116:$B$129) -> 26700 | C30: =SUMIF(Annahmen!$C$116:$C$129,C5,Annahmen!$B$116:$B$129) -> 2700 | D30: =SUMIF(Annahmen!$C$116:$C$129,D5,Annahmen!$B$116:$B$129) -> 11500 | E30: =SUMIF(Annahmen!$C$116:$C$129,E5,Annahmen!$B$116:$B$129) -> 4500 | F30: =SUMIF(Annahmen!$C$116:$C$129,F5,Annahmen!$B$116:$B$129) -> 3000 | G30: =SUMIF(Annahmen!$C$116:$C$129,G5,Annahmen!$B$116:$B$129) -> 2000 | H30: =SUMIF(Annahmen!$C$116:$C$129,H5,Annahmen!$B$116:$B$129) -> 0 | I30: =SUMIF(Annahmen!$C$116:$C$129,I5,Annahmen!$B$116:$B$129) -> 5500 | ... AK30: =SUMIF(Annahmen!$C$116:$C$129,AK5,Annahmen!$B$116:$B$129) -> 0
A31: Kosten gesamt | B31: =SUM(B22:B30) -> 34286.667 | C31: =SUM(C22:C30) -> 4494.8165 | D31: =SUM(D22:D30) -> 13459.338 | E31: =SUM(E22:E30) -> 6594.6028 | F31: =SUM(F22:F30) -> 5226.6299 | G31: =SUM(G22:G30) -> 4359.8162 | H31: =SUM(H22:H30) -> 2495.6425 | I31: =SUM(I22:I30) -> 8134.6952 | ... AK31: =SUM(AK22:AK30) -> 16080.519
A33: Ergebnis je Monat | B33: =B19-B31 -> -34286.667 | C33: =C19-C31 -> -4494.8165 | D33: =D19-D31 -> -13459.338 | E33: =E19-E31 -> -6594.6028 | F33: =F19-F31 -> -5226.6299 | G33: =G19-G31 -> -4359.8162 | H33: =H19-H31 -> -2495.6425 | I33: =I19-I31 -> -8134.6952 | ... AK33: =AK19-AK31 -> 4291.6116
A34: Kumulierte Liquidität | B34: =B33 -> -34286.667 | C34: =B34+C33 -> -38781.483 | D34: =C34+D33 -> -52240.821 | E34: =D34+E33 -> -58835.424 | F34: =E34+F33 -> -64062.054 | G34: =F34+G33 -> -68421.87 | H34: =G34+H33 -> -70917.513 | I34: =H34+I33 -> -79052.208 | J34: =I34+J33 -> -81829.414 | ... AK34: =AJ34+AK33 -> -108134.31
A36: nachrichtlich: Krankenversicherung privat, kumuliert | B36: =Annahmen!$B$154*Annahmen!$B$155 -> 400 | C36: =B36+Annahmen!$B$154*Annahmen!$B$155 -> 800 | D36: =C36+Annahmen!$B$154*Annahmen!$B$155 -> 1200 | E36: =D36+Annahmen!$B$154*Annahmen!$B$155 -> 1600 | F36: =E36+Annahmen!$B$154*Annahmen!$B$155 -> 2000 | G36: =F36+Annahmen!$B$154*Annahmen!$B$155 -> 2400 | H36: =G36+Annahmen!$B$154*Annahmen!$B$155 -> 2800 | I36: =H36+Annahmen!$B$154*Annahmen!$B$155 -> 3200 | J36: =I36+Annahmen!$B$154*Annahmen!$B$155 -> 3600 | ... AK36: =AJ36+Annahmen!$B$154*Annahmen!$B$155 -> 14400
A37: nachrichtlich: Lebenshaltung beider Gründer, kumuliert | B37: =Annahmen!$B$156*Annahmen!$B$155 -> 2200 | C37: =B37+Annahmen!$B$156*Annahmen!$B$155 -> 4400 | D37: =C37+Annahmen!$B$156*Annahmen!$B$155 -> 6600 | E37: =D37+Annahmen!$B$156*Annahmen!$B$155 -> 8800 | F37: =E37+Annahmen!$B$156*Annahmen!$B$155 -> 11000 | G37: =F37+Annahmen!$B$156*Annahmen!$B$155 -> 13200 | H37: =G37+Annahmen!$B$156*Annahmen!$B$155 -> 15400 | I37: =H37+Annahmen!$B$156*Annahmen!$B$155 -> 17600 | J37: =I37+Annahmen!$B$156*Annahmen!$B$155 -> 19800 | ... AK37: =AJ37+Annahmen!$B$156*Annahmen!$B$155 -> 79200
A39: Jahressummen (rechnen sich)
A40: Größe | B40: Jahr 1 | C40: Jahr 2 | D40: Jahr 3 | E40: 36 Monate
A41: MAU im Jahresmittel | B41: =AVERAGE(B7:M7) -> 3206.8769 | C41: =AVERAGE(N7:Y7) -> 15433.959 | D41: =AVERAGE(Z7:AK7) -> 42272.149 | E41: =AVERAGE(B7:AK7) -> 20304.328
A42: Zahlende Nutzer im Mittel | B42: =AVERAGE(B11:M11) -> 0 | C42: =AVERAGE(N11:Y11) -> 341.86879 | D42: =AVERAGE(Z11:AK11) -> 1389.4525 | E42: =AVERAGE(B11:AK11) -> 577.10711
A43: Erlöse gesamt | B43: =SUM(B19:M19) -> 0 | C43: =SUM(N19:Y19) -> 41199.51 | D43: =SUM(Z19:AK19) -> 164484.94 | E43: =SUM(B19:AK19) -> 205684.45
A44: Kosten gesamt | B44: =SUM(B31:M31) -> 90958.821 | C44: =SUM(N31:Y31) -> 68866.592 | D44: =SUM(Z31:AK31) -> 153993.36 | E44: =SUM(B31:AK31) -> 313818.77
A45: Ergebnis | B45: =SUM(B33:M33) -> -90958.821 | C45: =SUM(N33:Y33) -> -27667.081 | D45: =SUM(Z33:AK33) -> 10491.587 | E45: =SUM(B33:AK33) -> -108134.31

Sheet Optimistisch
A1: Szenario C — Optimistisch
A2: 36 Monate ab T0 — dem Start in der CSD-Saison; geplant wird ein Jahr nach dem Bestfall Sommer 2028 (Nr. 45). Alles rechnet sich aus dem Blatt „Annahmen“. Kein Gründergehalt in keinem Monat.
A4: Position | B4: M1 | C4: M2 | D4: M3 | E4: M4 | F4: M5 | G4: M6 | H4: M7 | I4: M8 | J4: M9 | K4: M10 | L4: M11 | M4: M12 | N4: M13 | O4: M14 | P4: M15 | Q4: M16 | R4: M17 | S4: M18 | T4: M19 | U4: M20 | V4: M21 | W4: M22 | X4: M23 | Y4: M24 | Z4: M25 | AA4: M26 | AB4: M27 | AC4: M28 | AD4: M29 | AE4: M30 | AF4: M31 | AG4: M32 | AH4: M33 | AI4: M34 | AJ4: M35 | AK4: M36
A5: Monat | B5: 1 | C5: 2 | D5: 3 | E5: 4 | F5: 5 | G5: 6 | H5: 7 | I5: 8 | J5: 9 | K5: 10 | L5: 11 | M5: 12 | N5: 13 | O5: 14 | P5: 15 | Q5: 16 | R5: 17 | S5: 18 | T5: 19 | U5: 20 | V5: 21 | W5: 22 | X5: 23 | Y5: 24 | Z5: 25 | AA5: 26 | AB5: 27 | AC5: 28 | AD5: 29 | AE5: 30 | AF5: 31 | AG5: 32 | AH5: 33 | AI5: 34 | AJ5: 35 | AK5: 36
A6: Jahr | B6: =ROUNDUP(B5/12,0) -> 1 | C6: =ROUNDUP(C5/12,0) -> 1 | D6: =ROUNDUP(D5/12,0) -> 1 | E6: =ROUNDUP(E5/12,0) -> 1 | F6: =ROUNDUP(F5/12,0) -> 1 | G6: =ROUNDUP(G5/12,0) -> 1 | H6: =ROUNDUP(H5/12,0) -> 1 | I6: =ROUNDUP(I5/12,0) -> 1 | ... AK6: =ROUNDUP(AK5/12,0) -> 3
A7: Aktive Nutzer im Monat (MAU) | B7: =IF(B5<Annahmen!$D$9,0,IF(B5<=12,Annahmen!$D$6*((B5-Annahmen!$D$9+1)/(12-Annahmen!$D$9+1))^Annahmen!$D$10,IF(B5<=24,Annahmen!$D$6+(Annahmen!$D$7-Annahmen!$D$6)*((B5-12)/12)^Annahmen!$D$11,Annahmen!$D$7+(Annahmen!$D$8-Annahmen!$D$7)*((B5-24)/12)^Annahmen!$D$11))) -> 0 | C7: =IF(C5<Annahmen!$D$9,0,IF(C5<=12,Annahmen!$D$6*((C5-Annahmen!$D$9+1)/(12-Annahmen!$D$9+1))^Annahmen!$D$10,IF(C5<=24,Annahmen!$D$6+(Annahmen!$D$7-Annahmen!$D$6)*((C5-12)/12)^Annahmen!$D$11,Annahmen!$D$7+(Annahmen!$D$8-Annahmen!$D$7)*((C5-24)/12)^Annahmen!$D$11))) -> 563.19895 | D7: =IF(D5<Annahmen!$D$9,0,IF(D5<=12,Annahmen!$D$6*((D5-Annahmen!$D$9+1)/(12-Annahmen!$D$9+1))^Annahmen!$D$10,IF(D5<=24,Annahmen!$D$6+(Annahmen!$D$7-Annahmen!$D$6)*((D5-12)/12)^Annahmen!$D$11,Annahmen!$D$7+(Annahmen!$D$8-Annahmen!$D$7)*((D5-24)/12)^Annahmen!$D$11))) -> 1425.7456 | E7: =IF(E5<Annahmen!$D$9,0,IF(E5<=12,Annahmen!$D$6*((E5-Annahmen!$D$9+1)/(12-Annahmen!$D$9+1))^Annahmen!$D$10,IF(E5<=24,Annahmen!$D$6+(Annahmen!$D$7-Annahmen!$D$6)*((E5-12)/12)^Annahmen!$D$11,Annahmen!$D$7+(Annahmen!$D$8-Annahmen!$D$7)*((E5-24)/12)^Annahmen!$D$11))) -> 2454.7333 | F7: =IF(F5<Annahmen!$D$9,0,IF(F5<=12,Annahmen!$D$6*((F5-Annahmen!$D$9+1)/(12-Annahmen!$D$9+1))^Annahmen!$D$10,IF(F5<=24,Annahmen!$D$6+(Annahmen!$D$7-Annahmen!$D$6)*((F5-12)/12)^Annahmen!$D$11,Annahmen!$D$7+(Annahmen!$D$8-Annahmen!$D$7)*((F5-24)/12)^Annahmen!$D$11))) -> 3609.2937 | G7: =IF(G5<Annahmen!$D$9,0,IF(G5<=12,Annahmen!$D$6*((G5-Annahmen!$D$9+1)/(12-Annahmen!$D$9+1))^Annahmen!$D$10,IF(G5<=24,Annahmen!$D$6+(Annahmen!$D$7-Annahmen!$D$6)*((G5-12)/12)^Annahmen!$D$11,Annahmen!$D$7+(Annahmen!$D$8-Annahmen!$D$7)*((G5-24)/12)^Annahmen!$D$11))) -> 4867.2275 | H7: =IF(H5<Annahmen!$D$9,0,IF(H5<=12,Annahmen!$D$6*((H5-Annahmen!$D$9+1)/(12-Annahmen!$D$9+1))^Annahmen!$D$10,IF(H5<=24,Annahmen!$D$6+(Annahmen!$D$7-Annahmen!$D$6)*((H5-12)/12)^Annahmen!$D$11,Annahmen!$D$7+(Annahmen!$D$8-Annahmen!$D$7)*((H5-24)/12)^Annahmen!$D$11))) -> 6214.1898 | I7: =IF(I5<Annahmen!$D$9,0,IF(I5<=12,Annahmen!$D$6*((I5-Annahmen!$D$9+1)/(12-Annahmen!$D$9+1))^Annahmen!$D$10,IF(I5<=24,Annahmen!$D$6+(Annahmen!$D$7-Annahmen!$D$6)*((I5-12)/12)^Annahmen!$D$11,Annahmen!$D$7+(Annahmen!$D$8-Annahmen!$D$7)*((I5-24)/12)^Annahmen!$D$11))) -> 7639.9974 | ... AK7: =IF(AK5<Annahmen!$D$9,0,IF(AK5<=12,Annahmen!$D$6*((AK5-Annahmen!$D$9+1)/(12-Annahmen!$D$9+1))^Annahmen!$D$10,IF(AK5<=24,Annahmen!$D$6+(Annahmen!$D$7-Annahmen!$D$6)*((AK5-12)/12)^Annahmen!$D$11,Annahmen!$D$7+(Annahmen!$D$8-Annahmen!$D$7)*((AK5-24)/12)^Annahmen!$D$11))) -> 150000
A8: Städte | B8: =IF(B5<=12,Annahmen!$D$12,IF(B5<=24,Annahmen!$D$13,Annahmen!$D$14)) -> 1 | C8: =IF(C5<=12,Annahmen!$D$12,IF(C5<=24,Annahmen!$D$13,Annahmen!$D$14)) -> 1 | D8: =IF(D5<=12,Annahmen!$D$12,IF(D5<=24,Annahmen!$D$13,Annahmen!$D$14)) -> 1 | E8: =IF(E5<=12,Annahmen!$D$12,IF(E5<=24,Annahmen!$D$13,Annahmen!$D$14)) -> 1 | F8: =IF(F5<=12,Annahmen!$D$12,IF(F5<=24,Annahmen!$D$13,Annahmen!$D$14)) -> 1 | G8: =IF(G5<=12,Annahmen!$D$12,IF(G5<=24,Annahmen!$D$13,Annahmen!$D$14)) -> 1 | H8: =IF(H5<=12,Annahmen!$D$12,IF(H5<=24,Annahmen!$D$13,Annahmen!$D$14)) -> 1 | I8: =IF(I5<=12,Annahmen!$D$12,IF(I5<=24,Annahmen!$D$13,Annahmen!$D$14)) -> 1 | ... AK8: =IF(AK5<=12,Annahmen!$D$12,IF(AK5<=24,Annahmen!$D$13,Annahmen!$D$14)) -> 6
A9: Neuregistrierungen (Treiber der Prüfkosten) | B9: =MAX(0,B7-0)+B7*Annahmen!$D$15*(1-Annahmen!$D$16) -> 0 | C9: =MAX(0,C7-B7)+C7*Annahmen!$D$15*(1-Annahmen!$D$16) -> 590.7957 | D9: =MAX(0,D7-C7)+D7*Annahmen!$D$15*(1-Annahmen!$D$16) -> 932.40815 | E9: =MAX(0,E7-D7)+E7*Annahmen!$D$15*(1-Annahmen!$D$16) -> 1149.2697 | F9: =MAX(0,F7-E7)+F7*Annahmen!$D$15*(1-Annahmen!$D$16) -> 1331.4158 | G9: =MAX(0,G7-F7)+G7*Annahmen!$D$15*(1-Annahmen!$D$16) -> 1496.4279 | H9: =MAX(0,H7-G7)+H7*Annahmen!$D$15*(1-Annahmen!$D$16) -> 1651.4576 | I9: =MAX(0,I7-H7)+I7*Annahmen!$D$15*(1-Annahmen!$D$16) -> 1800.1675 | J9: =MAX(0,J7-I7)+J7*Annahmen!$D$15*(1-Annahmen!$D$16) -> 1944.689 | ... AK9: =MAX(0,AK7-AJ7)+AK7*Annahmen!$D$15*(1-Annahmen!$D$16) -> 16695.441
A10: Konversion zu Zahlern | B10: =IF(B5<Annahmen!$D$22,0,Annahmen!$D$23*(Annahmen!$D$24+(1-Annahmen!$D$24)*MIN(1,(B5-Annahmen!$D$22+1)/Annahmen!$D$25))) -> 0 | C10: =IF(C5<Annahmen!$D$22,0,Annahmen!$D$23*(Annahmen!$D$24+(1-Annahmen!$D$24)*MIN(1,(C5-Annahmen!$D$22+1)/Annahmen!$D$25))) -> 0 | D10: =IF(D5<Annahmen!$D$22,0,Annahmen!$D$23*(Annahmen!$D$24+(1-Annahmen!$D$24)*MIN(1,(D5-Annahmen!$D$22+1)/Annahmen!$D$25))) -> 0 | E10: =IF(E5<Annahmen!$D$22,0,Annahmen!$D$23*(Annahmen!$D$24+(1-Annahmen!$D$24)*MIN(1,(E5-Annahmen!$D$22+1)/Annahmen!$D$25))) -> 0 | F10: =IF(F5<Annahmen!$D$22,0,Annahmen!$D$23*(Annahmen!$D$24+(1-Annahmen!$D$24)*MIN(1,(F5-Annahmen!$D$22+1)/Annahmen!$D$25))) -> 0 | G10: =IF(G5<Annahmen!$D$22,0,Annahmen!$D$23*(Annahmen!$D$24+(1-Annahmen!$D$24)*MIN(1,(G5-Annahmen!$D$22+1)/Annahmen!$D$25))) -> 0 | H10: =IF(H5<Annahmen!$D$22,0,Annahmen!$D$23*(Annahmen!$D$24+(1-Annahmen!$D$24)*MIN(1,(H5-Annahmen!$D$22+1)/Annahmen!$D$25))) -> 0 | I10: =IF(I5<Annahmen!$D$22,0,Annahmen!$D$23*(Annahmen!$D$24+(1-Annahmen!$D$24)*MIN(1,(I5-Annahmen!$D$22+1)/Annahmen!$D$25))) -> 0 | ... AK10: =IF(AK5<Annahmen!$D$22,0,Annahmen!$D$23*(Annahmen!$D$24+(1-Annahmen!$D$24)*MIN(1,(AK5-Annahmen!$D$22+1)/Annahmen!$D$25))) -> 0.042
A11: Zahlende Nutzer | B11: =B7*B10 -> 0 | C11: =C7*C10 -> 0 | D11: =D7*D10 -> 0 | E11: =E7*E10 -> 0 | F11: =F7*F10 -> 0 | G11: =G7*G10 -> 0 | H11: =H7*H10 -> 0 | I11: =I7*I10 -> 0 | ... AK11: =AK7*AK10 -> 6300
A12: Staffel-Stützstelle (Hilfsgröße) | B12: =MIN(MATCH(B7,Annahmen!$B$80:$F$80,1),4) -> 1 | C12: =MIN(MATCH(C7,Annahmen!$B$80:$F$80,1),4) -> 1 | D12: =MIN(MATCH(D7,Annahmen!$B$80:$F$80,1),4) -> 1 | E12: =MIN(MATCH(E7,Annahmen!$B$80:$F$80,1),4) -> 1 | F12: =MIN(MATCH(F7,Annahmen!$B$80:$F$80,1),4) -> 1 | G12: =MIN(MATCH(G7,Annahmen!$B$80:$F$80,1),4) -> 1 | H12: =MIN(MATCH(H7,Annahmen!$B$80:$F$80,1),4) -> 2 | I12: =MIN(MATCH(I7,Annahmen!$B$80:$F$80,1),4) -> 2 | ... AK12: =MIN(MATCH(AK7,Annahmen!$B$80:$F$80,1),4) -> 4
A13: ERLÖSE — fünf Quellen (Handbuch B, nach Nr. 65 und 74 neu geschnitten)
A14: Abonnements | B14: =B11*Annahmen!$D$26 -> 0 | C14: =C11*Annahmen!$D$26 -> 0 | D14: =D11*Annahmen!$D$26 -> 0 | E14: =E11*Annahmen!$D$26 -> 0 | F14: =F11*Annahmen!$D$26 -> 0 | G14: =G11*Annahmen!$D$26 -> 0 | H14: =H11*Annahmen!$D$26 -> 0 | I14: =I11*Annahmen!$D$26 -> 0 | ... AK14: =AK11*Annahmen!$D$26 -> 47624.079
A15: Werkzeugabo für Orte und Veranstalter | B15: =IF(AND(B5>=Annahmen!$D$62,B7>=Annahmen!$D$63),B8*Annahmen!$D$64*Annahmen!$D$65,0) -> 0 | C15: =IF(AND(C5>=Annahmen!$D$62,C7>=Annahmen!$D$63),C8*Annahmen!$D$64*Annahmen!$D$65,0) -> 0 | D15: =IF(AND(D5>=Annahmen!$D$62,D7>=Annahmen!$D$63),D8*Annahmen!$D$64*Annahmen!$D$65,0) -> 0 | E15: =IF(AND(E5>=Annahmen!$D$62,E7>=Annahmen!$D$63),E8*Annahmen!$D$64*Annahmen!$D$65,0) -> 0 | F15: =IF(AND(F5>=Annahmen!$D$62,F7>=Annahmen!$D$63),F8*Annahmen!$D$64*Annahmen!$D$65,0) -> 0 | G15: =IF(AND(G5>=Annahmen!$D$62,G7>=Annahmen!$D$63),G8*Annahmen!$D$64*Annahmen!$D$65,0) -> 0 | H15: =IF(AND(H5>=Annahmen!$D$62,H7>=Annahmen!$D$63),H8*Annahmen!$D$64*Annahmen!$D$65,0) -> 0 | I15: =IF(AND(I5>=Annahmen!$D$62,I7>=Annahmen!$D$63),I8*Annahmen!$D$64*Annahmen!$D$65,0) -> 0 | ... AK15: =IF(AND(AK5>=Annahmen!$D$62,AK7>=Annahmen!$D$63),AK8*Annahmen!$D$64*Annahmen!$D$65,0) -> 870
A16: Veranstaltungen: Anteil an Tickets | B16: =IF(AND(B5>=Annahmen!$D$66,B7>=Annahmen!$D$67),B8*Annahmen!$D$68*Annahmen!$D$69*Annahmen!$D$70*Annahmen!$D$71,0) -> 0 | C16: =IF(AND(C5>=Annahmen!$D$66,C7>=Annahmen!$D$67),C8*Annahmen!$D$68*Annahmen!$D$69*Annahmen!$D$70*Annahmen!$D$71,0) -> 0 | D16: =IF(AND(D5>=Annahmen!$D$66,D7>=Annahmen!$D$67),D8*Annahmen!$D$68*Annahmen!$D$69*Annahmen!$D$70*Annahmen!$D$71,0) -> 0 | E16: =IF(AND(E5>=Annahmen!$D$66,E7>=Annahmen!$D$67),E8*Annahmen!$D$68*Annahmen!$D$69*Annahmen!$D$70*Annahmen!$D$71,0) -> 0 | F16: =IF(AND(F5>=Annahmen!$D$66,F7>=Annahmen!$D$67),F8*Annahmen!$D$68*Annahmen!$D$69*Annahmen!$D$70*Annahmen!$D$71,0) -> 0 | G16: =IF(AND(G5>=Annahmen!$D$66,G7>=Annahmen!$D$67),G8*Annahmen!$D$68*Annahmen!$D$69*Annahmen!$D$70*Annahmen!$D$71,0) -> 0 | H16: =IF(AND(H5>=Annahmen!$D$66,H7>=Annahmen!$D$67),H8*Annahmen!$D$68*Annahmen!$D$69*Annahmen!$D$70*Annahmen!$D$71,0) -> 0 | I16: =IF(AND(I5>=Annahmen!$D$66,I7>=Annahmen!$D$67),I8*Annahmen!$D$68*Annahmen!$D$69*Annahmen!$D$70*Annahmen!$D$71,0) -> 0 | ... AK16: =IF(AND(AK5>=Annahmen!$D$66,AK7>=Annahmen!$D$67),AK8*Annahmen!$D$68*Annahmen!$D$69*Annahmen!$D$70*Annahmen!$D$71,0) -> 1382.4
A17: Unterstützerbeiträge | B17: =IF(B5>=Annahmen!$D$72,B7*Annahmen!$D$73,0) -> 0 | C17: =IF(C5>=Annahmen!$D$72,C7*Annahmen!$D$73,0) -> 0 | D17: =IF(D5>=Annahmen!$D$72,D7*Annahmen!$D$73,0) -> 0 | E17: =IF(E5>=Annahmen!$D$72,E7*Annahmen!$D$73,0) -> 0 | F17: =IF(F5>=Annahmen!$D$72,F7*Annahmen!$D$73,0) -> 0 | G17: =IF(G5>=Annahmen!$D$72,G7*Annahmen!$D$73,0) -> 0 | H17: =IF(H5>=Annahmen!$D$72,H7*Annahmen!$D$73,0) -> 0 | I17: =IF(I5>=Annahmen!$D$72,I7*Annahmen!$D$73,0) -> 0 | ... AK17: =IF(AK5>=Annahmen!$D$72,AK7*Annahmen!$D$73,0) -> 2250
A18: Gesundheitspartnerschaft | B18: =IF(B5>=Annahmen!$D$74,B8*Annahmen!$D$75,0) -> 0 | C18: =IF(C5>=Annahmen!$D$74,C8*Annahmen!$D$75,0) -> 0 | D18: =IF(D5>=Annahmen!$D$74,D8*Annahmen!$D$75,0) -> 0 | E18: =IF(E5>=Annahmen!$D$74,E8*Annahmen!$D$75,0) -> 0 | F18: =IF(F5>=Annahmen!$D$74,F8*Annahmen!$D$75,0) -> 0 | G18: =IF(G5>=Annahmen!$D$74,G8*Annahmen!$D$75,0) -> 0 | H18: =IF(H5>=Annahmen!$D$74,H8*Annahmen!$D$75,0) -> 0 | I18: =IF(I5>=Annahmen!$D$74,I8*Annahmen!$D$75,0) -> 0 | ... AK18: =IF(AK5>=Annahmen!$D$74,AK8*Annahmen!$D$75,0) -> 1602
A19: Erlöse gesamt | B19: =SUM(B14:B18) -> 0 | C19: =SUM(C14:C18) -> 0 | D19: =SUM(D14:D18) -> 0 | E19: =SUM(E14:E18) -> 0 | F19: =SUM(F14:F18) -> 0 | G19: =SUM(G14:G18) -> 0 | H19: =SUM(H14:H18) -> 0 | I19: =SUM(I14:I18) -> 0 | ... AK19: =SUM(AK14:AK18) -> 53728.479
A21: KOSTEN
A22: Pflichtpositionen (nicht kürzbar) | B22: =INDEX(Annahmen!$B$94:$F$94,B$12)+(B$7-INDEX(Annahmen!$B$80:$F$80,B$12))*(INDEX(Annahmen!$B$94:$F$94,B$12+1)-INDEX(Annahmen!$B$94:$F$94,B$12))/(INDEX(Annahmen!$B$80:$F$80,B$12+1)-INDEX(Annahmen!$B$80:$F$80,B$12)) -> 1000 | C22: =INDEX(Annahmen!$B$94:$F$94,C$12)+(C$7-INDEX(Annahmen!$B$80:$F$80,C$12))*(INDEX(Annahmen!$B$94:$F$94,C$12+1)-INDEX(Annahmen!$B$94:$F$94,C$12))/(INDEX(Annahmen!$B$80:$F$80,C$12+1)-INDEX(Annahmen!$B$80:$F$80,C$12)) -> 1033.7919 | D22: =INDEX(Annahmen!$B$94:$F$94,D$12)+(D$7-INDEX(Annahmen!$B$80:$F$80,D$12))*(INDEX(Annahmen!$B$94:$F$94,D$12+1)-INDEX(Annahmen!$B$94:$F$94,D$12))/(INDEX(Annahmen!$B$80:$F$80,D$12+1)-INDEX(Annahmen!$B$80:$F$80,D$12)) -> 1085.5447 | E22: =INDEX(Annahmen!$B$94:$F$94,E$12)+(E$7-INDEX(Annahmen!$B$80:$F$80,E$12))*(INDEX(Annahmen!$B$94:$F$94,E$12+1)-INDEX(Annahmen!$B$94:$F$94,E$12))/(INDEX(Annahmen!$B$80:$F$80,E$12+1)-INDEX(Annahmen!$B$80:$F$80,E$12)) -> 1147.284 | F22: =INDEX(Annahmen!$B$94:$F$94,F$12)+(F$7-INDEX(Annahmen!$B$80:$F$80,F$12))*(INDEX(Annahmen!$B$94:$F$94,F$12+1)-INDEX(Annahmen!$B$94:$F$94,F$12))/(INDEX(Annahmen!$B$80:$F$80,F$12+1)-INDEX(Annahmen!$B$80:$F$80,F$12)) -> 1216.5576 | G22: =INDEX(Annahmen!$B$94:$F$94,G$12)+(G$7-INDEX(Annahmen!$B$80:$F$80,G$12))*(INDEX(Annahmen!$B$94:$F$94,G$12+1)-INDEX(Annahmen!$B$94:$F$94,G$12))/(INDEX(Annahmen!$B$80:$F$80,G$12+1)-INDEX(Annahmen!$B$80:$F$80,G$12)) -> 1292.0336 | H22: =INDEX(Annahmen!$B$94:$F$94,H$12)+(H$7-INDEX(Annahmen!$B$80:$F$80,H$12))*(INDEX(Annahmen!$B$94:$F$94,H$12+1)-INDEX(Annahmen!$B$94:$F$94,H$12))/(INDEX(Annahmen!$B$80:$F$80,H$12+1)-INDEX(Annahmen!$B$80:$F$80,H$12)) -> 1355.5058 | I22: =INDEX(Annahmen!$B$94:$F$94,I$12)+(I$7-INDEX(Annahmen!$B$80:$F$80,I$12))*(INDEX(Annahmen!$B$94:$F$94,I$12+1)-INDEX(Annahmen!$B$94:$F$94,I$12))/(INDEX(Annahmen!$B$80:$F$80,I$12+1)-INDEX(Annahmen!$B$80:$F$80,I$12)) -> 1420.6856 | ... AK22: =INDEX(Annahmen!$B$94:$F$94,AK$12)+(AK$7-INDEX(Annahmen!$B$80:$F$80,AK$12))*(INDEX(Annahmen!$B$94:$F$94,AK$12+1)-INDEX(Annahmen!$B$94:$F$94,AK$12))/(INDEX(Annahmen!$B$80:$F$80,AK$12+1)-INDEX(Annahmen!$B$80:$F$80,AK$12)) -> 7233.3333
A23: Betrieb (ohne Altersprüfung) | B23: =INDEX(Annahmen!$B$95:$F$95,B$12)+(B$7-INDEX(Annahmen!$B$80:$F$80,B$12))*(INDEX(Annahmen!$B$95:$F$95,B$12+1)-INDEX(Annahmen!$B$95:$F$95,B$12))/(INDEX(Annahmen!$B$80:$F$80,B$12+1)-INDEX(Annahmen!$B$80:$F$80,B$12)) -> 270 | C23: =INDEX(Annahmen!$B$95:$F$95,C$12)+(C$7-INDEX(Annahmen!$B$80:$F$80,C$12))*(INDEX(Annahmen!$B$95:$F$95,C$12+1)-INDEX(Annahmen!$B$95:$F$95,C$12))/(INDEX(Annahmen!$B$80:$F$80,C$12+1)-INDEX(Annahmen!$B$80:$F$80,C$12)) -> 285.76957 | D23: =INDEX(Annahmen!$B$95:$F$95,D$12)+(D$7-INDEX(Annahmen!$B$80:$F$80,D$12))*(INDEX(Annahmen!$B$95:$F$95,D$12+1)-INDEX(Annahmen!$B$95:$F$95,D$12))/(INDEX(Annahmen!$B$80:$F$80,D$12+1)-INDEX(Annahmen!$B$80:$F$80,D$12)) -> 309.92088 | E23: =INDEX(Annahmen!$B$95:$F$95,E$12)+(E$7-INDEX(Annahmen!$B$80:$F$80,E$12))*(INDEX(Annahmen!$B$95:$F$95,E$12+1)-INDEX(Annahmen!$B$95:$F$95,E$12))/(INDEX(Annahmen!$B$80:$F$80,E$12+1)-INDEX(Annahmen!$B$80:$F$80,E$12)) -> 338.73253 | F23: =INDEX(Annahmen!$B$95:$F$95,F$12)+(F$7-INDEX(Annahmen!$B$80:$F$80,F$12))*(INDEX(Annahmen!$B$95:$F$95,F$12+1)-INDEX(Annahmen!$B$95:$F$95,F$12))/(INDEX(Annahmen!$B$80:$F$80,F$12+1)-INDEX(Annahmen!$B$80:$F$80,F$12)) -> 371.06022 | G23: =INDEX(Annahmen!$B$95:$F$95,G$12)+(G$7-INDEX(Annahmen!$B$80:$F$80,G$12))*(INDEX(Annahmen!$B$95:$F$95,G$12+1)-INDEX(Annahmen!$B$95:$F$95,G$12))/(INDEX(Annahmen!$B$80:$F$80,G$12+1)-INDEX(Annahmen!$B$80:$F$80,G$12)) -> 406.28237 | H23: =INDEX(Annahmen!$B$95:$F$95,H$12)+(H$7-INDEX(Annahmen!$B$80:$F$80,H$12))*(INDEX(Annahmen!$B$95:$F$95,H$12+1)-INDEX(Annahmen!$B$95:$F$95,H$12))/(INDEX(Annahmen!$B$80:$F$80,H$12+1)-INDEX(Annahmen!$B$80:$F$80,H$12)) -> 436.01835 | I23: =INDEX(Annahmen!$B$95:$F$95,I$12)+(I$7-INDEX(Annahmen!$B$80:$F$80,I$12))*(INDEX(Annahmen!$B$95:$F$95,I$12+1)-INDEX(Annahmen!$B$95:$F$95,I$12))/(INDEX(Annahmen!$B$80:$F$80,I$12+1)-INDEX(Annahmen!$B$80:$F$80,I$12)) -> 466.57137 | ... AK23: =INDEX(Annahmen!$B$95:$F$95,AK$12)+(AK$7-INDEX(Annahmen!$B$80:$F$80,AK$12))*(INDEX(Annahmen!$B$95:$F$95,AK$12+1)-INDEX(Annahmen!$B$95:$F$95,AK$12))/(INDEX(Annahmen!$B$80:$F$80,AK$12+1)-INDEX(Annahmen!$B$80:$F$80,AK$12)) -> 3416.6667
A24: Altersprüfung (Stufe 1 + Stufe 2) ⟵ Schalter | B24: =B9*Annahmen!$B$105+B9*Annahmen!$B$110*Annahmen!$B$111 -> 0 | C24: =C9*Annahmen!$B$105+C9*Annahmen!$B$110*Annahmen!$B$111 -> 336.75355 | D24: =D9*Annahmen!$B$105+D9*Annahmen!$B$110*Annahmen!$B$111 -> 531.47265 | E24: =E9*Annahmen!$B$105+E9*Annahmen!$B$110*Annahmen!$B$111 -> 655.08372 | F24: =F9*Annahmen!$B$105+F9*Annahmen!$B$110*Annahmen!$B$111 -> 758.907 | G24: =G9*Annahmen!$B$105+G9*Annahmen!$B$110*Annahmen!$B$111 -> 852.9639 | H24: =H9*Annahmen!$B$105+H9*Annahmen!$B$110*Annahmen!$B$111 -> 941.33084 | I24: =I9*Annahmen!$B$105+I9*Annahmen!$B$110*Annahmen!$B$111 -> 1026.0955 | ... AK24: =AK9*Annahmen!$B$105+AK9*Annahmen!$B$110*Annahmen!$B$111 -> 9516.4012
A25: SMS-Versand (Z-10) | B25: =B9*Annahmen!$D$146*Annahmen!$D$147*Annahmen!$D$148 -> 0 | C25: =C9*Annahmen!$D$146*Annahmen!$D$147*Annahmen!$D$148 -> 27.649239 | D25: =D9*Annahmen!$D$146*Annahmen!$D$147*Annahmen!$D$148 -> 43.636702 | E25: =E9*Annahmen!$D$146*Annahmen!$D$147*Annahmen!$D$148 -> 53.785821 | F25: =F9*Annahmen!$D$146*Annahmen!$D$147*Annahmen!$D$148 -> 62.310259 | G25: =G9*Annahmen!$D$146*Annahmen!$D$147*Annahmen!$D$148 -> 70.032825 | H25: =H9*Annahmen!$D$146*Annahmen!$D$147*Annahmen!$D$148 -> 77.288217 | I25: =I9*Annahmen!$D$146*Annahmen!$D$147*Annahmen!$D$148 -> 84.247839 | ... AK25: =AK9*Annahmen!$D$146*Annahmen!$D$147*Annahmen!$D$148 -> 781.34662
A26: Personal: Moderation | B26: =INDEX(Annahmen!$B$96:$F$96,B$12)+(B$7-INDEX(Annahmen!$B$80:$F$80,B$12))*(INDEX(Annahmen!$B$96:$F$96,B$12+1)-INDEX(Annahmen!$B$96:$F$96,B$12))/(INDEX(Annahmen!$B$80:$F$80,B$12+1)-INDEX(Annahmen!$B$80:$F$80,B$12)) -> 0 | C26: =INDEX(Annahmen!$B$96:$F$96,C$12)+(C$7-INDEX(Annahmen!$B$80:$F$80,C$12))*(INDEX(Annahmen!$B$96:$F$96,C$12+1)-INDEX(Annahmen!$B$96:$F$96,C$12))/(INDEX(Annahmen!$B$80:$F$80,C$12+1)-INDEX(Annahmen!$B$80:$F$80,C$12)) -> 0 | D26: =INDEX(Annahmen!$B$96:$F$96,D$12)+(D$7-INDEX(Annahmen!$B$80:$F$80,D$12))*(INDEX(Annahmen!$B$96:$F$96,D$12+1)-INDEX(Annahmen!$B$96:$F$96,D$12))/(INDEX(Annahmen!$B$80:$F$80,D$12+1)-INDEX(Annahmen!$B$80:$F$80,D$12)) -> 0 | E26: =INDEX(Annahmen!$B$96:$F$96,E$12)+(E$7-INDEX(Annahmen!$B$80:$F$80,E$12))*(INDEX(Annahmen!$B$96:$F$96,E$12+1)-INDEX(Annahmen!$B$96:$F$96,E$12))/(INDEX(Annahmen!$B$80:$F$80,E$12+1)-INDEX(Annahmen!$B$80:$F$80,E$12)) -> 0 | F26: =INDEX(Annahmen!$B$96:$F$96,F$12)+(F$7-INDEX(Annahmen!$B$80:$F$80,F$12))*(INDEX(Annahmen!$B$96:$F$96,F$12+1)-INDEX(Annahmen!$B$96:$F$96,F$12))/(INDEX(Annahmen!$B$80:$F$80,F$12+1)-INDEX(Annahmen!$B$80:$F$80,F$12)) -> 0 | G26: =INDEX(Annahmen!$B$96:$F$96,G$12)+(G$7-INDEX(Annahmen!$B$80:$F$80,G$12))*(INDEX(Annahmen!$B$96:$F$96,G$12+1)-INDEX(Annahmen!$B$96:$F$96,G$12))/(INDEX(Annahmen!$B$80:$F$80,G$12+1)-INDEX(Annahmen!$B$80:$F$80,G$12)) -> 0 | H26: =INDEX(Annahmen!$B$96:$F$96,H$12)+(H$7-INDEX(Annahmen!$B$80:$F$80,H$12))*(INDEX(Annahmen!$B$96:$F$96,H$12+1)-INDEX(Annahmen!$B$96:$F$96,H$12))/(INDEX(Annahmen!$B$80:$F$80,H$12+1)-INDEX(Annahmen!$B$80:$F$80,H$12)) -> 0 | I26: =INDEX(Annahmen!$B$96:$F$96,I$12)+(I$7-INDEX(Annahmen!$B$80:$F$80,I$12))*(INDEX(Annahmen!$B$96:$F$96,I$12+1)-INDEX(Annahmen!$B$96:$F$96,I$12))/(INDEX(Annahmen!$B$80:$F$80,I$12+1)-INDEX(Annahmen!$B$80:$F$80,I$12)) -> 0 | ... AK26: =INDEX(Annahmen!$B$96:$F$96,AK$12)+(AK$7-INDEX(Annahmen!$B$80:$F$80,AK$12))*(INDEX(Annahmen!$B$96:$F$96,AK$12+1)-INDEX(Annahmen!$B$96:$F$96,AK$12))/(INDEX(Annahmen!$B$80:$F$80,AK$12+1)-INDEX(Annahmen!$B$80:$F$80,AK$12)) -> 9066.6667
A27: Marketing (Barmittel) | B27: =INDEX(Annahmen!$B$97:$F$97,B$12)+(B$7-INDEX(Annahmen!$B$80:$F$80,B$12))*(INDEX(Annahmen!$B$97:$F$97,B$12+1)-INDEX(Annahmen!$B$97:$F$97,B$12))/(INDEX(Annahmen!$B$80:$F$80,B$12+1)-INDEX(Annahmen!$B$80:$F$80,B$12)) -> 150 | C27: =INDEX(Annahmen!$B$97:$F$97,C$12)+(C$7-INDEX(Annahmen!$B$80:$F$80,C$12))*(INDEX(Annahmen!$B$97:$F$97,C$12+1)-INDEX(Annahmen!$B$97:$F$97,C$12))/(INDEX(Annahmen!$B$80:$F$80,C$12+1)-INDEX(Annahmen!$B$80:$F$80,C$12)) -> 161.26398 | D27: =INDEX(Annahmen!$B$97:$F$97,D$12)+(D$7-INDEX(Annahmen!$B$80:$F$80,D$12))*(INDEX(Annahmen!$B$97:$F$97,D$12+1)-INDEX(Annahmen!$B$97:$F$97,D$12))/(INDEX(Annahmen!$B$80:$F$80,D$12+1)-INDEX(Annahmen!$B$80:$F$80,D$12)) -> 178.51491 | E27: =INDEX(Annahmen!$B$97:$F$97,E$12)+(E$7-INDEX(Annahmen!$B$80:$F$80,E$12))*(INDEX(Annahmen!$B$97:$F$97,E$12+1)-INDEX(Annahmen!$B$97:$F$97,E$12))/(INDEX(Annahmen!$B$80:$F$80,E$12+1)-INDEX(Annahmen!$B$80:$F$80,E$12)) -> 199.09467 | F27: =INDEX(Annahmen!$B$97:$F$97,F$12)+(F$7-INDEX(Annahmen!$B$80:$F$80,F$12))*(INDEX(Annahmen!$B$97:$F$97,F$12+1)-INDEX(Annahmen!$B$97:$F$97,F$12))/(INDEX(Annahmen!$B$80:$F$80,F$12+1)-INDEX(Annahmen!$B$80:$F$80,F$12)) -> 222.18587 | G27: =INDEX(Annahmen!$B$97:$F$97,G$12)+(G$7-INDEX(Annahmen!$B$80:$F$80,G$12))*(INDEX(Annahmen!$B$97:$F$97,G$12+1)-INDEX(Annahmen!$B$97:$F$97,G$12))/(INDEX(Annahmen!$B$80:$F$80,G$12+1)-INDEX(Annahmen!$B$80:$F$80,G$12)) -> 247.34455 | H27: =INDEX(Annahmen!$B$97:$F$97,H$12)+(H$7-INDEX(Annahmen!$B$80:$F$80,H$12))*(INDEX(Annahmen!$B$97:$F$97,H$12+1)-INDEX(Annahmen!$B$97:$F$97,H$12))/(INDEX(Annahmen!$B$80:$F$80,H$12+1)-INDEX(Annahmen!$B$80:$F$80,H$12)) -> 276.01835 | I27: =INDEX(Annahmen!$B$97:$F$97,I$12)+(I$7-INDEX(Annahmen!$B$80:$F$80,I$12))*(INDEX(Annahmen!$B$97:$F$97,I$12+1)-INDEX(Annahmen!$B$97:$F$97,I$12))/(INDEX(Annahmen!$B$80:$F$80,I$12+1)-INDEX(Annahmen!$B$80:$F$80,I$12)) -> 306.57137 | ... AK27: =INDEX(Annahmen!$B$97:$F$97,AK$12)+(AK$7-INDEX(Annahmen!$B$80:$F$80,AK$12))*(INDEX(Annahmen!$B$97:$F$97,AK$12+1)-INDEX(Annahmen!$B$97:$F$97,AK$12))/(INDEX(Annahmen!$B$80:$F$80,AK$12+1)-INDEX(Annahmen!$B$80:$F$80,AK$12)) -> 3200
A28: Eigene Veranstaltungen (Nr. 74) | B28: =IF(B5>=Annahmen!$D$145,B8*Annahmen!$D$144/12,0) -> 166.66667 | C28: =IF(C5>=Annahmen!$D$145,C8*Annahmen!$D$144/12,0) -> 166.66667 | D28: =IF(D5>=Annahmen!$D$145,D8*Annahmen!$D$144/12,0) -> 166.66667 | E28: =IF(E5>=Annahmen!$D$145,E8*Annahmen!$D$144/12,0) -> 166.66667 | F28: =IF(F5>=Annahmen!$D$145,F8*Annahmen!$D$144/12,0) -> 166.66667 | G28: =IF(G5>=Annahmen!$D$145,G8*Annahmen!$D$144/12,0) -> 166.66667 | H28: =IF(H5>=Annahmen!$D$145,H8*Annahmen!$D$144/12,0) -> 166.66667 | I28: =IF(I5>=Annahmen!$D$145,I8*Annahmen!$D$144/12,0) -> 166.66667 | ... AK28: =IF(AK5>=Annahmen!$D$145,AK8*Annahmen!$D$144/12,0) -> 1000
A29: CSD-Auftritte (zum Start und Folgejahre) | B29: =IF(B5=Annahmen!$D$136,Annahmen!$D$135,0)+IF(B5=Annahmen!$D$138,Annahmen!$D$137,0)+IF(B5=Annahmen!$D$140,Annahmen!$D$139,0) -> 3500 | C29: =IF(C5=Annahmen!$D$136,Annahmen!$D$135,0)+IF(C5=Annahmen!$D$138,Annahmen!$D$137,0)+IF(C5=Annahmen!$D$140,Annahmen!$D$139,0) -> 0 | D29: =IF(D5=Annahmen!$D$136,Annahmen!$D$135,0)+IF(D5=Annahmen!$D$138,Annahmen!$D$137,0)+IF(D5=Annahmen!$D$140,Annahmen!$D$139,0) -> 0 | E29: =IF(E5=Annahmen!$D$136,Annahmen!$D$135,0)+IF(E5=Annahmen!$D$138,Annahmen!$D$137,0)+IF(E5=Annahmen!$D$140,Annahmen!$D$139,0) -> 0 | F29: =IF(F5=Annahmen!$D$136,Annahmen!$D$135,0)+IF(F5=Annahmen!$D$138,Annahmen!$D$137,0)+IF(F5=Annahmen!$D$140,Annahmen!$D$139,0) -> 0 | G29: =IF(G5=Annahmen!$D$136,Annahmen!$D$135,0)+IF(G5=Annahmen!$D$138,Annahmen!$D$137,0)+IF(G5=Annahmen!$D$140,Annahmen!$D$139,0) -> 0 | H29: =IF(H5=Annahmen!$D$136,Annahmen!$D$135,0)+IF(H5=Annahmen!$D$138,Annahmen!$D$137,0)+IF(H5=Annahmen!$D$140,Annahmen!$D$139,0) -> 0 | I29: =IF(I5=Annahmen!$D$136,Annahmen!$D$135,0)+IF(I5=Annahmen!$D$138,Annahmen!$D$137,0)+IF(I5=Annahmen!$D$140,Annahmen!$D$139,0) -> 0 | ... AK29: =IF(AK5=Annahmen!$D$136,Annahmen!$D$135,0)+IF(AK5=Annahmen!$D$138,Annahmen!$D$137,0)+IF(AK5=Annahmen!$D$140,Annahmen!$D$139,0) -> 0
A30: Einmalkosten | B30: =SUMIF(Annahmen!$C$116:$C$129,B5,Annahmen!$B$116:$B$129) -> 26700 | C30: =SUMIF(Annahmen!$C$116:$C$129,C5,Annahmen!$B$116:$B$129) -> 2700 | D30: =SUMIF(Annahmen!$C$116:$C$129,D5,Annahmen!$B$116:$B$129) -> 11500 | E30: =SUMIF(Annahmen!$C$116:$C$129,E5,Annahmen!$B$116:$B$129) -> 4500 | F30: =SUMIF(Annahmen!$C$116:$C$129,F5,Annahmen!$B$116:$B$129) -> 3000 | G30: =SUMIF(Annahmen!$C$116:$C$129,G5,Annahmen!$B$116:$B$129) -> 2000 | H30: =SUMIF(Annahmen!$C$116:$C$129,H5,Annahmen!$B$116:$B$129) -> 0 | I30: =SUMIF(Annahmen!$C$116:$C$129,I5,Annahmen!$B$116:$B$129) -> 5500 | ... AK30: =SUMIF(Annahmen!$C$116:$C$129,AK5,Annahmen!$B$116:$B$129) -> 0
A31: Kosten gesamt | B31: =SUM(B22:B30) -> 31786.667 | C31: =SUM(C22:C30) -> 4711.8949 | D31: =SUM(D22:D30) -> 13815.757 | E31: =SUM(E22:E30) -> 7060.6474 | F31: =SUM(F22:F30) -> 5797.6876 | G31: =SUM(G22:G30) -> 5035.324 | H31: =SUM(H22:H30) -> 3252.8283 | I31: =SUM(I22:I30) -> 8970.8383 | ... AK31: =SUM(AK22:AK30) -> 34214.414
A33: Ergebnis je Monat | B33: =B19-B31 -> -31786.667 | C33: =C19-C31 -> -4711.8949 | D33: =D19-D31 -> -13815.757 | E33: =E19-E31 -> -7060.6474 | F33: =F19-F31 -> -5797.6876 | G33: =G19-G31 -> -5035.324 | H33: =H19-H31 -> -3252.8283 | I33: =I19-I31 -> -8970.8383 | ... AK33: =AK19-AK31 -> 19514.065
A34: Kumulierte Liquidität | B34: =B33 -> -31786.667 | C34: =B34+C33 -> -36498.562 | D34: =C34+D33 -> -50314.318 | E34: =D34+E33 -> -57374.966 | F34: =E34+F33 -> -63172.653 | G34: =F34+G33 -> -68207.977 | H34: =G34+H33 -> -71460.805 | I34: =H34+I33 -> -80431.644 | J34: =I34+J33 -> -84124.212 | ... AK34: =AJ34+AK33 -> 27079.811
A36: nachrichtlich: Krankenversicherung privat, kumuliert | B36: =Annahmen!$B$154*Annahmen!$B$155 -> 400 | C36: =B36+Annahmen!$B$154*Annahmen!$B$155 -> 800 | D36: =C36+Annahmen!$B$154*Annahmen!$B$155 -> 1200 | E36: =D36+Annahmen!$B$154*Annahmen!$B$155 -> 1600 | F36: =E36+Annahmen!$B$154*Annahmen!$B$155 -> 2000 | G36: =F36+Annahmen!$B$154*Annahmen!$B$155 -> 2400 | H36: =G36+Annahmen!$B$154*Annahmen!$B$155 -> 2800 | I36: =H36+Annahmen!$B$154*Annahmen!$B$155 -> 3200 | J36: =I36+Annahmen!$B$154*Annahmen!$B$155 -> 3600 | ... AK36: =AJ36+Annahmen!$B$154*Annahmen!$B$155 -> 14400
A37: nachrichtlich: Lebenshaltung beider Gründer, kumuliert | B37: =Annahmen!$B$156*Annahmen!$B$155 -> 2200 | C37: =B37+Annahmen!$B$156*Annahmen!$B$155 -> 4400 | D37: =C37+Annahmen!$B$156*Annahmen!$B$155 -> 6600 | E37: =D37+Annahmen!$B$156*Annahmen!$B$155 -> 8800 | F37: =E37+Annahmen!$B$156*Annahmen!$B$155 -> 11000 | G37: =F37+Annahmen!$B$156*Annahmen!$B$155 -> 13200 | H37: =G37+Annahmen!$B$156*Annahmen!$B$155 -> 15400 | I37: =H37+Annahmen!$B$156*Annahmen!$B$155 -> 17600 | J37: =I37+Annahmen!$B$156*Annahmen!$B$155 -> 19800 | ... AK37: =AJ37+Annahmen!$B$156*Annahmen!$B$155 -> 79200
A39: Jahressummen (rechnen sich)
A40: Größe | B40: Jahr 1 | C40: Jahr 2 | D40: Jahr 3 | E40: 36 Monate
A41: MAU im Jahresmittel | B41: =AVERAGE(B7:M7) -> 6077.6584 | C41: =AVERAGE(N7:Y7) -> 36296.191 | D41: =AVERAGE(Z7:AK7) -> 103622.98 | E41: =AVERAGE(B7:AK7) -> 48665.611
A42: Zahlende Nutzer im Mittel | B42: =AVERAGE(B11:M11) -> 50.984133 | C42: =AVERAGE(N11:Y11) -> 1119.5211 | D42: =AVERAGE(Z11:AK11) -> 4188.5159 | E42: =AVERAGE(B11:AK11) -> 1786.3404
A43: Erlöse gesamt | B43: =SUM(B19:M19) -> 4624.8997 | C43: =SUM(N19:Y19) -> 123984.78 | D43: =SUM(Z19:AK19) -> 444855.81 | E43: =SUM(B19:AK19) -> 573465.49
A44: Kosten gesamt | B44: =SUM(B31:M31) -> 97075.424 | C44: =SUM(N31:Y31) -> 137831.27 | D44: =SUM(Z31:AK31) -> 311478.98 | E44: =SUM(B31:AK31) -> 546385.68
A45: Ergebnis | B45: =SUM(B33:M33) -> -92450.525 | C45: =SUM(N33:Y33) -> -13846.493 | D45: =SUM(Z33:AK33) -> 133376.83 | E45: =SUM(B33:AK33) -> 27079.811

Sheet Kennzahlen
A1: Kennzahlen und Abgleich gegen Handbuch B
A2: Alles auf diesem Blatt rechnet sich. Die Abweichungsspalten sind die Selbstkontrolle des Modells.
A4: 1 · Die drei Zahlen, auf die es ankommt
A5: Kennzahl | B5: Pessimistisch | C5: Realistisch | D5: Optimistisch | E5: Anmerkung
A6: Tiefpunkt der Liquiditätskurve | B6: =MIN(Pessimistisch!$B$34:$AK$34) -> -145217.21 | C6: =MIN(Realistisch!$B$34:$AK$34) -> -126877.22 | D6: =MIN(Optimistisch!$B$34:$AK$34) -> -112675.09 | E6: Der tiefste Punkt der kumulierten Kasse. Diese Summe muss finanziert sein, bevor überhaupt etwas zurückfließt.
A7: … erreicht in Monat | B7: =MATCH(MIN(Pessimistisch!$B$34:$AK$34),Pessimistisch!$B$34:$AK$34,0) -> 36 | C7: =MATCH(MIN(Realistisch!$B$34:$AK$34),Realistisch!$B$34:$AK$34,0) -> 27 | D7: =MATCH(MIN(Optimistisch!$B$34:$AK$34),Optimistisch!$B$34:$AK$34,0) -> 20 | E7: gezählt ab T0 — dem Start in der CSD-Saison (Nr. 45)
A8: Break-even (erster Monat mit positivem Monatsergebnis) | B8: =IFERROR(MATCH(TRUE(),INDEX(Pessimistisch!$B$33:$AK$33>0,0),0),0) -> 0 | C8: =IFERROR(MATCH(TRUE(),INDEX(Realistisch!$B$33:$AK$33>0,0),0),0) -> 28 | D8: =IFERROR(MATCH(TRUE(),INDEX(Optimistisch!$B$33:$AK$33>0,0),0),0) -> 21 | E8: 0 bedeutet: kein Break-even innerhalb von 36 Monaten. Gemeint ist das MONATSergebnis, nicht der Ausgleich der aufgelaufenen Verluste.
A9: Monat, in dem die aufgelaufenen Verluste ausgeglichen sind | B9: =IFERROR(MATCH(TRUE(),INDEX(Pessimistisch!$B$34:$AK$34>0,0),0),0) -> 0 | C9: =IFERROR(MATCH(TRUE(),INDEX(Realistisch!$B$34:$AK$34>0,0),0),0) -> 0 | D9: =IFERROR(MATCH(TRUE(),INDEX(Optimistisch!$B$34:$AK$34>0,0),0),0) -> 35 | E9: Die härtere Kennzahl. Bis dahin ist jeder Euro Fremdgeld noch im Spiel.
A11: 2 · Kapitalbedarf
A12: Position | B12: Pessimistisch | C12: Realistisch | D12: Optimistisch | E12: Anmerkung
A13: Finanzierungsbedarf am Tiefpunkt | B13: =-MIN(Pessimistisch!$B$34:$AK$34) -> 145217.21 | C13: =-MIN(Realistisch!$B$34:$AK$34) -> 126877.22 | D13: =-MIN(Optimistisch!$B$34:$AK$34) -> 112675.09 | E13: Betrag ohne Vorzeichen
A14: Rücklage Rechtsvorfall | B14: =Annahmen!$B$152 -> 8000 | C14: =Annahmen!$B$152 -> 8000 | D14: =Annahmen!$B$152 -> 8000 | E14: Handbuch B
A15: Sicherheitspuffer | B15: =-MIN(Pessimistisch!$B$34:$AK$34)*Annahmen!$B$153 -> 29043.443 | C15: =-MIN(Realistisch!$B$34:$AK$34)*Annahmen!$B$153 -> 25375.443 | D15: =-MIN(Optimistisch!$B$34:$AK$34)*Annahmen!$B$153 -> 22535.018
A16: KAPITALBEDARF DER FIRMA | B16: =-MIN(Pessimistisch!$B$34:$AK$34)*(1+Annahmen!$B$153)+Annahmen!$B$152 -> 182260.66 | C16: =-MIN(Realistisch!$B$34:$AK$34)*(1+Annahmen!$B$153)+Annahmen!$B$152 -> 160252.66 | D16: =-MIN(Optimistisch!$B$34:$AK$34)*(1+Annahmen!$B$153)+Annahmen!$B$152 -> 143210.11 | E16: Die Zahl, die in einen Businessplan gehört.
A17: nachrichtlich: Krankenversicherung beider Gründer bis Break-even | B17: =Annahmen!$B$154*Annahmen!$B$155*IFERROR(MATCH(TRUE(),INDEX(Pessimistisch!$B$33:$AK$33>0,0),0),36) -> 14400 | C17: =Annahmen!$B$154*Annahmen!$B$155*IFERROR(MATCH(TRUE(),INDEX(Realistisch!$B$33:$AK$33>0,0),0),36) -> 11200 | D17: =Annahmen!$B$154*Annahmen!$B$155*IFERROR(MATCH(TRUE(),INDEX(Optimistisch!$B$33:$AK$33>0,0),0),36) -> 8400 | E17: Fällt PRIVAT an, nicht in der Firma — steht deshalb in keiner Kostentabelle und muss trotzdem bezahlt werden.
A18: Kapitalbedarf einschließlich privater Krankenversicherung | B18: =-MIN(Pessimistisch!$B$34:$AK$34)*(1+Annahmen!$B$153)+Annahmen!$B$152+Annahmen!$B$154*Annahmen!$B$155*IFERROR(MATCH(TRUE(),INDEX(Pessimistisch!$B$33:$AK$33>0,0),0),36) -> 196660.66 | C18: =-MIN(Realistisch!$B$34:$AK$34)*(1+Annahmen!$B$153)+Annahmen!$B$152+Annahmen!$B$154*Annahmen!$B$155*IFERROR(MATCH(TRUE(),INDEX(Realistisch!$B$33:$AK$33>0,0),0),36) -> 171452.66 | D18: =-MIN(Optimistisch!$B$34:$AK$34)*(1+Annahmen!$B$153)+Annahmen!$B$152+Annahmen!$B$154*Annahmen!$B$155*IFERROR(MATCH(TRUE(),INDEX(Optimistisch!$B$33:$AK$33>0,0),0),36) -> 151610.11 | E18: Firmenbedarf plus Krankenversicherung. Die Lebenshaltung folgt in der nächsten Zeile.
A19: nachrichtlich: Lebenshaltung beider Gründer bis Break-even | B19: =Annahmen!$B$156*Annahmen!$B$155*IFERROR(MATCH(TRUE(),INDEX(Pessimistisch!$B$33:$AK$33>0,0),0),36) -> 79200 | C19: =Annahmen!$B$156*Annahmen!$B$155*IFERROR(MATCH(TRUE(),INDEX(Realistisch!$B$33:$AK$33>0,0),0),36) -> 61600 | D19: =Annahmen!$B$156*Annahmen!$B$155*IFERROR(MATCH(TRUE(),INDEX(Optimistisch!$B$33:$AK$33>0,0),0),36) -> 46200 | E19: Fällt PRIVAT an. ANNAHME 1.100 € je Person und Monat (Blatt „Annahmen“, Zeile 156), bis zum ersten Monat mit positivem Ergebnis — danach kann die Firma zumindest einen Teil tragen.
A20: GESAMTBEDARF — Firma, Krankenversicherung und Lebenshaltung (Nr. 38) | B20: =B18+B19 -> 275860.66 | C20: =C18+C19 -> 233052.66 | D20: =D18+D19 -> 197810.11 | E20: Die Zahl, gegen die seit dem 19.09.2026 geplant wird (Nr. 38): der Bedarf der Firma und der beiden Menschen, die sie tragen. Gleich der Gesamtlücke auf dem Blatt „Finanzierungswege“.
A22: 3 · Abgleich gegen Handbuch B — die Selbstkontrolle
A23: WICHTIG VOR DEM LESEN DER ABWEICHUNGEN — Stand 21.09.2026 (A-52). Die Abweichungen unten haben zwei Ursachen, die man auseinanderhalten muss. ERSTENS der JMStV-Schalter: Er steht auf 2 (eID, 1,00 € je Prüfung), Handbuch B rechnet mit einer reinen Altersschätzung zu rund 0,22 €; das sind im realistischen Fall rund 36.000 € mehr Prüfaufwand über 36 Monate. ZWEITENS die Beschlüsse vom 19. und 21.09.2026, die Handbuch B nicht kennt: Code-Prüfung (Nr. 73), CSD zum Start (Nr. 45, 80), eigene Veranstaltungen (Nr. 74), SMS (Nr. 46), Werkzeugabo und Ticketanteil statt bezahlter Sichtbarkeit (Nr. 65, A-55), die berichtigten CSD-Monate und die neue Erlöskette (Nr. 67, A-53). Zusammen vertiefen sie den Tiefpunkt im realistischen Fall von −82.790 € auf −126.877 €. DIE RECHENMECHANIK IST DAVON UNBERÜHRT: Mit Schalter 0 und ohne die Beschlussposten lag der Tiefpunkt am 27.07.2026 bei rund −73.500 € gegen die genannten −71.000 €, also 3,6 % Abweichung. Nachgeprüft am 21.09.2026: Nimmt man alle Änderungen aus A-52 wieder heraus, ergibt sich der alte Kapitalbedarf von 107.349 € auf 19 € genau (Rundung der Erlöskette). Die Zeilen zu Nutzern und Zahlern stimmen weiter auf wenige Prozent mit Handbuch B überein; die großen Abweichungen bei Tiefpunkt, Erlösen und Kosten sind Beschlüsse, keine Rechenfehler. Einzelwirkung jedes Beschlusses: Blatt „Herkunft & Widersprüche“, Abschnitt 5.
A24: Eckwert | B24: Pessimistisch | C24: Realistisch | D24: Optimistisch | E24: Erklärung, wo die Abweichung über 10 % liegt
A25: MAU im Jahresmittel, Jahr 1 | B25: =AVERAGE(Pessimistisch!$B$7:$M$7) -> 1835.3359 | C25: =AVERAGE(Realistisch!$B$7:$M$7) -> 3206.8769 | D25: =AVERAGE(Optimistisch!$B$7:$M$7) -> 6077.6584
A26: … Handbuch B nennt / Abweichung | B26: =FIXED(1800,0)&" / "&IF(1800=0,"—",IF(B25>=1800,"+","")&FIXED((B25-(1800))/ABS(1800)*100,1)&" %") -> 1.800 / +2,0 % | C26: =FIXED(3200,0)&" / "&IF(3200=0,"—",IF(C25>=3200,"+","")&FIXED((C25-(3200))/ABS(3200)*100,1)&" %") -> 3.200 / +0,2 % | D26: =FIXED(6000,0)&" / "&IF(6000=0,"—",IF(D25>=6000,"+","")&FIXED((D25-(6000))/ABS(6000)*100,1)&" %") -> 6.000 / +1,3 %
A27: MAU im Jahresmittel, Jahr 2 | B27: =AVERAGE(Pessimistisch!$N$7:$Y$7) -> 8696.7502 | C27: =AVERAGE(Realistisch!$N$7:$Y$7) -> 15433.959 | D27: =AVERAGE(Optimistisch!$N$7:$Y$7) -> 36296.191
A28: … Handbuch B nennt / Abweichung | B28: =FIXED(8500,0)&" / "&IF(8500=0,"—",IF(B27>=8500,"+","")&FIXED((B27-(8500))/ABS(8500)*100,1)&" %") -> 8.500 / +2,3 % | C28: =FIXED(15500,0)&" / "&IF(15500=0,"—",IF(C27>=15500,"+","")&FIXED((C27-(15500))/ABS(15500)*100,1)&" %") -> 15.500 / -0,4 % | D28: =FIXED(36000,0)&" / "&IF(36000=0,"—",IF(D27>=36000,"+","")&FIXED((D27-(36000))/ABS(36000)*100,1)&" %") -> 36.000 / +0,8 %
A29: MAU im Jahresmittel, Jahr 3 | B29: =AVERAGE(Pessimistisch!$Z$7:$AK$7) -> 21514.8 | C29: =AVERAGE(Realistisch!$Z$7:$AK$7) -> 42272.149 | D29: =AVERAGE(Optimistisch!$Z$7:$AK$7) -> 103622.98
A30: … Handbuch B nennt / Abweichung | B30: =FIXED(22000,0)&" / "&IF(22000=0,"—",IF(B29>=22000,"+","")&FIXED((B29-(22000))/ABS(22000)*100,1)&" %") -> 22.000 / -2,2 % | C30: =FIXED(42000,0)&" / "&IF(42000=0,"—",IF(C29>=42000,"+","")&FIXED((C29-(42000))/ABS(42000)*100,1)&" %") -> 42.000 / +0,6 % | D30: =FIXED(105000,0)&" / "&IF(105000=0,"—",IF(D29>=105000,"+","")&FIXED((D29-(105000))/ABS(105000)*100,1)&" %") -> 105.000 / -1,3 %
A31: Zahlende Nutzer im Mittel, Jahr 2 | B31: =AVERAGE(Pessimistisch!$N$11:$Y$11) -> 125.23178 | C31: =AVERAGE(Realistisch!$N$11:$Y$11) -> 341.86879 | D31: =AVERAGE(Optimistisch!$N$11:$Y$11) -> 1119.5211
A32: … Handbuch B nennt / Abweichung | B32: =FIXED(128,0)&" / "&IF(128=0,"—",IF(B31>=128,"+","")&FIXED((B31-(128))/ABS(128)*100,1)&" %") -> 128 / -2,2 % | C32: =FIXED(341,0)&" / "&IF(341=0,"—",IF(C31>=341,"+","")&FIXED((C31-(341))/ABS(341)*100,1)&" %") -> 341 / +0,3 % | D32: =FIXED(1116,0)&" / "&IF(1116=0,"—",IF(D31>=1116,"+","")&FIXED((D31-(1116))/ABS(1116)*100,1)&" %") -> 1.116 / +0,3 %
A33: Zahlende Nutzer im Mittel, Jahr 3 | B33: =AVERAGE(Pessimistisch!$Z$11:$AK$11) -> 473.32561 | C33: =AVERAGE(Realistisch!$Z$11:$AK$11) -> 1389.4525 | D33: =AVERAGE(Optimistisch!$Z$11:$AK$11) -> 4188.5159
A34: … Handbuch B nennt / Abweichung | B34: =FIXED(484,0)&" / "&IF(484=0,"—",IF(B33>=484,"+","")&FIXED((B33-(484))/ABS(484)*100,1)&" %") -> 484 / -2,2 % | C34: =FIXED(1386,0)&" / "&IF(1386=0,"—",IF(C33>=1386,"+","")&FIXED((C33-(1386))/ABS(1386)*100,1)&" %") -> 1.386 / +0,2 % | D34: =FIXED(4200,0)&" / "&IF(4200=0,"—",IF(D33>=4200,"+","")&FIXED((D33-(4200))/ABS(4200)*100,1)&" %") -> 4.200 / -0,3 %
A35: Tiefpunkt der Liquiditätskurve | B35: =MIN(Pessimistisch!$B$34:$AK$34) -> -145217.21 | C35: =MIN(Realistisch!$B$34:$AK$34) -> -126877.22 | D35: =MIN(Optimistisch!$B$34:$AK$34) -> -112675.09 | E35: Seit A-52 in allen drei Fällen deutlich tiefer — Grund sind die Beschlüsse (Kasten oben), nicht die Rechnung. Der Widerspruch in Handbuch B bleibt: Pessimistisch nennt es 105.000 €, obwohl das eigene 36-Monats-Ergebnis nur −90.400 € beträgt; die Differenz entspricht fast genau der privaten Krankenversicherung (14.400 €). Siehe Widerspruch 2.
A36: … Handbuch B nennt / Abweichung | B36: =FIXED(-105000,0)&" / "&IF(-105000=0,"—",IF(B35>=-105000,"+","")&FIXED((B35-(-105000))/ABS(-105000)*100,1)&" %") -> -105.000 / -38,3 % | C36: =FIXED(-71000,0)&" / "&IF(-71000=0,"—",IF(C35>=-71000,"+","")&FIXED((C35-(-71000))/ABS(-71000)*100,1)&" %") -> -71.000 / -78,7 % | D36: =FIXED(-55000,0)&" / "&IF(-55000=0,"—",IF(D35>=-55000,"+","")&FIXED((D35-(-55000))/ABS(-55000)*100,1)&" %") -> -55.000 / -104,9 %
A37: Erlöse gesamt über 36 Monate | B37: =SUM(Pessimistisch!$B$19:$AK$19) -> 77192.965 | C37: =SUM(Realistisch!$B$19:$AK$19) -> 205684.45 | D37: =SUM(Optimistisch!$B$19:$AK$19) -> 573465.49 | E37: Seit A-52: Werkzeugabo und Ticketanteil statt Ortspartnerschaften und Ticketing (Nr. 65, A-55) — deutlich weniger als in Handbuch B; dafür bringt die Erlöskette je Zahler rund 2,4 % mehr (Web-Anteil 60 %). Die Reichweitenschwellen aus Handbuch B (8.000 und 20.000 MAU) gelten weiter, deshalb bleibt der pessimistische Fall nahe am Handbuchwert.
A38: … Handbuch B nennt / Abweichung | B38: =FIXED(77400,0)&" / "&IF(77400=0,"—",IF(B37>=77400,"+","")&FIXED((B37-(77400))/ABS(77400)*100,1)&" %") -> 77.400 / -0,3 % | C38: =FIXED(227900,0)&" / "&IF(227900=0,"—",IF(C37>=227900,"+","")&FIXED((C37-(227900))/ABS(227900)*100,1)&" %") -> 227.900 / -9,7 % | D38: =FIXED(671700,0)&" / "&IF(671700=0,"—",IF(D37>=671700,"+","")&FIXED((D37-(671700))/ABS(671700)*100,1)&" %") -> 671.700 / -14,6 %
A39: Kosten gesamt über 36 Monate | B39: =SUM(Pessimistisch!$B$31:$AK$31) -> 222410.18 | C39: =SUM(Realistisch!$B$31:$AK$31) -> 313818.77 | D39: =SUM(Optimistisch!$B$31:$AK$31) -> 546385.68 | E39: Das Modell rechnet Position für Position aus der Kostenstaffel. Handbuch B nennt in den Szenariotabellen abweichende Summen (Widerspruch 3). Seit A-52 kommen hinzu: Code-Prüfung, Testgeräte, CSD zum Start, eigene Veranstaltungen und SMS.
A40: … Handbuch B nennt / Abweichung | B40: =FIXED(167800,0)&" / "&IF(167800=0,"—",IF(B39>=167800,"+","")&FIXED((B39-(167800))/ABS(167800)*100,1)&" %") -> 167.800 / +32,5 % | C40: =FIXED(215900,0)&" / "&IF(215900=0,"—",IF(C39>=215900,"+","")&FIXED((C39-(215900))/ABS(215900)*100,1)&" %") -> 215.900 / +45,4 % | D40: =FIXED(430400,0)&" / "&IF(430400=0,"—",IF(D39>=430400,"+","")&FIXED((D39-(430400))/ABS(430400)*100,1)&" %") -> 430.400 / +26,9 %
A42: 4 · Was der JMStV-Schalter kostet
A43: Größe | B43: Pessimistisch | C43: Realistisch | D43: Optimistisch | E43: Anmerkung
A44: Altersprüfungen über 36 Monate | B44: =SUM(Pessimistisch!$B$9:$AK$9) -> 56919.385 | C44: =SUM(Realistisch!$B$9:$AK$9) -> 102933.53 | D44: =SUM(Optimistisch!$B$9:$AK$9) -> 235846.14 | E44: entspricht den Neuregistrierungen — jede Registrierung wird genau einmal geprüft
A45: davon Stufe 2 (volle Identifizierung nach AVS-Raster) | B45: =SUM(Pessimistisch!$B$9:$AK$9)*Annahmen!$B$110 -> 19921.785 | C45: =SUM(Realistisch!$B$9:$AK$9)*Annahmen!$B$110 -> 36026.734 | D45: =SUM(Optimistisch!$B$9:$AK$9)*Annahmen!$B$110 -> 82546.148 | E45: nur wer den privaten expliziten Bereich betritt — Anteil im Blatt „Annahmen“ einstellbar
A46: Prüfkosten gesamt bei der aktuellen Schalterstellung | B46: =SUM(Pessimistisch!$B$24:$AK$24) -> 32444.049 | C46: =SUM(Realistisch!$B$24:$AK$24) -> 58672.11 | D46: =SUM(Optimistisch!$B$24:$AK$24) -> 134432.3 | E46: Stufe 1 für alle plus Stufe 2 für den eingestellten Anteil
A48: Vergleich der vier Wege — Prüfkosten über 36 Monate, realistisches Szenario
A49: Weg für Stufe 2 | B49: Preis je Prüfung | C49: Prüfkosten über 36 Monate | D49: Kapitalbedarf der Firma (realistisch) — NÄHERUNG, siehe Zeile 54 | E49: Einordnung
A50: 0 — nicht erforderlich (Rechtsfrage fällt zu unseren Gunsten aus) | B50: 0 | C50: =SUM(Realistisch!$B$9:$AK$9)*Annahmen!$B$105+SUM(Realistisch!$B$9:$AK$9)*Annahmen!$B$110*0 -> 22645.376 | D50: =$C$16+(SUMPRODUCT((Realistisch!$B$5:$AK$5<=$C$7)*Realistisch!$B$9:$AK$9)*(Annahmen!$B$105+Annahmen!$B$110*0)-SUMPRODUCT((Realistisch!$B$5:$AK$5<=$C$7)*Realistisch!$B$24:$AK$24))*(1+Annahmen!$B$153) -> 140232.7 | E50: Nur Stufe 1 für alle. Die günstigste Möglichkeit, und sie hängt an einer einzigen Rechtsfrage: Gilt § 4 Abs. 2 JMStV auch für den beidseitig freigegebenen privaten Austausch zwischen zwei erwachsenen Nutzern, oder nur für das, was der Anbieter selbst zugänglich macht? Gehört als erste Frage in den Anwaltstermin.
A51: 1 — EUDI-Wallet („d-you“) | B51: =Annahmen!$B$106 -> 0.15 | C51: =SUM(Realistisch!$B$9:$AK$9)*Annahmen!$B$105+SUM(Realistisch!$B$9:$AK$9)*Annahmen!$B$110*Annahmen!$B$106 -> 28049.386 | D51: =$C$16+(SUMPRODUCT((Realistisch!$B$5:$AK$5<=$C$7)*Realistisch!$B$9:$AK$9)*(Annahmen!$B$105+Annahmen!$B$110*Annahmen!$B$106)-SUMPRODUCT((Realistisch!$B$5:$AK$5<=$C$7)*Realistisch!$B$24:$AK$24))*(1+Annahmen!$B$153) -> 143235.7 | E51: Ab 02.01.2027 kostenlos für alle in Deutschland, mit Altersnachweis; der Dienst erfährt nur „Altersgrenze erfüllt“ (A-53). Zum geplanten Start (Nr. 45) rund zweieinhalb Jahre im Feld. Der Preis ist geschätzt; die Richtung ist belegt.
A52: 2 — eID des Personalausweises | B52: =Annahmen!$B$107 -> 1 | C52: =SUM(Realistisch!$B$9:$AK$9)*Annahmen!$B$105+SUM(Realistisch!$B$9:$AK$9)*Annahmen!$B$110*Annahmen!$B$107 -> 58672.11 | D52: =$C$16+(SUMPRODUCT((Realistisch!$B$5:$AK$5<=$C$7)*Realistisch!$B$9:$AK$9)*(Annahmen!$B$105+Annahmen!$B$110*Annahmen!$B$107)-SUMPRODUCT((Realistisch!$B$5:$AK$5<=$C$7)*Realistisch!$B$24:$AK$24))*(1+Annahmen!$B$153) -> 160252.66 | E52: Vom AVS-Raster der KJM ausdrücklich als Weg der persönlichen Identifizierung genannt. Vollautomatisch, in Sekunden, ohne Videokonferenz. VOREINGESTELLT.
A53: 3 — VideoIdent / AutoIdent | B53: =Annahmen!$B$108 -> 3.5 | C53: =SUM(Realistisch!$B$9:$AK$9)*Annahmen!$B$105+SUM(Realistisch!$B$9:$AK$9)*Annahmen!$B$110*Annahmen!$B$108 -> 148738.95 | D53: =$C$16+(SUMPRODUCT((Realistisch!$B$5:$AK$5<=$C$7)*Realistisch!$B$9:$AK$9)*(Annahmen!$B$105+Annahmen!$B$110*Annahmen!$B$108)-SUMPRODUCT((Realistisch!$B$5:$AK$5<=$C$7)*Realistisch!$B$24:$AK$24))*(1+Annahmen!$B$153) -> 210302.54 | E53: Der teuerste Weg. Belegt: Banken zahlen derzeit 7–8 € je Vorgang, erwartet wird ein Rückgang auf etwa 2 €. Nur nötig, wenn Anwalt oder KJM die günstigeren Wege ausschließen.
A54: NACHRECHNUNG 21.09.2026 (A-52) — ersetzt die vom 16.09.2026 (A-39): Die Spalte „Kapitalbedarf der Firma“ oben ist eine NÄHERUNG. Sie rechnet die Prüfkosten nur bis zum Tiefpunkt der AKTUELLEN Schalterstellung um; verschiebt ein anderer Weg den Tiefpunkt, weicht sie ab. Vollständig nachgerechnet — Schalter umgestellt, alles neu berechnet, mit allen Beschlüssen vom September: Weg 0 = 143.397 € · Weg 1 = 145.888 € · Weg 2 = 160.253 € · Weg 3 = 245.841 €; erster Monat mit Überschuss 26 · 26 · 28 · keiner innerhalb von 36 Monaten. Stand 16.09.2026 war: 95.258 · 97.003 · 107.349 · 166.548 €. Die Spanne zwischen Weg 0 und Weg 3 wächst auf rund 102.000 €, und mit Weg 3 trägt sich die Firma im realistischen Fall in drei Jahren nicht. Für genaue Werte den Schalter im Blatt „Annahmen“ (Zeile 109) umstellen und oben Zeile 16 ablesen.
A55: LESEHILFE ZU PUNKT 4: Handbuch B enthält diese Frage überhaupt nicht. Seine Kostenstaffel setzt eine Altersprüfung an, die zurückgerechnet 0,22 € je Vorgang kostet — das ist eine automatisierte Altersschätzung. Zwischen dem teuersten und dem günstigsten der vier Wege liegen im realistischen Szenario rund 126.000 € Prüfkosten über 36 Monate. Vier Dinge entschärfen die Zahl, und alle vier sind belegt: ERSTENS ist die Identifizierung nach dem AVS-Raster EINMALIG je Person — Rückkehrer kosten nichts, nur echte Neuzugänge. ZWEITENS nennt das Raster mehrere zulässige Wege, darunter die eID des Personalausweises; es verlangt nicht das teuerste Verfahren. DRITTENS gibt es die staatliche Brieftasche „d-you“ mit Altersnachweis ab 02.01.2027 kostenlos, rund zweieinhalb Jahre vor dem geplanten Start (Nr. 45). VIERTENS erkennt die KJM nach A-53 die Altersschätzung per Gesicht als Identifizierungsmodul an. Hinzu kommt der Architekturhebel: Nach der Zonenlogik aus A-37 braucht nur die volle Identifizierung, wer den privaten expliziten Bereich betritt.
A57: 5 · Empfindlichkeit — welcher Hebel wie stark wirkt
A58: Hebel | B58: Wirkung laut Handbuch B | E58: Wie man es hier selbst prüft
A59: Preis 20 % höher | B59: Break-even zwei Monate früher. Wirkung gering, Risiko für die Positionierung hoch. | E59: Annahmen, Abschnitt 2a: die acht Preise in den Zeilen 31 bis 34 um 20 % erhöhen. Nachgerechnet 21.09.2026: Break-even in Monat 26 statt 28, Kapitalbedarf der Firma −9.100 € (realistisch) — deckt sich mit Handbuch B.
A60: Konversion 1,5 statt 2,8 % | B60: Break-even sieben Monate später, Kapitalbedarf +30.000 €. | E60: Annahmen, Zeile „Zielkonversion Jahr 3“ senken.
A61: Nutzerwachstum halbiert | B61: Break-even zwölf bis fünfzehn Monate später, Kapitalbedarf +60.000 €. | E61: Annahmen, die drei MAU-Zeilen halbieren.
A62: Fixkosten 25 % niedriger | B62: Break-even drei Monate früher — aber die Pflichtpositionen sind nicht kürzbar. | E62: Annahmen, Kostenstaffel. Der Block „Pflichtpositionen“ ist per Definition nicht kürzbar.
A63: Altersprüfung im Identverfahren | B63: in Handbuch B nicht betrachtet | E63: Annahmen, Zeile 109 (Schalter). Voreingestellt ist 2 (eID). Siehe Punkt 4 — der größte Hebel im Modell: Weg 3 statt 2 kostet rund 85.600 € mehr Kapitalbedarf der Firma.
A64: Anteil PRO 20 statt 30 % | B64: in Handbuch B nicht betrachtet — seit Nr. 48 und 67 die unsicherste Erlösannahme | E64: Annahmen, Zeile 36. Nachgerechnet: Kapitalbedarf der Firma +4.700 €, Break-even Monat 30 statt 28 (realistisch). Bei 10 % PRO: +10.900 €, Monat 32.
A65: Web-Anteil 40 statt 60 % | B65: Handbuch B: die Verschiebung von 40 auf 70 % Web bringt bei 1.000 Abonnenten rund 3.300 € im Jahr | E65: Annahmen, Zeile 41. Nachgerechnet: +1.400 € Kapitalbedarf; 80 % statt 60 %: −1.300 €. Wirkt über den Nettoerlös je Zahler.
A66: Code-Prüfung am Rand der Spanne | B66: in Handbuch B nicht enthalten (Nr. 73) | E66: Annahmen, Zeile 128. Untergrenze 11.880 €: −8.400 €; Obergrenze 25.920 €: +8.400 € Kapitalbedarf.
A67: Eigene Veranstaltungen insgesamt statt je Stadt | B67: in Handbuch B nicht enthalten (Nr. 74) | E67: Nur über die Formel prüfbar: Zeile 28 der Szenarioblätter ohne den Faktor „Städte“. Nachgerechnet: −3.200 € Kapitalbedarf.
A69: 6 · Wie viele Zahler es braucht (A-52)
A70: Ausbaustand | B70: Laufende Kosten je Monat (Staffel) | C70: Nötige Zahler | D70: Zahler bei Zielkonversion (realistisch) | E70: Lesehilfe
A71: ="bei "&FIXED(Annahmen!C80,0)&" MAU" -> bei 5.000 MAU | B71: =Annahmen!C98 -> 2260 | C71: =ROUNDUP(B71/Annahmen!$B$51,0) -> 299 | D71: =ROUND(Annahmen!C80*Annahmen!$C$23,0) -> 180 | E71: ="Aboerlöse allein decken "&FIXED(D71/C71*100,0)&" % der laufenden Kosten — sobald die Zielkonversion von "&FIXED(Annahmen!$C$23*100,1)&" % erreicht ist." -> Aboerlöse allein decken 60 % der laufenden Kosten — sobald die Zielkonversion von 3,6 % erreicht ist.
A72: ="bei "&FIXED(Annahmen!D80,0)&" MAU" -> bei 12.000 MAU | B72: =Annahmen!D98 -> 3100 | C72: =ROUNDUP(B72/Annahmen!$B$51,0) -> 411 | D72: =ROUND(Annahmen!D80*Annahmen!$C$23,0) -> 432 | E72: ="Aboerlöse allein decken "&FIXED(D72/C72*100,0)&" % der laufenden Kosten — sobald die Zielkonversion von "&FIXED(Annahmen!$C$23*100,1)&" % erreicht ist." -> Aboerlöse allein decken 105 % der laufenden Kosten — sobald die Zielkonversion von 3,6 % erreicht ist.
A73: ="bei "&FIXED(Annahmen!E80,0)&" MAU" -> bei 20.000 MAU | B73: =Annahmen!E98 -> 5800 | C73: =ROUNDUP(B73/Annahmen!$B$51,0) -> 768 | D73: =ROUND(Annahmen!E80*Annahmen!$C$23,0) -> 720 | E73: ="Aboerlöse allein decken "&FIXED(D73/C73*100,0)&" % der laufenden Kosten — sobald die Zielkonversion von "&FIXED(Annahmen!$C$23*100,1)&" % erreicht ist." -> Aboerlöse allein decken 94 % der laufenden Kosten — sobald die Zielkonversion von 3,6 % erreicht ist.
A74: ="bei "&FIXED(Annahmen!F80,0)&" MAU" -> bei 50.000 MAU | B74: =Annahmen!F98 -> 10750 | C74: =ROUNDUP(B74/Annahmen!$B$51,0) -> 1423 | D74: =ROUND(Annahmen!F80*Annahmen!$C$23,0) -> 1800 | E74: ="Aboerlöse allein decken "&FIXED(D74/C74*100,0)&" % der laufenden Kosten — sobald die Zielkonversion von "&FIXED(Annahmen!$C$23*100,1)&" % erreicht ist." -> Aboerlöse allein decken 126 % der laufenden Kosten — sobald die Zielkonversion von 3,6 % erreicht ist.
A75: Handbuch B nennt | B75: — | C75: 253 | D75: — | E75: „253 Abonnenten decken die Fixkosten“ — bei 7,38 € sind das 1.867 € im Monat. Welche Kosten gemeint sind, sagt Handbuch B nicht; keine Spalte der Staffel ergibt diesen Betrag. Hier deshalb die ganze Staffelsumme je Ausbaustand, geteilt durch den Nettoerlös je Zahler — ohne Einmalkosten, CSD und eigene Veranstaltungen.
A77: WIE MAN DAS LIEST: Die Zahl der Zahler steigt mit jedem Ausbaustand, weil die Kosten mitwachsen. Entscheidend ist der Abstand zur rechten Spalte: Erst ab rund 12.000 aktiven Nutzern tragen die Abos allein die laufenden Kosten, und bei 20.000 kippt es kurz zurück, weil dort die Moderationskraft beginnt. Die übrigen vier Erlösquellen sind in dieser Tabelle bewusst nicht enthalten — sie sind die Reserve, nicht die Grundlage.

Sheet Finanzierungswege
A1: Sechs Wege, die Lücke zu schließen
A2: Vorgabe Henry, 27.07.2026. Dieses Blatt EMPFIEHLT NICHTS. Es stellt gegenüber — auch das, was ein Weg mit den Gründern macht. Fortgeschrieben am 26.09.2026 (Nr. 90): Abschnitt 7 nennt die Reserve, auf die die Finanzierungsfolge auslegen muss.
A4: 1 · Die Lücke, um die es geht
A5: Größe | B5: Pessimistisch | C5: Realistisch | D5: Optimistisch | E5: Herkunft
A6: Kapitalbedarf der Firma | B6: =Kennzahlen!B$16 -> 182260.66 | C6: =Kennzahlen!C$16 -> 160252.66 | D6: =Kennzahlen!D$16 -> 143210.11 | E6: Blatt „Kennzahlen“, Punkt 2
A7: Lebenshaltung je Gründer und Monat | B7: =Annahmen!$B$156 -> 1100 | C7: =Annahmen!$B$156 -> 1100 | D7: =Annahmen!$B$156 -> 1100 | E7: rechnet sich seit A-52 aus dem Blatt „Annahmen“, Zeile 156 (dort der Stellhebel). 1.100 € entspricht dem Gründungsstipendium Niedersachsen; KfW-Studienkredit deckt höchstens 650 €, EXIST für Studierende 1.000 €.
A8: Monate ohne Gehalt (bis Break-even) | B8: =IFERROR(MATCH(TRUE(),INDEX(Pessimistisch!$B$33:$AK$33>0,0),0),36) -> 36 | C8: =IFERROR(MATCH(TRUE(),INDEX(Realistisch!$B$33:$AK$33>0,0),0),36) -> 28 | D8: =IFERROR(MATCH(TRUE(),INDEX(Optimistisch!$B$33:$AK$33>0,0),0),36) -> 21 | E8: rechnet sich aus dem jeweiligen Szenario
A9: Lebenshaltung beider Gründer bis Break-even | B9: =B7*Annahmen!$B$155*B8 -> 79200 | C9: =C7*Annahmen!$B$155*C8 -> 61600 | D9: =D7*Annahmen!$B$155*D8 -> 46200 | E9: Diese Zahl fehlt in Handbuch B vollständig — dort steht „nicht beziffert“.
A10: Krankenversicherung beider Gründer bis Break-even | B10: =Annahmen!$B$154*Annahmen!$B$155*B8 -> 14400 | C10: =Annahmen!$B$154*Annahmen!$B$155*C8 -> 11200 | D10: =Annahmen!$B$154*Annahmen!$B$155*D8 -> 8400 | E10: Handbuch B, 200 € je Person
A11: GESAMTLÜCKE (Firma + Leben + Krankenversicherung) | B11: =B6+B9+B10 -> 275860.66 | C11: =C6+C9+C10 -> 233052.66 | D11: =D6+D9+D10 -> 197810.11 | E11: Das ist die ehrliche Zahl. Handbuch B nennt nur den Firmenteil. — Beschluss Nr. 90 (26.09.2026): Diese Zahl (realistisch) gilt nach außen; der Abstand zum pessimistischen Fall steht als benannte Reserve in Abschnitt 7.
A13: WARUM DIESE ZEILE WICHTIGER IST ALS ALLES DARÜBER: Handbuch B rechnet den Kapitalbedarf der Firma aus und schreibt bei der Lebenshaltung beider Gründer ausdrücklich „nicht beziffert“. Das war der größte blinde Fleck des Plans. Zwei Menschen können zwei Jahre lang kein Gehalt beziehen — aber sie können nicht zwei Jahre lang nicht essen. Wer nur den Firmenbedarf finanziert, hat rund zwei Drittel des Problems gelöst. Seit dem 19.09.2026 wird gegen die ganze Zahl geplant (Nr. 38); seit A-52 steht sie auch auf dem Blatt „Kennzahlen“, Zeile 20.
A14: 2 · Die sechs Wege im Vergleich
A15: Weg | B15: Was er einbringt | C15: Wofür er verwendbar ist | D15: Was er kostet — in Geld | E15: Was er kostet — an Freiheit | F15: Was passiert, wenn wir abbrechen
A16: (a) Ganz ohne Förderung | B16: Nur Eigenmittel und Erlöse. Nichts von außen. | C16: alles, ohne Auflagen | D16: ="Nichts direkt. Indirekt: Die Firma wächst nur so schnell, wie sie sich selbst trägt. Bei einem Kapitalbedarf von rund "&FIXED(ROUND(C6,-3),0)&" € im realistischen Fall bedeutet das ohne Eigenmittel schlicht: geht nicht." -> Nichts direkt. Indirekt: Die Firma wächst nur so schnell, wie sie sich selbst trägt. Bei einem Kapitalbedarf von rund 160.000 € im realistischen Fall bedeutet das ohne Eigenmittel schlicht: geht nicht. | E16: Nichts. Vollständige Entscheidungsfreiheit, keine Berichte, keine Fristen, kein fremder Blick auf die Bücher. | F16: Nichts bleibt zurück außer der eigenen Zeit. Das ist der einzige Weg ohne Nachspiel — und für viele Gründungen der Grund, ihn trotz allem zu wählen.
A17: (b) Gründungsstipendium Niedersachsen | B17: 1.100 € je Person und Monat, bis zu 10 Monate. Bei zwei Gründern rund 22.000 €. | C17: AUSSCHLIESSLICH Lebensunterhalt. Kein Firmenbudget, keine Sachmittel. | D17: Nichts. Zuschuss, keine Rückzahlung, keine Anteile. | E17: Wohnsitz UND Unternehmenssitz müssen während der gesamten Förderdauer in Niedersachsen liegen — für jede antragstellende Person. Beide ziehen an den Sitz (Nr. 33 und 37, entschieden 19.09.2026; Sitz Niedersachsen oder NRW nach Förderlage). Antrag vor Vorhabenbeginn, Frist nach heutigem Stand 31.03.2027 — für einen Start 2029 braucht es ein Nachfolgeprogramm (R-01 beobachtet das). Begleitung durch eine niedersächsische Einrichtung nötig. Berichtspflichten. | F17: Nichts bleibt zurück. Ein Zuschuss, der zweckentsprechend verwendet wurde, wird nicht zurückgefordert. Das ist der entscheidende Unterschied zu jedem Kredit.
A18: (c) EXIST-Gründungsstipendium | B18: Für Studierende 1.000 € je Person und Monat, dazu Sachmittel und Coaching-Budget. | C18: Lebensunterhalt plus Sachmittel — also mehr als (b). | D18: Nichts. Zuschuss. | E18: SETZT EINE HOCHSCHULEINSCHREIBUNG VORAUS und verlangt, dass zum Förderbeginn noch KEINE Gesellschaft besteht. Das kollidiert direkt mit dem Beschluss, zu T0 zu gründen (Nr. 34: Weg A oder B bleibt bis 2028 offen). Schließt das Landesstipendium (b) aus — beide finanzieren Lebenshaltung. Antrag über eine Hochschule, mehrmonatiges Verfahren. | F18: Nichts bleibt zurück. Aber: Die Gründung wurde dafür um ein bis zwei Jahre verschoben. Diese Zeit kommt nicht wieder.
A19: (d) KfW-Studienkredit | B19: 100 bis 650 € je Person und Monat, höchstens 54.600 € über 14 Semester. | C19: PRIVATER Lebensunterhalt. Kein Firmengeld. Das Geld gehört der Person, nicht der GmbH. | D19: 6,53 % effektiver Jahreszins, Stand 01.04.2026, variabel auf Basis des Sechs-Monats-Euribor und halbjährlich neu festgesetzt. Bei 650 € über 24 Monate je Person entstehen rund 15.600 € Schuld — plus Zinsen, die während des Studiums bereits laufen. | E19: Der Zinssatz ist nicht festgeschrieben. Rückzahlung bis zu 25 Jahre, Raten ab 20 € im Monat. Setzt eine Immatrikulation voraus. Wirkt auf die Krankenversicherung und kann auf Stipendienansprüche angerechnet werden — vor der Aufnahme prüfen. | F19: DIE SCHULD BLEIBT. Vollständig, persönlich, unabhängig davon, ob das Vorhaben je Erlöse hatte. Bei zwei Gründern über 24 Monate sind das rund 31.000 € gemeinsame Privatschuld — bei einem Vorhaben, das an Tor 1 enden kann.
A20: (e) Eigenkapital der Gründer | B20: 0 bis 100.000 €, je nach Familienlage. Einzelheiten in Abschnitt 3. | C20: alles — Stammeinlage, Firmenbudget, Lebenshaltung | D20: Nichts an Zinsen. Aber es ist Geld, das weg sein kann. | E20: Nichts an Auflagen. Dafür entsteht innerhalb der Familie eine Erwartung, die nirgends steht und trotzdem wirkt. Wer Geld von Eltern nimmt, sollte die Bedingungen aufschreiben — auch und gerade dann, wenn niemand danach fragt. | F20: Das Geld ist weg. Bei Familienmitteln ist der Verlust nicht nur finanziell. Diese Frage gehört vor die Zusage, nicht danach.
A21: (f) Business Angel / Pre-Seed | B21: Nach Marktlage 2026 je Angel 25.000 bis 200.000 €; Runden meist 3 bis 8 Angels, gesamt 50.000 bis 500.000 €. | C21: alles — aber gebunden an einen Wachstumsplan | D21: Kein Zins, dafür Anteile: typisch 5 bis 15 % Verwässerung je Angel-Runde. Bei 100.000 € auf eine Frühphasenbewertung wären das grob 10 bis 20 % der Gesellschaft. | E21: Berichtspflichten, meist quartalsweise. Mitsprache bei größeren Entscheidungen. Vor allem aber: eine Erwartung von Wachstum und irgendwann Ausstieg. | F21: Der Angel verliert sein Geld — das ist einkalkuliert. Zurück bleibt eine Gesellschafterstruktur, die eine Fortführung in kleinerem Rahmen erschweren kann.
A23: ZUR EHRLICHKEIT BEI (f): Ein Angel erwartet Wachstum und einen Ausstieg. Cruizy ist so entworfen, dass es Erlöse bewusst begrenzt — kein Werbe-Tracking, kein Datenverkauf, eine Streichliste mit dreizehn dauerhaft abgelehnten Funktionen, Preise glatt statt auf 99 Cent. Das sind keine Übergangsentscheidungen, sondern die Positionierung selbst. Ein Investor, der 10 bis 20 % hält, wird genau diese Punkte irgendwann zur Sprache bringen — nicht aus Bosheit, sondern weil sein Geschäft darin besteht. Handbuch B setzt Angel-Kapital nicht ohne Grund erst ab Monat 24 und nur bei ausdrücklichem Skalierungswunsch an. Wer früher zugreift, verkauft Anteile zum niedrigsten Preis, den das Vorhaben je haben wird — und zugleich die Freiheit, Nein zu sagen.
A24: 3 · Eigenkapitalstufen — was jede Stufe tatsächlich kauft
A25: Die Verbrennungsrate unten rechnet sich aus dem realistischen Szenario: der Fehlbetrag am Tiefpunkt, geteilt durch die Zahl der Monate bis dorthin, zuzüglich Lebenshaltung und Krankenversicherung beider Gründer. Sie ist die einzige ehrliche Umrechnung von Euro in Zeit — und sie fällt deutlich höher aus als der Firmenbedarf allein vermuten lässt, weil zwei Menschen mitfinanziert werden müssen.
A26: Monatliche Gesamtverbrennung (realistisch, inkl. Leben) | B26: =(-MIN(Realistisch!$B$34:$AK$34))/MATCH(MIN(Realistisch!$B$34:$AK$34),Realistisch!$B$34:$AK$34,0)+C7*Annahmen!$B$155+Annahmen!$B$154*Annahmen!$B$155 -> 7299.1561 | C26: ="je Monat, gemittelt bis zum Tiefpunkt (M"&Kennzahlen!C7&") — danach trägt sich die Firma zunehmend selbst" -> je Monat, gemittelt bis zum Tiefpunkt (M27) — danach trägt sich die Firma zunehmend selbst
A28: Eigenkapital | B28: Startbahn in Monaten | C28: Stammeinlage GmbH gedeckt? | D28: Fremdkapital noch nötig? (realistisch) | E28: Was sich am persönlichen Risiko ändert | F28: Praktische Einordnung
A29: 0 | B29: =IF($B$26<=0,0,0/$B$26) -> 0 | C29: Ohne einen Euro Eigenkapital ist die GmbH nicht gründbar — 12.500 € Mindesteinzahlung sind Gesetz, nicht Verhandlungssache. | D29: =IF(0>=C11,"nein — vollständig gedeckt","ja, noch "&FIXED(C11-0,0)&" €") -> ja, noch 233.053 € | E29: Kein eigenes Geld im Risiko. Dafür hängt alles an Zusagen Dritter, und jede davon kann ausbleiben. | F29: Rechnerisch kein Start. Realistisch nur denkbar in Verbindung mit (b) oder (c) plus Preisgeldern — und selbst dann sehr eng.
A30: 25000 | B30: =IF($B$26<=0,0,25000/$B$26) -> 3.4250535 | C30: Ja — 25.000 € decken die volle Stammeinlage, davon 12.500 € sofort einzuzahlen. | D30: =IF(25000>=C11,"nein — vollständig gedeckt","ja, noch "&FIXED(C11-25000,0)&" €") -> ja, noch 208.053 € | E30: 25.000 € im Risiko. Bei Familienmitteln: 25.000 €, die im Zweifel nicht zurückkommen. | F30: Die Schwelle, ab der eine GmbH überhaupt entsteht. Für den Betrieb bleibt danach fast nichts übrig — die Startbahn ist kurz.
A31: 50000 | B31: =IF($B$26<=0,0,50000/$B$26) -> 6.8501069 | C31: Ja, mit Reserve. | D31: =IF(50000>=C11,"nein — vollständig gedeckt","ja, noch "&FIXED(C11-50000,0)&" €") -> ja, noch 183.053 € | E31: ="50.000 € im Risiko — rund "&FIXED(50000/C11*100,0)&" % der Gesamtlücke im realistischen Fall." -> 50.000 € im Risiko — rund 21 % der Gesamtlücke im realistischen Fall. | F31: ="Deckt rund "&FIXED(50000/Kennzahlen!C13*100,0)&" % des Finanzierungsbedarfs am Tiefpunkt der Firma — die Lebenshaltung noch nicht mitgerechnet. Nur zusammen mit Stipendium, Preisgeldern und weiterem Kapital denkbar." -> Deckt rund 39 % des Finanzierungsbedarfs am Tiefpunkt der Firma — die Lebenshaltung noch nicht mitgerechnet. Nur zusammen mit Stipendium, Preisgeldern und weiterem Kapital denkbar.
A32: 100000 | B32: =IF($B$26<=0,0,100000/$B$26) -> 13.700214 | C32: Ja, deutlich. | D32: =IF(100000>=C11,"nein — vollständig gedeckt","ja, noch "&FIXED(C11-100000,0)&" €") -> ja, noch 133.053 € | E32: 100.000 € im Risiko — der mit Abstand größte Einzelposten in dieser Übersicht. | F32: ="Deckt im realistischen Fall rund "&FIXED(100000/C11*100,0)&" % der Gesamtlücke. Ohne weiteres Kapital — Stipendium, Preisgelder, Kredit oder Angel — reicht auch das nicht; im pessimistischen Fall fehlen noch "&FIXED(B11-100000,0)&" €." -> Deckt im realistischen Fall rund 43 % der Gesamtlücke. Ohne weiteres Kapital — Stipendium, Preisgelder, Kredit oder Angel — reicht auch das nicht; im pessimistischen Fall fehlen noch 175.861 €.
A34: 4 · Kombinationen, die sich ausschließen oder aneinander stoßen
A35: Kombination | B35: Was kollidiert | C35: Wo es geregelt ist
A36: (b) und (c) gleichzeitig | B36: Landesstipendium und EXIST finanzieren beide den Lebensunterhalt. Doppelbezug ist ausgeschlossen. | C36: A-10, offene Entscheidung Nr. 34
A37: (c) und Gründung zu T0 | B37: EXIST verlangt, dass zum Förderbeginn noch keine Gesellschaft besteht. Der Beschluss vom 26.07.2026 sieht die Gründung zu T0 vor. | C37: offene Entscheidung Nr. 22 gegen Nr. 34
A38: (b) und der Wohnsitz von Nicolas | B38: Das Gründungsstipendium verlangt Wohnsitz und Sitz in Niedersachsen — für jede antragstellende Person. | C38: entschieden 19.09.2026: Beide ziehen an den Sitz (Nr. 33, 37)
A39: Wettbewerbspreise und Social Impact Award | B39: Der Social Impact Award schließt Projekte mit externen Zuschüssen über 6.000 € aus. Ein einziger Gewinn bei STARTUP TEENS (10.000 €) überschreitet das. | C39: A-12, Blatt „Zeitachse & Reihenfolge“
A40: (d) und (b) | B40: Ein Studienkredit kann auf Stipendienansprüche angerechnet werden und wirkt auf den Krankenversicherungsstatus. Vor der Aufnahme klären. | C40: Anwaltsakte B13, offene Entscheidung Nr. 25
A41: (f) und die Streichliste | B41: Ein Angel erwartet Wachstum; die Positionierung begrenzt Erlöse bewusst. Das ist kein Rechtsproblem, sondern ein Zielkonflikt. | C41: Handbuch A, Streichliste · Handbuch B, Kapitalfahrplan
A43: 5 · Weitere Geldquellen jenseits der sechs Wege
A44: Nachtrag vom 27.07.2026. Diese Quellen stehen weder in Handbuch B noch in A-09 oder A-12. Sie sind kein Ersatz für die sechs Wege oben, sondern Ergänzungen — teils erst nach der Gründung nutzbar, teils vorher.
A45: Quelle | B45: Größenordnung | C45: Konditionen und Voraussetzungen | D45: Wann nutzbar | E45: Warum sie hier steht | F45: Haken
A46: Mikromezzaninfonds Deutschland | B46: bis 100.000 €, für Zielgruppen bis 150.000 € | C46: Stille Beteiligung über die mittelständische Beteiligungsgesellschaft des Sitzlandes. Laufzeit 10 Jahre, vierteljährliche ergebnisunabhängige Vergütung von 11 % p. a. mit 3 % Zinszuschuss, Tilgung erst ab Jahr 7 in drei gleichen Raten. Keine Sicherheiten nötig. | D46: nach der Gründung, ab T0 | E46: DIE INTERESSANTESTE ERGÄNZUNG. Sie wirkt bilanziell wie Eigenkapital, verlangt keine Sicherheiten, gibt keine Stimmrechte ab und tilgt erst ab Jahr 7 — also weit nach dem Break-even. Zu den ausdrücklich angesprochenen Zielgruppen gehören gemeinwohlorientierte Unternehmen. | F46: 11 % Vergütung sind teuer, und sie fallen ergebnisunabhängig an — auch in Verlustjahren. Über 10 Jahre auf 100.000 € summiert sich das erheblich.
A47: ERP-Förderkredit Gründung und Nachfolge (077) | B47: abhängig vom Vorhaben | C47: Seit 01.11.2024 Nachfolger der älteren Programme. Wird ohne eigene Besicherung vergeben — mit Ausnahme einer Garantie der Bürgschaftsbank. Der Nachrang der Vorgängerprogramme entfällt. | D47: ab Gründung | E47: Der Standardweg für Fremdkapital ohne Sicherheiten. Ersetzt in der Praxis das früher oft genannte ERP-Kapital für Gründung (058). | F47: Die HAUSBANK entscheidet, nicht die KfW. Ohne Umsatz und ohne Sicherheiten ist die Zusage unwahrscheinlich — Handbuch B sagt dasselbe über das StartGeld.
A48: Bürgschaftsbank Niedersachsen — Classic-Bürgschaft | B48: mindestens 12.000 €, bis 2,0 Mio. € je Kreditnehmereinheit | C48: Ausfallbürgschaft für bis zu 80 % des Kreditbetrags. Antrag NICHT direkt, sondern über die Hausbank. | D48: ab Gründung | E48: Das fehlende Stück zwischen „die Bank will Sicherheiten“ und „wir haben keine“. Ohne Bürgschaft scheitern Gründungskredite meist genau hier. | F48: Läuft über die Hausbank, also über dieselbe Instanz, die ohnehin skeptisch ist. Kostet Provision. Und sie sichert die Bank ab, nicht euch.
A49: INVEST — Zuschuss für Wagniskapital (BAFA) | B49: 15 % Erwerbszuschuss auf die Investition des Angels; 25 % Exitzuschuss auf den Veräußerungsgewinn | C49: Der Zuschuss geht an den INVESTOR, nicht an uns. Wir müssen vorab als förderfähiges Unternehmen anerkannt werden; der Angel stellt seinen Antrag VOR Vertragsschluss. Vollständig digital über das BAFA-Portal. | D49: nur mit Angel (Weg f) | E49: Macht uns für Angels attraktiver, ohne dass wir mehr abgeben — der Staat zahlt einen Teil des Tickets. Der Satz lag 2023 bei 25 % und liegt 2026 bei 15 %. | F49: ACHTUNG: Das Programm ist bis zum 31.12.2026 verlängert. Unser Start liegt frühestens im Sommer 2028, geplant wird ein Jahr später (Nr. 45). Ob es dann noch existiert, ist offen — vor jeder Planung neu prüfen.
A50: Vorverkauf von Jahresabos an die Warteliste | B50: rechnerisch: 500 Jahresabos à 70 € = 35.000 € brutto | C50: Kein Kredit, keine Anteile, keine Zinsen. Geld von genau den Menschen, für die gebaut wird. Nach Nr. 60 als befristete Codes, eingelöst auf der Webseite. | D50: V4, kurz vor T0 | E50: Die einzige Quelle in dieser Übersicht, die zugleich Marktforschung ist: Wer vorab zahlt, hat den Bedarf bewiesen. Und sie passt zur Positionierung besser als jede andere. | F50: RECHTLICH NICHT TRIVIAL. Vorkasse für eine noch nicht existierende Leistung, Widerrufsrecht, Insolvenzrisiko der Käufer, umsatzsteuerliche Behandlung der Anzahlung. Vor jedem Verkauf anwaltlich klären — gehört auf die Anwaltsliste — dort steht es seit dem 22.09.2026 als Frage R16 (Nachtrag 04 zur Anwaltsakte).
A51: Werkzeugabo-Jahresverträge im Voraus (Nr. 65) | B51: bei 10 Werkzeugabos à 29 € (zwei Städte zu je fünf) und Jahreszahlung: rund 2.800 € netto | C51: Handbuch B sieht für Jahresverträge 20 % Nachlass vor; das gilt sinngemäß für das Werkzeugabo. Vorauszahlung statt monatlicher Abbuchung kostet nichts zusätzlich. Nach Nr. 65 ohne Sichtbarkeit. | D51: ab dem zweiten Jahr, wenn das Veranstalterportal steht (F39) und die Reichweite trägt | E51: Verwandelt planbaren Umsatz in sofortige Liquidität — genau in der Phase, in der die Kurve am tiefsten liegt. | F51: Bindet die Partner ein Jahr an ein Produkt, das sich noch beweisen muss. Wer enttäuscht wird, kommt nicht wieder und erzählt es weiter.
A52: Preisgelder aus Wettbewerben | B52: JUGEND GRÜNDET, STARTUP TEENS 7 × 10.000 €, start2grow bis 40.000 €, Startup-Impuls 4 × 25.000 € | C52: Zuschuss ohne Gegenleistung, ohne Rückzahlung, ohne Anteile. | D52: ab sofort — JUGEND GRÜNDET startet am 01.09.2026 | E52: Die günstigste Form von Kapital überhaupt. Vollständige Übersicht in `wettbewerbe.xlsx` (A-12). | F52: Aufwand in Arbeitsstunden statt in Geld. Und: Der Social Impact Award schließt bei über 6.000 € externen Zuschüssen aus — die Reihenfolge zählt.
A53: Crowdfunding | B53: in Handbuch B als Baustein des Kapitalfahrplans M6–10 geführt | C53: Vorverkauf oder Unterstützung, je nach Modell. | D53: erst ab 1.000 Wartelisten-Einträgen | E53: Steht bereits als Aufgabe A-21 im Plan. | F53: Blockiert, bis die Warteliste trägt. Eine gescheiterte Kampagne ist öffentlich und schadet mehr, als das Geld genützt hätte.
A55: 6 · Was dieses Blatt nicht entscheidet
A56: Welcher Weg der richtige ist, hängt an drei Fragen, die keine Tabelle beantwortet: Wie viel Risiko trägt jeder von euch persönlich? Was passiert mit dem Verhältnis zu den Eltern, wenn das Geld weg ist? Und wollt ihr ein Unternehmen bauen, das euch gehört, oder eines, das wächst? Die Zahlen oben sind der Rahmen für dieses Gespräch, nicht sein Ergebnis. Eine Beobachtung sei erlaubt: Die Wege (b), (c) und Preisgelder sind die einzigen, bei denen nach einem Abbruch nichts zurückbleibt. Bei einem Vorhaben mit einem Weiter-oder-Stopp-Tor nach 90 Tagen ist das kein Nebenaspekt.
A58: 7 · Die Reserve nach Beschluss Nr. 90 (26.09.2026)
A59: BESCHLUSS NR. 90 VOM 26.09.2026 — Weg (C): Nach außen wird der realistische Gesamtbedarf genannt. Der Abstand zum pessimistischen Fall wird nicht in die Hauptzahl gerechnet, aber ausdrücklich als Reserve benannt. Dazu der Grundsatz aus der Antwort: „immer lieber etwas zu viel Geld als zu wenig planen" — wo das Modell eine Spanne nennt, muss die Finanzierungsfolge den oberen Rand tragen können, auch wenn geplant wird mit der Mitte.
A60: Größe | B60: Betrag | C60: Was damit gemeint ist
A61: Zielgröße nach außen (realistisch) | B61: =Kennzahlen!C20 -> 233052.66 | C61: Die Zahl in Businessplan, Pitchdeck und Förderpräsentation. Seit Nr. 38 der Gesamtbedarf, nicht der Firmenbedarf.
A62: Pessimistischer Gesamtbedarf | B62: =Kennzahlen!B20 -> 275860.66 | C62: Handbuch B verlangt, gegen dieses Szenario zu planen — es hat mit 40 % die höchste Einzelwahrscheinlichkeit.
A63: BENANNTE RESERVE | B63: =Kennzahlen!B20-Kennzahlen!C20 -> 42807.998 | C63: Der Abstand. Er wird nicht eingesammelt und dann liegen gelassen, sondern in der Finanzierungsfolge als erreichbare Stufe geführt: Zusagen, Kreditlinien oder Eigenmittel, die abrufbar sind, wenn der pessimistische Fall eintritt.
A64: Reserve in Prozent der Zielgröße | B64: =(Kennzahlen!B20-Kennzahlen!C20)/Kennzahlen!C20 -> 0.1836838 | C64: Zur Einordnung gegenüber Geldgebern.
A66: WAS DIE RESERVE NICHT IST: kein zweiter Kapitalbedarf und keine Erhöhung der Zahl nach außen. Weg (B) — pessimistisch als Hauptzahl — wurde ausdrücklich nicht gewählt. Die Reserve ist die Antwort auf die Frage, die ein Förderprüfer stellt, der Handbuch B gelesen hat: „Ihr rechnet realistisch, euer eigenes Handbuch verlangt pessimistisch — was passiert, wenn es so kommt?"
A67: GEPRÜFT AM 26.09.2026 (Teil 3, Nr. 67): Der schlechteste geprüfte Fall des Bezahlstufen-Zuschnitts — PRO-Anteil 15 % statt 30 % und Unterstützerertrag 0,008 statt 0,015 € je MAU — ergibt einen Gesamtbedarf von 254.188 €, also 21.135 € über der Zielgröße. Das liegt innerhalb dieser Reserve. Der Zuschnitt ist damit finanziert, auch wenn er schlechter läuft als angenommen.

Sheet Ist-Werte
A1: Ist-Werte — ab dem ersten realen Monat auszufüllen
A2: Gelb = eintragen. Weiß = rechnet sich. Zuständig: wiederkehrende Aufgabe R-02, monatlich.
A4: SO WIRD DIESES BLATT BENUTZT: Am Monatsende die gelben Zeilen ausfüllen. Die weißen Zeilen vergleichen automatisch mit dem realistischen Szenario. Ab drei Monaten in Folge mit mehr als 25 % Abweichung ist nicht das Ist falsch, sondern der Plan — dann werden die Annahmen angepasst und nicht die Erwartung.
A5: Position | B5: M1 | C5: M2 | D5: M3 | E5: M4 | F5: M5 | G5: M6 | H5: M7 | I5: M8 | J5: M9 | K5: M10 | L5: M11 | M5: M12 | N5: M13 | O5: M14 | P5: M15 | Q5: M16 | R5: M17 | S5: M18 | T5: M19 | U5: M20 | V5: M21 | W5: M22 | X5: M23 | Y5: M24 | Z5: M25 | AA5: M26 | AB5: M27 | AC5: M28 | AD5: M29 | AE5: M30 | AF5: M31 | AG5: M32 | AH5: M33 | AI5: M34 | AJ5: M35 | AK5: M36
A6: Aktive Nutzer im Monat (MAU)
A7: Zahlende Nutzer
A8: Erlöse gesamt
A9: Kosten gesamt
A10: Neuregistrierungen
A12: Plan-MAU (realistisch) | B12: =Realistisch!B7 -> 0 | C12: =Realistisch!C7 -> 274.11914 | D12: =Realistisch!D7 -> 713.44542 | E12: =Realistisch!E7 -> 1248.4372 | F12: =Realistisch!F7 -> 1856.8728 | G12: =Realistisch!G7 -> 2526.4922 | H12: =Realistisch!H7 -> 3249.2871 | I12: =Realistisch!I7 -> 4019.5242 | ... AK12: =Realistisch!AK7 -> 62000
A13: Abweichung MAU | B13: =IF(B12=0,"",(B6-B12)/B12) | C13: =IF(C12=0,"",(C6-C12)/C12) -> -1 | D13: =IF(D12=0,"",(D6-D12)/D12) -> -1 | E13: =IF(E12=0,"",(E6-E12)/E12) -> -1 | F13: =IF(F12=0,"",(F6-F12)/F12) -> -1 | G13: =IF(G12=0,"",(G6-G12)/G12) -> -1 | H13: =IF(H12=0,"",(H6-H12)/H12) -> -1 | I13: =IF(I12=0,"",(I6-I12)/I12) -> -1 | ... AK13: =IF(AK12=0,"",(AK6-AK12)/AK12) -> -1
A14: Plan-Erlöse (realistisch) | B14: =Realistisch!B19 -> 0 | C14: =Realistisch!C19 -> 0 | D14: =Realistisch!D19 -> 0 | E14: =Realistisch!E19 -> 0 | F14: =Realistisch!F19 -> 0 | G14: =Realistisch!G19 -> 0 | H14: =Realistisch!H19 -> 0 | I14: =Realistisch!I19 -> 0 | ... AK14: =Realistisch!AK19 -> 20372.131
A15: Abweichung Erlöse | B15: =IF(B14=0,"",(B8-B14)/B14) | C15: =IF(C14=0,"",(C8-C14)/C14) | D15: =IF(D14=0,"",(D8-D14)/D14) | E15: =IF(E14=0,"",(E8-E14)/E14) | F15: =IF(F14=0,"",(F8-F14)/F14) | G15: =IF(G14=0,"",(G8-G14)/G14) | H15: =IF(H14=0,"",(H8-H14)/H14) | I15: =IF(I14=0,"",(I8-I14)/I14) | ... AK15: =IF(AK14=0,"",(AK8-AK14)/AK14) -> -1
A16: Plan-Ergebnis (realistisch) | B16: =Realistisch!B33 -> -34286.667 | C16: =Realistisch!C33 -> -4494.8165 | D16: =Realistisch!D33 -> -13459.338 | E16: =Realistisch!E33 -> -6594.6028 | F16: =Realistisch!F33 -> -5226.6299 | G16: =Realistisch!G33 -> -4359.8162 | H16: =Realistisch!H33 -> -2495.6425 | I16: =Realistisch!I33 -> -8134.6952 | ... AK16: =Realistisch!AK33 -> 4291.6116
A17: Ist-Ergebnis | B17: =B8-B9 -> 0 | C17: =C8-C9 -> 0 | D17: =D8-D9 -> 0 | E17: =E8-E9 -> 0 | F17: =F8-F9 -> 0 | G17: =G8-G9 -> 0 | H17: =H8-H9 -> 0 | I17: =I8-I9 -> 0 | ... AK17: =AK8-AK9 -> 0
A18: Kumulierte Liquidität (Ist) | B18: =B17 -> 0 | C18: =B18+C17 -> 0 | D18: =C18+D17 -> 0 | E18: =D18+E17 -> 0 | F18: =E18+F17 -> 0 | G18: =F18+G17 -> 0 | H18: =G18+H17 -> 0 | I18: =H18+I17 -> 0 | J18: =I18+J17 -> 0 | ... AK18: =AJ18+AK17 -> 0
A19: Ampel | B19: =IF(B6="","",IF(B13>=-0.1,"grün",IF(B13>=-0.25,"gelb","rot"))) | C19: =IF(C6="","",IF(C13>=-0.1,"grün",IF(C13>=-0.25,"gelb","rot"))) | D19: =IF(D6="","",IF(D13>=-0.1,"grün",IF(D13>=-0.25,"gelb","rot"))) | E19: =IF(E6="","",IF(E13>=-0.1,"grün",IF(E13>=-0.25,"gelb","rot"))) | F19: =IF(F6="","",IF(F13>=-0.1,"grün",IF(F13>=-0.25,"gelb","rot"))) | G19: =IF(G6="","",IF(G13>=-0.1,"grün",IF(G13>=-0.25,"gelb","rot"))) | H19: =IF(H6="","",IF(H13>=-0.1,"grün",IF(H13>=-0.25,"gelb","rot"))) | I19: =IF(I6="","",IF(I13>=-0.1,"grün",IF(I13>=-0.25,"gelb","rot"))) | ... AK19: =IF(AK6="","",IF(AK13>=-0.1,"grün",IF(AK13>=-0.25,"gelb","rot")))

Sheet Herkunft & Widersprüche
A1: Herkunft jeder Zahl — und fünf Widersprüche in Handbuch B
A2: Vor jeder Verwendung nach außen lesen. Handbuch B ist die Wahrheitsquelle; wo es sich selbst widerspricht, steht das hier statt einer stillen Korrektur.
A4: 1 · Die fünf Widersprüche
A5: Alle fünf sind beim Nachrechnen von Handbuch B aufgefallen. Keiner wurde im Modell stillschweigend aufgelöst. Sie stehen hier, weil sie vor dem ersten Förderantrag und vor dem ersten Investorengespräch geklärt sein sollten — dort wird nachgerechnet.
A6: Widerspruch | B6: Was in Handbuch B steht | C6: Was beim Nachrechnen herauskommt | D6: Wie das Modell damit umgeht
A7: 1 · Kostenstaffel bei 50.000 MAU | B7: Die Spalte „50.000 MAU“ wird mit 12.150 € je Monat summiert. | C7: Die Einzelpositionen derselben Spalte ergeben 10.750 €. Es fehlen 1.400 €. Die vier anderen Spalten stimmen auf den Euro genau. | D7: Das Modell rechnet mit den Einzelpositionen. Die Differenz wird auf dem Blatt „Annahmen“ als eigene Zeile ausgewiesen. Naheliegende Erklärung: eine zweite Moderationskraft (3.400 € statt 4.800 €), die bei 50.000 MAU ohnehin plausibel wäre — A-37 rechnet bei 40.000 MAU bereits mit 37 bis 73 Bildern täglich in der menschlichen Warteschlange.
A8: 2 · Tiefpunkt im pessimistischen Fall | B8: Tiefpunkt 105.000 €, zugleich 36-Monats-Ergebnis −90.400 €. | C8: Wenn jedes der drei Jahre negativ ist, kann die Kurve nicht tiefer liegen als ihr Endpunkt. Die Differenz von 14.600 € entspricht fast genau der privaten Krankenversicherung über 36 Monate (14.400 €). | D8: Das Modell weist Firmenbedarf und private Krankenversicherung getrennt aus — so, wie es der Text von Handbuch B selbst verlangt („fällt privat an, nicht in der Firma“). Auf dem Blatt „Kennzahlen“ stehen beide Zahlen untereinander.
A9: 3 · Szenariotabellen gegen Kostenstaffel | B9: Die Szenariotabellen nennen Jahressummen für laufende Kosten und Marketing. | C9: Diese Summen lassen sich aus der eigenen Kostenstaffel nicht herleiten: Das Marketing im pessimistischen Fall liegt über 50 % höher als die Staffel hergibt, die laufenden Kosten im realistischen Jahr 3 rund 12 % darunter. Die beiden Teile von Handbuch B sind offenbar unabhängig voneinander geschätzt worden. | D9: Das Modell rechnet ausschließlich aus der Staffel — sie ist die detailliertere und damit überprüfbare Quelle. Die Abweichung zu den Szenariotabellen steht auf dem Blatt „Kennzahlen“ offen ausgewiesen.
A10: 5 · Startzeitpunkt der App gegen die MAU-Zahlen | B10: Handbuch A stellt die App erst in Monat 10 öffentlich (Phase 2); Monat 8–9 ist eine geschlossene Beta mit 150 Testnutzern. Handbuch B nennt für das erste Jahr im realistischen Fall einen MAU-Jahresmittelwert von 3.200. | C10: Beides zusammen geht nicht auf. Startet die App in Monat 10 und erreicht Ende Monat 12 die genannten 7.500 MAU, liegt der Jahresmittelwert bei etwa 900 statt bei 3.200 — eine Abweichung von rund 72 %. Aufgefallen am 27.07.2026 beim Übereinanderlegen der beiden Zeitrechnungen (A-23). | D10: Das Modell folgt Handbuch B, weil von dort sämtliche Finanzzahlen stammen; der kalibrierte Startmonat ist 2. Der Startmonat steht auf dem Blatt „Annahmen“ als blaues Feld und kann auf 10 gesetzt werden, um die andere Lesart zu sehen. Die Abweichung ist erheblich und gehört vor dem ersten Förderantrag geklärt. Herleitung: `01-steuerung/tor-1-zeitachse-analyse.md` Abschnitt 8. Stand 21.09.2026: Mit Nr. 73 (gebaut wird vor T0) und Nr. 45 (Start in der CSD-Saison) spricht die Beschlusslage für die Lesart des Modells. Aufgelöst ist der Widerspruch erst mit Nr. 88 — der Reihenfolge von Gründung, Prüfungen und Start. Ein Start in Monat 5 oder 10 ändert den Kapitalbedarf im Modell kaum (−1.590 € bzw. −4.232 €), weil die Nutzerzahl zum Jahresende festgehalten ist.
A11: 4 · Zahlende Nutzer im ersten Jahr | B11: Realistisches Szenario: 12 Zahler im Jahresmittel bei Monetarisierungsstart in Monat 14. | C11: Vor Monat 14 kann es keine Zahler geben. Rechnerisch muss das erste Jahr null sein. Es geht um 1.100 € von 227.900 € Gesamterlös — sachlich unerheblich, aber ein Hinweis darauf, dass die Tabellen nicht durchgerechnet, sondern geschätzt sind. | D11: Das Modell setzt vor dem Monetarisierungsstart konsequent null. Dieselbe Beobachtung gilt für das optimistische Szenario, wo das erste Jahr eine höhere Konversion voraussetzen würde als das dritte.
A13: 2 · Herkunft der Annahmen
A14: Gruppe | B14: Was direkt aus Handbuch B stammt | C14: Was abgeleitet oder kalibriert wurde | D14: Was frei angenommen ist
A15: Nutzerentwicklung | B15: MAU-Anker für Ende Jahr 1, 2 und 3 je Szenario; Städtezahl Ende Jahr 3; 30-Tage-Wiederkehr; Eintrittswahrscheinlichkeiten. | C15: Startmonat und die beiden Rampenexponenten sind so KALIBRIERT, dass die Jahresmittel aus Handbuch B getroffen werden — Abweichung höchstens 2,3 %. | D15: Die monatliche Nutzerabwanderung (10 / 8 / 7 %) ist eine Annahme. Sie steht in Handbuch B nicht und bestimmt die Zahl der Neuregistrierungen und damit die Prüfkosten.
A16: Monetarisierung | B16: Monetarisierungsstart je Szenario, Zielkonversion Jahr 3; die Preise, die Laufzeitanteile und der Anteil PRO (30 %) der Erlöskette. Bis zum 21.09.2026 stand hier auch der Nettoerlös von 7,38 € je Zahler als feste Zahl. | C16: Anfangsanteil und Rampendauer der Konversion sind KALIBRIERT auf die Zahler-Jahresmittel der Jahre 2 und 3 — Abweichung höchstens 2,2 %. Seit A-52 rechnet sich der Nettoerlös je Zahler (7,56 €) aus der Kette im Blatt „Annahmen“, Abschnitt 2a. | D16: Seit A-52: der Anteil der Zahlungen über das Web (60 %; Handbuch B rechnet mit 40 %) und die Gebühr des Web-Zahlungsdienstes nach A-53.
A17: Weitere Erlösquellen | B17: Auslösemonate und Schwellen aller vier Nebenquellen; der Erlösmix im Reifezustand (drei Städte, 40.000 MAU, 14.546 € im Monat). | C17: Die Umrechnung in Erlös je MAU beziehungsweise je Partner ist ABGELEITET aus diesem Reifezustand — Handbuch B nennt nur Endwerte, keine Formeln. Seit A-52 rechnen Werkzeugabo und Ticketanteil je Stadt nach dem Veranstaltungskonzept (A-55); die Reichweitenschwellen aus Handbuch B gelten weiter. | D17: Dass die Nebenquellen linear mit der Nutzerzahl mitwachsen. Realistisch wachsen sie sprunghaft, weil jeder Partner einzeln gewonnen wird. Seit A-52 ersetzt: Ortspartnerschaften mit Hervorhebung (Nr. 65 schließt sie aus) durch ein Werkzeugabo, das Ticketing zu 6 % durch einen Anteil von 3 % — beides Annahmen aus A-55.
A18: Kosten | B18: Alle 35.800 € Einmalkosten mit Position und Monat; die vollständige Kostenstaffel mit 13 Positionen über 5 Stützstellen; CSD-Beträge. | C18: Zwischen den Stützstellen wird linear interpoliert; oberhalb von 50.000 MAU wird das letzte Segment fortgeschrieben. | D18: Die Monatszuordnung der CSD-Auftritte ist eine Annahme — Handbuch B nennt nur „Jahr 2“ und „Jahr 3“. Bis 21.09.2026 stand sie auf Monat 19 und 31; das war falsch, weil T0 selbst in der CSD-Saison liegt. Jetzt Monat 13 und 25, dazu der CSD zum Start in Monat 1. Frei angenommen sind außerdem die Beträge der Beschlussposten (Abschnitt 5).
A19: Altersprüfung | B19: Die Staffelzeile „Altersprüfung“ (0 / 300 / 520 / 780 / 1.600 € je Monat). | C19: Daraus RÜCKGERECHNET: rund 0,22 € je Prüfung. Bemerkenswert nah an der einzigen öffentlichen Preisangabe aus A-07 (Didit: 0,20 $ White-Label-Verifizierung, Marketingangabe). | D19: Die Spanne 2 bis 5 € für ein KJM-konformes Identverfahren stammt aus der Marktbeobachtung. KEIN Anbieter in A-07 nennt öffentliche Preise. Diese Zahl ist im Gespräch zu bestätigen, bevor irgendetwas darauf gebaut wird.
A20: Kapital und Leben | B20: Rücklage Rechtsvorfall 8.000 €, Puffer 20 %, Krankenversicherung 200 € je Person und Monat. | C20: Der Kapitalbedarf rechnet sich aus dem jeweiligen Tiefpunkt statt aus einer festen Zahl. | D20: Die Lebenshaltung von 1.100 € je Person und Monat ist eine ANNAHME dieses Modells. Handbuch B schreibt an dieser Stelle ausdrücklich „nicht beziffert“. Der Wert entspricht dem Gründungsstipendium Niedersachsen, das genau diesen Zweck hat. Seit A-52 steht sie als Stellhebel im Blatt „Annahmen“ (Zeile 156) und in der Gesamtsicht auf dem Blatt „Kennzahlen“ (Zeile 20).
A22: 3 · Externe Quellen, die nicht aus Handbuch B stammen
A23: Angabe | B23: Wert | C23: Quelle | D23: Stand
A24: KfW-Studienkredit — Zinssatz | B24: 6,34 % Sollzins, 6,53 % effektiver Jahreszins; variabel auf Basis des Sechs-Monats-Euribor, Anpassung jeweils zum 1. April und 1. Oktober | C24: kfw.de, Informationen zu den Zinsen des KfW-Studienkredits | D24: per 01.04.2026, abgerufen 27.07.2026
A25: KfW-Studienkredit — Rahmen | B25: 100 bis 650 € monatlich, höchstens 14 Semester, damit maximal 54.600 €; Rückzahlung bis zu 25 Jahre, Raten ab 20 € | C25: kfw.de, KfW-Studienkredit (174) | D25: abgerufen 27.07.2026
A26: Business Angel — Ticketgröße | B26: 25.000 bis 200.000 € je Angel; Runden meist 3 bis 8 Angels; Pre-Seed-Runden gesamt 50.000 bis 500.000 € | C26: Marktübersichten Pre-Seed-Finanzierung Deutschland 2026 | D26: abgerufen 27.07.2026
A27: Business Angel — Verwässerung | B27: 5 bis 15 % je Angel-Runde | C27: dieselben Übersichten | D27: abgerufen 27.07.2026
A28: Gründungsstipendium Niedersachsen | B28: 1.100 € je Person und Monat, bis zu 10 Monate; Wohnsitz und Sitz in Niedersachsen | C28: A-09, `foerdermittel-uebersicht.xlsx` | D28: 27.07.2026
A29: EXIST für Studierende | B29: 1.000 € je Person und Monat, dazu Sachmittel und Coaching; keine bestehende Gesellschaft zum Förderbeginn | C29: A-10, `exist-voraussetzungen.md` | D29: 27.07.2026
A30: Preis je Altersprüfung, Anbieterlage | B30: Kein Anbieter mit öffentlicher Preisliste; einzige Angabe: 0,10 $ Altersschätzung / 0,20 $ White-Label-Verifizierung (Marketingangabe eines Anbieters) | C30: A-07, `verifizierungsanbieter-vergleich.xlsx` | D30: 27.07.2026
A31: Mengengerüst Moderation | B31: Bei 40.000 MAU 37 bis 73 Bilder täglich in der menschlichen Warteschlange | C31: A-37, `moderationsarchitektur.md` | D31: 27.07.2026
A32: Web-Zahlungsdienst (Mollie) | B32: 1,80 % + 0,25 € je Zahlung mit EWR-Karte, keine Monatsgebühr | C32: A-53, `eu-alternativen-stack.md` (StackPatrol, Vergleich europäischer Zahlungsdienste) | D32: abgerufen 20.09.2026
A33: Apple, Richtlinie 3.1.3(b) | B33: Auf der Webseite erworbene Abos darf die App anerkennen, sofern sie dort auch als In-App-Kauf angeboten werden; eigene Freischaltmechanismen in der App sind nach 3.1.1 verboten | C33: developer.apple.com, App Review Guidelines | D33: abgerufen 21.09.2026
A34: SMS-Versand (Sweego) | B34: Deutschland 0,078 €, Österreich 0,035 €, Schweiz 0,068 € je SMS, zuzüglich Steuer; E-Mail kostenlos bis 100 am Tag, 10 € im Monat für 20.000 bis 50.000 | C34: sweego.io, „Worldwide SMS pricing“ und „Pricing“ | D34: abgerufen 21.09.2026
... A37: Stundensatz für die Code-Prüfung | B37: Median 90 € je Stunde für Software- und Webentwicklung (95 € über alle IT-Disziplinen) | C37: Freelancer-Kompass 2026, freelancermap.de; A-46, `entwicklungsmodelle.md` | D37: veröffentlicht 02.07.2026, abgerufen 19.09.2026
A39: 4 · Was dieses Modell nicht kann
A40: Es rechnet keine Steuern. Körperschaft- und Gewerbesteuer fallen erst bei Gewinn an, also im realistischen Fall frühestens im dritten Jahr; die Umsatzsteuer ist im Nettoerlös je Zahler bereits abgezogen (Blatt „Annahmen“, Abschnitt 2a). Für einen Businessplan reicht das; für eine Liquiditätsplanung ab dem ersten Gewinnjahr nicht. Es rechnet keine Zahlungsziele. Erlöse und Kosten fallen im selben Monat an, in dem sie entstehen. In Wirklichkeit zahlen Stores mit 30 bis 60 Tagen Verzug, Web-Zahlungen kommen schneller — das verschiebt die Liquiditätskurve um ein bis zwei Monate nach hinten, ändert aber nichts am Tiefpunkt. Es rechnet kein Gründergehalt. Handbuch B tut das im optimistischen Fall ab Monat 16. Hier bleibt es bewusst außen vor, weil ein Gehalt eine Entscheidung ist. Wer es einplanen will, trägt es als eigene Kostenzeile ein. Und es kennt die Zukunft nicht. Der Start liegt frühestens im Sommer 2028, geplant wird ein Jahr später (Nr. 45). Bis dahin ändern sich Preise, Anbieter, Provisionen und Recht. Der Wert dieses Modells liegt nicht in seinen Zahlen, sondern darin, dass sichtbar wird, welche Größe das Ergebnis bewegt — und das ist in dieser Reihenfolge: die Nutzerzahl, die Rechtsfrage zur Altersprüfung, und erst danach alles andere.
A42: 5 · Fortschreibung A-52 vom 21.09.2026 — was sich geändert hat und was es bewirkt
A43: Neun Änderungen aus den Beschlüssen vom 19. und 21.09.2026 und den Aufgaben A-51 bis A-55. Die Wirkung ist nacheinander nachgerechnet, in der Reihenfolge der Tabelle: jede Zeile zeigt, um wie viel der Kapitalbedarf der Firma im realistischen Fall steigt, wenn diese Änderung zu den darüber stehenden hinzukommt. Der Kapitalbedarf enthält den Sicherheitspuffer von 20 %; deshalb wirkt ein Einmalbetrag vor dem Tiefpunkt mit dem 1,2-Fachen. Probe: Nimmt man alle Änderungen zurück, ergibt sich der alte Stand von 107.349 € auf 19 € genau (Rundung der Erlöskette).
A44: Änderung | B44: Grundlage und Wert im Modell | C44: Wo | D44: Wirkung auf den Kapitalbedarf der Firma, realistisch
A45: 1 · Nebenerlöse neu geschnitten | B45: Nr. 65, 74, A-55: Werkzeugabo 5 Konten zu 29 € je Stadt statt Ortspartnerschaften mit Hervorhebung; Ticketanteil 3 % statt 6 %; Reichweitenschwellen aus Handbuch B bleiben | C45: Annahmen 62–71 · Szenarien 15–16 | D45: +3.799 €
A46: 2 · Erlöskette je Zahler | B46: Nr. 67, A-51, A-53: 60 % der Zahlungen über das Web, dort 1,80 % + 0,25 € statt pauschal 4 %; Nettoerlös 7,56 € statt 7,38 € | C46: Annahmen 2a und 26 | D46: −1.387 €
A47: 3 · SMS-Versand | B47: Nr. 46, Z-10: 30 % der Neuregistrierungen mit Mobilnummer, 2 SMS je Person, 0,078 € je SMS | C47: Annahmen 146–148 · Szenarien 25 | D47: +2.763 €
A48: 4 · Eigene Veranstaltungen | B48: Nr. 74: 2.000 € je Stadt und Jahr ab Monat 1 (Veranstaltungskonzept, Abschnitt 5) | C48: Annahmen 144–145 · Szenarien 28 | D48: +12.800 €
A49: 5 · CSD-Monate berichtigt | B49: Nr. 45: Monat 13 und 25 statt 19 und 31 — der Auftritt im dritten Jahr fällt damit vor den Tiefpunkt | C49: Annahmen 138 und 140 | D49: +3.590 €
A50: 6 · CSD zum Start | B50: Nr. 45, 80: 10.000 / 6.000 / 3.500 € in Monat 1 | C50: Annahmen 135–136 · Szenarien 29 | D50: +7.200 €
A51: 7 · Testgeräte zweite Plattform | B51: A-51: 1.200 € in Monat 1 | C51: Annahmen 129 | D51: +1.440 €
A52: 8 · Code-Prüfung vollständig | B52: Nr. 73, A-46, A-51: 18.900 € in Monat 1 (Spanne 11.880 bis 25.920 €) | C52: Annahmen 128 | D52: +22.680 €
A53: 9 · Lebenshaltung und Gesamtbedarf | B53: Nr. 38: 1.100 € je Person und Monat bis zum Break-even; eigener Stellhebel und Gesamtbedarf | C53: Annahmen 156 · Kennzahlen 19–20 | D53: keine auf die Firma — Gesamtbedarf siehe unten
A54: Zusammen | B54: Kapitalbedarf der Firma, realistisch: 107.349 € → 160.253 € | C54: Kennzahlen 16 | D54: +52.904 € (davon 19 € Rundung)
A56: Kennzahl, vorher → nachher | B56: Pessimistisch | C56: Realistisch | D56: Optimistisch
... A62: GESAMTBEDARF mit Krankenversicherung und Lebenshaltung (Nr. 38) | B62: 214.255 € → 275.861 € | C62: 169.749 € → 233.053 € | D62: 148.351 € → 197.810 €
A64: NICHT EINGERECHNET, weil klein oder nicht schätzbar: Apple-Entwicklerkonto (99 $ im Jahr) und Google Play (25 $ einmalig) — ob die Staffelzeile „Werkzeuge, Entwicklerzugänge“ sie enthält, sagt Handbuch B nicht · E-Mail-Versand (Sweego: kostenlos bis 100 Mails am Tag, 10 € im Monat für 20.000 bis 50.000) · das Postfach hinter dem Kontaktservice (A-58) · der Selbstbetrieb von listmonk: Zeit statt Geld, geschätzt ein bis zwei Tage Einrichtung, danach zwei bis vier Stunden im Monat für Pflege und Zustellüberwachung; der Server läuft im Posten „Hosting“ mit · die Nachprüfung der Korrekturen nach der Code-Prüfung · Codes für Streamer, Unterstützer und Kampagne (Nr. 60), die einen kleinen Teil der Aboerlöse ersetzen · die Sonderbedingungen der Stores in der EU nach dem Digital Markets Act.
A66: WAS OFFEN BLEIBT: Nr. 40 (Altersprüfung, Stufe 2) kann den Kapitalbedarf um rund 14.000 bis 17.000 € senken, wenn Weg 1 oder 0 gilt, und um rund 86.000 € erhöhen, wenn nur Weg 3 bleibt. Nr. 85 (Travel-Paket) und die Stufeninhalte (Nr. 67, Feinschnitt) bestimmen den Anteil PRO — die unsicherste Erlösannahme. Nr. 88 klärt, ob die Prüfungen vor oder nach der Gründung liegen. Nichts davon ist heute entscheidbar, alles davon ist hier einstellbar.
