Workbook

Sheet Ergebnis
A1: Kostenmodell „GmbH ohne Produkt“ — das Ergebnis
A2: Aufgabe A-26 · erstellt 27.07.2026 · Rolle: Finanzmodellierer · Fenster V0 · alle Zahlen per Websuche am 27.07.2026 belegt
A4: DIESES BLATT EMPFIEHLT KEINEN ZEITPUNKT. Die Aufgabenstellung verbietet das ausdrücklich, und zwar zu Recht: Der Gründungszeitpunkt ist eine gesellschaftsrechtliche und steuerliche Entscheidung, die die Gründer gemeinsam mit dem Anwalt treffen. Dieses Modell stellt gegenüber, damit sie gerechnet und nicht gefühlt getroffen wird.
A6: Die eine Zahl
A7: Eine sofortige Gründung kostet bis zum Start mehr als eine Gründung kurz davor: | D7: ='Drei Zeitpunkte'!D18 -> 16773
A9: Die drei Zeitpunkte auf einen Blick
A10: Größe | B10: S1 · sofort | C10: S2 · 1 Jahr vorher | D10: S3 · kurz vorher | E10: Anmerkung
A11: Monate mit Gesellschaft bis T0 | B11: ='Drei Zeitpunkte'!B6 -> 24 | C11: ='Drei Zeitpunkte'!C6 -> 12 | D11: ='Drei Zeitpunkte'!D6 -> 3 | E11: gezählt bis Sommer 2028
A12: Gesamtkosten bis T0 | B12: ='Drei Zeitpunkte'!B15 -> 23299 | C12: ='Drei Zeitpunkte'!C15 -> 12970 | D12: ='Drei Zeitpunkte'!D15 -> 6526 | E12: mit den aktuell gesetzten Schaltern
A13: günstigster Fall | B13: ='Drei Zeitpunkte'!B23 -> 10099 | C13: ='Drei Zeitpunkte'!C23 -> 6370 | D13: ='Drei Zeitpunkte'!D23 -> 4876 | E13: alle vier Zweifelsfragen fallen zu unseren Gunsten aus
A14: ungünstigster Fall | B14: ='Drei Zeitpunkte'!B24 -> 32899 | C14: ='Drei Zeitpunkte'!C24 -> 17770 | D14: ='Drei Zeitpunkte'!D24 -> 7726 | E14: alle vier fallen ungünstig aus
A16: Die vier Fragen, an denen die Spanne hängt
A17: Zwischen bestem und schlechtestem Fall liegt bei sofortiger Gründung ein fünfstelliger Betrag. Er hängt an vier Fragen, die heute alle klärbar sind: 1 · Ist ein externer Datenschutzbeauftragter schon vor dem Produktivbetrieb pflichtig? Art. 37 Abs. 1 lit. c DSGVO knüpft an die Kerntätigkeit an — eine Gesellschaft ohne Verarbeitung hat keine. Das ist Frage W1 aus A-11. 2 · Braucht eine Gesellschaft ohne Telemedienangebot einen Jugendschutzbeauftragten? § 7 JMStV setzt ein laufendes Angebot voraus. 3 · Ist eine Cyber- und Betriebshaftpflicht vor dem Start sinnvoll, wenn es weder Nutzer noch Daten gibt? 4 · Fällt die Familienversicherung durch die Geschäftsführerstellung weg, auch ohne Gehalt und während der Ausbildung? Offene Entscheidung Nr. 25. Diese Frage allein bewegt bei 24 Monaten 9.600 €. Drei davon gehören in den Anwaltstermin, eine an die Krankenkasse — und zwar schriftlich.
A19: Verhältnis zum Finanzmodell A-13 — bitte vor dem Addieren lesen
A20: HIER LAUERT EIN DOPPELZÄHLUNGSFEHLER. Das Finanzmodell in `finanzmodell.xlsx` beginnt mit Monat 1 = T0. Alles, was VOR T0 anfällt, steht dort nicht — mit einer Ausnahme: Die einmaligen Gründungskosten (2.600 € für Notar, Handelsregister und Gesellschaftsvertrag) sind in A-13 als Einmalkosten in Monat 1 enthalten. Sie sind hier dieselbe Ausgabe, nur genauer aufgeschlüsselt. Wer die beiden Modelle zusammenrechnet, geht deshalb so vor:
A21: Rechenschritt | B21: S1 · sofort | C21: S2 · 1 Jahr vorher | D21: S3 · kurz vorher | E21: Erläuterung
A22: Gesamtkosten bis T0 aus diesem Modell | B22: ='Drei Zeitpunkte'!B15 -> 23299 | C22: ='Drei Zeitpunkte'!C15 -> 12970 | D22: ='Drei Zeitpunkte'!D15 -> 6526 | E22: alles, was die Rechtsform vor dem Start kostet
A23: abzüglich der einmaligen Gründungskosten | B23: =-Kostenpositionen!$B$10 -> -2641 | C23: =-Kostenpositionen!$B$10 -> -2641 | D23: =-Kostenpositionen!$B$10 -> -2641 | E23: sie stecken bereits in den Einmalkosten von A-13, Monat 1
A24: ZUSÄTZLICHER Kapitalbedarf VOR T0 | B24: =B22+B23 -> 20658 | C24: =C22+C23 -> 10329 | D24: =D22+D23 -> 3885 | E24: Dieser Betrag kommt zum Kapitalbedarf aus A-13 hinzu und ist dort nirgends enthalten.
A26: ZUR EINORDNUNG: Der Kapitalbedarf aus A-13 beträgt im realistischen Szenario rund 107.000 € für die Firma, rund 165.000 € einschließlich der Lebenshaltung beider Gründer. Die Beträge auf diesem Blatt kommen hinzu — sie sind gemessen daran klein. Das ist selbst ein Ergebnis: Der Gründungszeitpunkt ist keine Frage des Geldes allein. Die 16.773 € Unterschied wiegen weniger als die Förderansprüche, die eine frühe Gründung vernichtet. Siehe Blatt „Was man dafür bekommt“.
A28: Wie dieses Modell aufgebaut ist
A29: Blatt | B29: Was darin steht
A30: Kostenpositionen | B30: Jede Position einzeln mit Betrag, Quelle und — bei den vier strittigen — einem gelben Schalter.
A31: Drei Zeitpunkte | B31: Die Rechnung. Gesamtkosten je Zeitpunkt, Differenz, Bandbreite zwischen bestem und schlechtestem Fall.
A32: Was man dafür bekommt | B32: Die nicht-monetäre Seite: Haftungsschutz, Förderfähigkeit, Vertragsfähigkeit, Marke, Außenwirkung — je Zeitpunkt bewertet.
A33: Quellen | B33: Jede externe Zahl mit Fundstelle und Abrufdatum.

Sheet Kostenpositionen
A1: Jede Position einzeln, mit Quelle
A2: Blau = Stellhebel. Gelb = Schalter für die drei strittigen Positionen. Spalte E nennt die Herkunft jeder Zahl.
A4: 1 · Einmalige Gründungskosten
A5: Position | B5: Betrag | C5: Art | E5: Quelle
A6: Notar — Beurkundung individueller Gesellschaftsvertrag, brutto | B6: 476 | C6: gesetzlich | E6: GNotKG Anlage 2 Tabelle B, § 107 GNotKG: 2,0-Gebühr auf einen Mindestgeschäftswert von 30.000 € = 250 € netto, zzgl. Vollzug, Betreuung, HR-Anmeldung, XML-Strukturdaten, Auslagen und 19 % USt. Stand 2026.
A7: Handelsregister — Ersteintragung bei Bargründung | B7: 225 | C7: gesetzlich | E7: HRegGebV Nr. 2100. Bundeseinheitlich, ohne Umsatzsteuer. Bei Sachgründung wären es 360 € (Nr. 2101).
A8: Gewerbeanmeldung | B8: 40 | C8: gesetzlich | E8: Rahmen 20–60 € je nach Kommune. Mittelwert angesetzt.
A9: Anwaltliche Gestaltung des Gesellschaftsvertrags | B9: 1900 | C9: verhandelbar | E9: ABGELEITET: Handbuch B setzt 2.600 € für „Notar, Handelsregister, Gesellschaftsvertrag" an. Die gesetzlichen Gebühren betragen 741 €. Die Differenz ist die anwaltliche Gestaltung — Vesting, Stichentscheid, Vinkulierung. Der Notar beurkundet; entworfen wird der Vertrag üblicherweise anwaltlich.
A10: Summe einmalig | B10: =SUM(B6:B9) -> 2641
A11: davon gesetzlich unvermeidbar | B11: =SUMIF(C6:C9,"gesetzlich",B6:B9) -> 741
A12: davon verhandelbar | B12: =SUMIF(C6:C9,"verhandelbar",B6:B9) -> 1900
A13: ABGLEICH: Handbuch B setzt für „Notar, Handelsregister, Gesellschaftsvertrag“ pauschal 2.600 € an. Die Rechnung von unten ergibt 2.641 € — 1,6 % Abweichung. Der Wert stimmt also. Bemerkenswert ist seine ZUSAMMENSETZUNG: Nur 741 € sind gesetzliche Gebühren, die niemand verhandeln kann. Die übrigen rund 1.900 € sind anwaltliche Gestaltung des Gesellschaftsvertrags. Handbuch B nennt das nicht getrennt, und genau dort liegt der einzige Spielraum. Wer stattdessen das Musterprotokoll nähme, spart die 1.900 € fast vollständig — verliert aber Vesting und Stichentscheid. Handbuch B nennt das selbst „den teuersten Sparbetrag im ganzen Plan“, und das ist bei zwei Gründern richtig.
A15: 2 · Laufende Kosten je Monat — GmbH ohne Produkt
A16: Position | B16: je Monat | C16: pflichtig | D16: Schalter (1 = fällt an) | E16: Quelle und Vorbehalt
A17: Buchhaltung, laufende Steuerberatung | B17: 150 | C17: ja | D17: 1 | E17: Handbuch B, Kostenstaffel Spalte „Vor Launch". Eine GmbH ist buchführungspflichtig, auch ohne Umsatz.
A18: Geschäftskonto | B18: 10 | C18: ja | D18: 1 | E18: Marktvergleiche 2026: Kontoführung meist 5–30 €/Monat; kostenlose Konten mit Inklusivvolumen existieren und stehen laut Anbieterangaben auch der GmbH offen (Finom, FYRST, Holvi, Qonto). 10 € vorsichtig angesetzt.
A19: Ladungsfähige Geschäftsadresse | B19: 6 | C19: ja | D19: 1 | E19: A-04, `impressumsloesung-vergleich.md`: 3,33 € bis 6,70 € je Monat bei den geprüften Anbietern. Oberer Wert angesetzt.
A20: Cyber- und Betriebshaftpflicht | B20: 200 | C20: nein | D20: 1 | E20: Handbuch B, Kostenstaffel. FRAGLICH vor dem Produktivbetrieb: Eine Gesellschaft ohne Nutzer, ohne Daten und ohne Dienst hat kaum ein versicherbares Risiko. Als Schalter ausgeführt.
A21: Externer Datenschutzbeauftragter | B21: 250 | C21: nein | D21: 1 | E21: Handbuch B setzt 250 € an. A-11 hat den Markt geprüft: 60–120 € für 1–10 Beschäftigte. OB ÜBERHAUPT PFLICHTIG, ist offen (Frage W1 aus A-11): Art. 37 Abs. 1 lit. c DSGVO knüpft an die Kerntätigkeit an. Eine GmbH ohne Produkt verarbeitet nichts. Als Schalter ausgeführt.
A22: Jugendschutzbeauftragter | B22: 100 | C22: nein | D22: 1 | E22: Handbuch B, Kostenstaffel Spalte „Vor Launch". § 7 JMStV knüpft an ein laufendes Telemedienangebot an — vor dem Start gibt es keines. Als Schalter ausgeführt.
A23: Summe je Monat (mit den gesetzten Schaltern) | B23: =SUMPRODUCT(B17:B22,D17:D22) -> 716
A24: zum Vergleich: alle drei Schalter aus | B24: =SUMIF(C17:C22,"ja",B17:B22) -> 166
A25: zum Vergleich: alle drei Schalter an | B25: =SUM(B17:B22) -> 716
A27: DIE DREI SCHALTER SIND DER KERN DIESES BLATTES. Handbuch B setzt in der Spalte „Vor Launch“ 1.420 € je Monat an — darin stecken aber auch Hosting, Werkzeuge, KI-Zugänge und Marketing, die eine Gesellschaft ohne Produkt nicht braucht. Bleiben die Positionen, die wirklich an der Rechtsform hängen. Und bei dreien davon ist zweifelhaft, ob sie vor dem Start überhaupt anfallen:\n\n• DATENSCHUTZBEAUFTRAGTER: Art. 37 Abs. 1 lit. c DSGVO knüpft an die KERNTÄTIGKEIT an. Eine Gesellschaft, die noch nichts verarbeitet, hat keine. Das ist Frage W1 aus dem Fragenkatalog A-11 — dort ausdrücklich als Kompetenztest gestellt, weil viele Anbieter reflexartig „ab Tag 1“ antworten.\n• JUGENDSCHUTZBEAUFTRAGTER: § 7 JMStV knüpft an ein laufendes Telemedienangebot an. Vor dem Start gibt es keines.\n• VERSICHERUNGEN: Eine Gesellschaft ohne Nutzer, ohne Daten und ohne Dienst hat kaum ein versicherbares Risiko. Eine Betriebshaftpflicht kann trotzdem sinnvoll sein, sobald Verträge geschlossen werden.\n\nZusammen machen diese drei Positionen 550 € im Monat aus — bei 24 Monaten sind das 13.200 €. Die Frage, ob sie anfallen, ist damit teurer als die gesamte Gründung.
A29: 3 · Jährliche Kosten
A30: Position | B30: je Jahr | E30: Quelle
A31: Jahresabschluss durch Steuerberater | B31: 1500 | E31: Marktübersicht 2026: Kleinstkapitalgesellschaft 1.500–3.000 € netto; kleine GmbH mit Bilanzsumme bis 100.000 € eher 800–2.000 €. Unterer Rand angesetzt, weil eine GmbH ohne Geschäftsbetrieb der einfachste denkbare Fall ist.
A32: Hinterlegung beim Bundesanzeiger | B32: 37 | E32: Kleinstkapitalgesellschaften nach § 267a HGB hinterlegen nur, statt offenzulegen. Gebühr rund 37 €; wer ausschließlich die Bilanz einreicht, zahlt seit 2026 keine Einreichungsgebühr.
A33: IHK-Grundbeitrag | B33: 200 | E33: Jede IHK setzt den Grundbeitrag in ihrer Wirtschaftssatzung selbst fest; die Spanne reicht von rund 64 € bis über 300 €. 200 € als vorsichtiger Mittelwert. VOR DER GRÜNDUNG in der Wirtschaftssatzung der zuständigen Kammer nachlesen.
A34: Summe je Jahr | B34: =SUM(B31:B33) -> 1737
A36: 4 · Privatkosten, die an der Gründung hängen
A37: Position | B37: je Monat | C37: Anzahl | D37: Schalter (1 = fällt an) | E37: Quelle und Vorbehalt
A38: Krankenversicherung je Gründer und Monat | B38: 200 | C38: 2 | D38: 0 | E38: Handbuch B: rund 200 € je Person. Als Geschäftsführer einer GmbH ohne Gehalt weder pflicht- noch dauerhaft familienversichert. HÄNGT AN DER GRÜNDUNG: Ohne Gesellschaft bleibt die Familienversicherung bestehen. Offene Entscheidung Nr. 25.
A40: VOREINGESTELLT AUF 0, UND ZWAR BEWUSST. Handbuch B rechnet mit 200 € je Person, weil Geschäftsführer einer GmbH ohne Gehalt weder pflicht- noch dauerhaft familienversichert sind. Bei zwei Schülern beziehungsweise Studierenden ist das aber nicht ausgemacht: Solange die Ausbildung läuft und keine hauptberufliche Selbständigkeit vorliegt, kann die Familienversicherung bestehen bleiben. Das ist offene Entscheidung Nr. 25 und muss VOR der Gründung mit der Krankenkasse geklärt werden — schriftlich, nicht am Telefon. Bei 24 Monaten und zwei Personen geht es um 9.600 €, also um mehr als das Dreifache der gesamten Gründungskosten. Auf 1 gesetzt zeigt das Modell den ungünstigen Fall.

Sheet Drei Zeitpunkte
A1: Was jeder Gründungszeitpunkt bis zum Start kostet
A2: T0 = Sommer 2028. Alles rechnet sich aus dem Blatt „Kostenpositionen“. Die Zeile ganz unten ist die Antwort auf die Aufgabenstellung.
A4: Position | B4: S1 · sofort | C4: S2 · 1 Jahr vorher | D4: S3 · kurz vorher | E4: Anmerkung
A5: Gründung im Zeitraum | B5: 27.07.2026 | C5: Sommer 2027 | D5: Frühjahr 2028 | E5: T0 = Sommer 2028
A6: Monate mit bestehender Gesellschaft bis T0 | B6: 24 | C6: 12 | D6: 3 | E6: blaues Feld — änderbar, wenn sich die Zeitachse verschiebt
A7: davon Geschäftsjahre mit Jahresabschluss | B7: =MAX(1,ROUNDUP(B6/12,0)) -> 2 | C7: =MAX(1,ROUNDUP(C6/12,0)) -> 1 | D7: =MAX(1,ROUNDUP(D6/12,0)) -> 1 | E7: Auch ein Rumpfgeschäftsjahr von drei Monaten verlangt einen Jahresabschluss. Deshalb mindestens 1.
A9: Kostenblöcke
A10: Einmalige Gründungskosten | B10: =Kostenpositionen!$B$10 -> 2641 | C10: =Kostenpositionen!$B$10 -> 2641 | D10: =Kostenpositionen!$B$10 -> 2641 | E10: fallen in jedem Fall an, nur zu unterschiedlichen Zeitpunkten
A11: Laufende Kosten der Gesellschaft | B11: =B6*Kostenpositionen!$B$23 -> 17184 | C11: =C6*Kostenpositionen!$B$23 -> 8592 | D11: =D6*Kostenpositionen!$B$23 -> 2148 | E11: Monate × Monatssumme mit den gesetzten Schaltern
A12: Jahresabschlüsse, Hinterlegung, IHK | B12: =B7*Kostenpositionen!$B$34 -> 3474 | C12: =C7*Kostenpositionen!$B$34 -> 1737 | D12: =D7*Kostenpositionen!$B$34 -> 1737 | E12: je angefangenem Geschäftsjahr
A13: Krankenversicherung beider Gründer | B13: =B6*Kostenpositionen!$B$38*Kostenpositionen!$C$38*Kostenpositionen!$D$38 -> 0 | C13: =C6*Kostenpositionen!$B$38*Kostenpositionen!$C$38*Kostenpositionen!$D$38 -> 0 | D13: =D6*Kostenpositionen!$B$38*Kostenpositionen!$C$38*Kostenpositionen!$D$38 -> 0 | E13: nur wenn der Schalter auf dem Blatt „Kostenpositionen“ auf 1 steht — siehe offene Entscheidung Nr. 25
A15: GESAMTKOSTEN BIS T0 | B15: =SUM(B10:B13) -> 23299 | C15: =SUM(C10:C13) -> 12970 | D15: =SUM(D10:D13) -> 6526 | E15: Alles, was die Rechtsform bis zum Start kostet — ohne Produktentwicklung, ohne Marketing, ohne Lebenshaltung.
A17: Die Antwort auf die Aufgabenstellung
A18: MEHRKOSTEN EINER SOFORTIGEN GRÜNDUNG GEGENÜBER EINER GRÜNDUNG KURZ VOR DEM START | D18: =B15-D15 -> 16773 | E18: Das ist die eine Zahl, die die Aufgabe verlangt.
A19: Mehrkosten S2 gegenüber S3 | C19: =C15-D15 -> 6444 | E19: eine Gründung ein Jahr vorher gegenüber kurz vorher
A21: Bandbreite, weil drei Positionen strittig sind
A22: Variante | B22: S1 · sofort | C22: S2 · 1 Jahr vorher | D22: S3 · kurz vorher | E22: Bedeutung
A23: günstigster Fall: DSB, Jugendschutz, Versicherung und Krankenversicherung entfallen alle | B23: =Kostenpositionen!$B$10+B6*SUMIF(Kostenpositionen!$C$17:$C$22,"ja",Kostenpositionen!$B$17:$B$22)+B7*Kostenpositionen!$B$34 -> 10099 | C23: =Kostenpositionen!$B$10+C6*SUMIF(Kostenpositionen!$C$17:$C$22,"ja",Kostenpositionen!$B$17:$B$22)+C7*Kostenpositionen!$B$34 -> 6370 | D23: =Kostenpositionen!$B$10+D6*SUMIF(Kostenpositionen!$C$17:$C$22,"ja",Kostenpositionen!$B$17:$B$22)+D7*Kostenpositionen!$B$34 -> 4876 | E23: Alle vier Zweifelsfragen fallen zu unseren Gunsten aus.
A24: ungünstigster Fall: alles fällt an, einschließlich Krankenversicherung | B24: =Kostenpositionen!$B$10+B6*SUM(Kostenpositionen!$B$17:$B$22)+B7*Kostenpositionen!$B$34+B6*Kostenpositionen!$B$38*Kostenpositionen!$C$38 -> 32899 | C24: =Kostenpositionen!$B$10+C6*SUM(Kostenpositionen!$B$17:$B$22)+C7*Kostenpositionen!$B$34+C6*Kostenpositionen!$B$38*Kostenpositionen!$C$38 -> 17770 | D24: =Kostenpositionen!$B$10+D6*SUM(Kostenpositionen!$B$17:$B$22)+D7*Kostenpositionen!$B$34+D6*Kostenpositionen!$B$38*Kostenpositionen!$C$38 -> 7726 | E24: Alle vier fallen ungünstig aus.
A25: Spanne zwischen beiden | B25: =B24-B23 -> 22800 | C25: =C24-C23 -> 11400 | D25: =D24-D23 -> 2850 | E25: So viel hängt an vier Fragen, die heute mit vier Telefonaten und einem Anwaltstermin klärbar wären.
A27: WAS DIESE TABELLE NICHT SAGT: Sie empfiehlt keinen Zeitpunkt. Kosten sind nur eine von vier Größen — die anderen drei stehen auf dem Blatt „Was man dafür bekommt“, und eine davon dreht das Vorzeichen um: Eine frühe Gründung VERNICHTET Ansprüche auf EXIST und das Gründungsstipendium Niedersachsen, die zusammen deutlich mehr wert sind als die hier gerechneten Mehrkosten. Wer nur auf diese Tabelle schaut, trifft die Entscheidung auf halber Grundlage.

Sheet Was man dafür bekommt
A1: Die andere Hälfte der Entscheidung
A2: Kosten sind nur eine Größe. Diese Seite listet, was eine frühe Gründung bringt — und wo sie schadet.
A4: Was | B4: Worum es geht | C4: S1 sofort | D4: S2 1 Jahr | E4: S3 kurz vorher | F4: Einordnung
A5: Haftungsschutz | B5: Ab Eintragung ins Handelsregister haftet die Gesellschaft, nicht ihr persönlich. VORHER: In der Vorbereitungsphase bildet ihr vermutlich eine GbR mit unbeschränkter persönlicher Haftung (offene Entscheidung Nr. 26, Anwaltsakte B3). Zwischen Beurkundung und Eintragung besteht zudem die Vor-GmbH, in der die Handelnden persönlich haften. | C5: hoch | D5: hoch | E5: gering | F5: Solange kein Produkt läuft, ist das Haftungsrisiko überschaubar: keine Nutzer, keine Daten, keine Verträge mit Verbrauchern. Es steigt genau dann, wenn die ersten Verträge geschlossen werden.
A6: Förderfähigkeit — Programme, die eine Gesellschaft VERLANGEN | B6: KfW Award Gründen (Gründung ab 2021), OUT OF THE BOX.NRW (gegründete digitale Start-ups), push! Hessen, Mikromezzaninfonds, ERP-Förderkredite, Bürgschaftsbank. | C6: hoch | D6: mittel | E6: gering | F6: Diese Programme greifen alle erst NACH dem Start. Eine frühe Gründung bringt hier keinen Vorteil, weil die übrigen Voraussetzungen ohnehin fehlen.
A7: Förderfähigkeit — Programme, die eine Gesellschaft AUSSCHLIESSEN | B7: EXIST-Gründungsstipendium (zum Förderbeginn darf keine Gesellschaft bestehen), Gründungsstipendium Niedersachsen (Antrag vor Vorhabenbeginn). | C7: schädlich | D7: schädlich | E7: neutral | F7: HIER KEHRT SICH DAS VORZEICHEN UM. Eine frühe Gründung VERNICHTET Ansprüche, die zusammen im fünfstelligen Bereich liegen. Siehe A-10 und offene Entscheidung Nr. 34.
A8: Vertragsfähigkeit | B8: Verträge mit Ortspartnern, Anbietern, Auftragsverarbeitern und Dienstleistern laufen auf die Gesellschaft statt auf Privatpersonen. Auftragsverarbeitungsverträge nach Art. 28 DSGVO brauchen einen Verantwortlichen. | C8: gering | D8: mittel | E8: hoch | F8: Wird erst relevant, wenn tatsächlich Verträge geschlossen werden — also in V3/V4. Vorher genügt es, Absichtserklärungen als Privatpersonen zu führen.
A9: Markenschutz | B9: Eine Marke kann von natürlichen Personen angemeldet und später auf die Gesellschaft übertragen werden. | C9: kein Vorteil | D9: kein Vorteil | E9: kein Vorteil | F9: WICHTIG, WEIL ES OFT FALSCH ANGENOMMEN WIRD: Markenschutz ist KEIN Argument für eine frühe Gründung. Die Anmeldung sollte früh erfolgen — die Gründung deshalb nicht.
A10: Außenwirkung gegenüber Partnern und Presse | B10: Eine GmbH wirkt verbindlicher als zwei Privatpersonen mit einer Idee. | C10: mittel | D10: mittel | E10: gering | F10: Real, aber schwer zu beziffern. Bei Ortspartnern in Köln zählt Vorbereitung und persönliche Verlässlichkeit erfahrungsgemäß mehr als die Rechtsform.
A12: Der Punkt, an dem sich das Vorzeichen umkehrt
A13: EINE FRÜHE GRÜNDUNG KOSTET NICHT NUR GELD — SIE VERNICHTET ANSPRÜCHE. Das EXIST-Gründungsstipendium verlangt ausdrücklich, dass zum Förderbeginn noch KEINE Gesellschaft besteht. Das Gründungsstipendium Niedersachsen verlangt einen Antrag vor Vorhabenbeginn. Beide finanzieren den Lebensunterhalt und liegen nach A-09 und A-10 zusammen im deutlich fünfstelligen Bereich — für zwei Personen über zehn Monate rund 22.000 € allein beim Landesstipendium. Damit ist die Rechnung nicht mehr „Gründung früh kostet X mehr“, sondern „Gründung früh kostet X mehr UND schließt Y aus“. Beide Beträge liegen in derselben Größenordnung. Das ist der Grund, warum die Entscheidung vom 26.07.2026 — Gründung erst zu T0 — auch nach dieser Rechnung Bestand hat, ohne dass dieses Blatt sie empfehlen müsste.
A15: Was zwischen heute und der Gründung trotzdem geregelt sein muss
A16: Punkt | B16: Warum | F16: Wo es steht
A17: Vorbereitungs-Vereinbarung zwischen den Gründern | B17: Bis zur Gründung bildet ihr vermutlich eine GbR mit unbeschränkter persönlicher Haftung. Rechte und Pflichten gehen NICHT automatisch auf die GmbH über. Wer was einbringt, wem die Ergebnisse gehören und was bei einem Ausstieg passiert, gehört schriftlich fixiert. | F17: Aufgabe A-25, offene Entscheidung Nr. 26, Anwaltsakte B3
A18: Markenanmeldung | B18: Kann und sollte von natürlichen Personen erfolgen und später übertragen werden. Sie ist von der Gründung unabhängig — und im Windhundverfahren zählt der frühere Anmeldetag. | F18: Aufgabe A-01, `markenrecherche-cruizy.md`
A19: Übertragungsvereinbarung | B19: Damit alles, was vor der Gründung entsteht — Marke, Code, Verträge, Konzepte —, sauber auf die Gesellschaft übergeht. | F19: Anwaltsakte B3, Entwurf folgt aus A-25
A20: Krankenversicherungsstatus schriftlich klären | B20: Vor der Gründung, nicht danach. Es geht bei 24 Monaten um 9.600 € — und die Auskunft am Telefon hilft im Streitfall nicht. | F20: offene Entscheidung Nr. 25, Anwaltsakte B13

Sheet Quellen
A1: Quellen und Vorbehalte
A2: Alle externen Angaben am 27.07.2026 per Websuche erhoben.
A4: Nr | B4: Was belegt wird | C4: Fundstelle | D4: Stand
A5: 1 | B5: Notargebühren GmbH-Gründung: 2,0-Gebühr bei individuellem Vertrag, Mindestgeschäftswert 30.000 €, rund 476 € brutto bei 25.000 € Stammkapital | C5: GNotKG Anlage 2 (Gebührentabelle B) und § 107 GNotKG, gesetze-im-internet.de; Berechnung nachvollzogen über deutschland-rechner.de | D5: Stand 2026, Rechner zuletzt aktualisiert 06.06.2026
A6: 2 | B6: Handelsregister Ersteintragung: 225 € bei Bargründung, 360 € bei Sachgründung | C6: HRegGebV Anlage Nr. 2100 und 2101, gesetze-im-internet.de | D6: Fassung vom 30.04.2025
A7: 3 | B7: Mindeststammkapital 25.000 €, Mindesteinzahlung 12.500 € bei Bargründung | C7: § 5 und § 7 Abs. 2 GmbHG | D7: geltendes Recht
A8: 4 | B8: Musterprotokoll nur bis 3 Gesellschafter und 1 Geschäftsführer ohne individuelle Regelungen | C8: § 2 Abs. 1a GmbHG | D8: geltendes Recht
A9: 5 | B9: Gewerbeanmeldung 20–60 € je nach Kommune | C9: deutschland-rechner.de, GmbH-Gründungskosten | D9: abgerufen 27.07.2026
A10: 6 | B10: Jahresabschluss Kleinstkapitalgesellschaft 1.500–3.000 € netto; kleine GmbH mit Bilanzsumme bis 100.000 € eher 800–2.000 € | C10: onlinebilanz.de, Jahresabschluss-Kosten 2026 | D10: abgerufen 27.07.2026
A11: 7 | B11: Kleinstkapitalgesellschaft: Bilanzsumme ≤ 450.000 €, Umsatz ≤ 900.000 €, ≤ 10 Beschäftigte; verkürzte Bilanz ohne Anhang, Hinterlegung statt Offenlegung | C11: § 267a HGB | D11: geltendes Recht, Schwellenwerte in der Fassung seit 2024
A12: 8 | B12: Hinterlegung beim Bundesanzeiger rund 37 € für Kleinstkapitalgesellschaften; seit 2026 keine Einreichungsgebühr bei reiner Bilanzeinreichung | C12: onlinebilanz.de, Bundesanzeiger-Kosten GmbH 2026 | D12: abgerufen 27.07.2026
A13: 9 | B13: IHK-Beitrag: keine Existenzgründerbefreiung für Kapitalgesellschaften, weil § 3 Abs. 3 IHKG an natürliche Personen ohne Handelsregistereintrag anknüpft | C13: IHKG § 3 Abs. 3; IHK Frankfurt und IHK Berlin zur Beitragsbefreiung | D13: abgerufen 27.07.2026
A14: 10 | B14: IHK-Grundbeitrag wird von jeder Kammer in ihrer Wirtschaftssatzung selbst festgesetzt; Spanne von rund 64 € bis über 300 € | C14: Wirtschaftssatzungen 2026 verschiedener Kammern; IHK Berlin nennt 64 € für Handelsregister-eingetragene Unternehmen | D14: abgerufen 27.07.2026
A15: 11 | B15: Geschäftskonto: Kontoführung meist 5–30 € monatlich; kostenlose Konten mit Inklusivvolumen auch für die GmbH verfügbar | C15: Geschäftskonto-Vergleiche 07/2026 (fuer-gruender.de, gruenderkueche.de) | D15: abgerufen 27.07.2026
A16: 12 | B16: Ladungsfähige Geschäftsadresse 3,33 € bis 6,70 € je Monat | C16: eigene Vorarbeit A-04, `10-recht-gruendung/impressumsloesung-vergleich.md` | D16: 26.07.2026
... A20: 16 | B20: EXIST verlangt, dass zum Förderbeginn keine Gesellschaft besteht; Gründungsstipendium Niedersachsen verlangt Antrag vor Vorhabenbeginn | C20: eigene Vorarbeiten A-09 und A-10 | D20: 27.07.2026
A22: Vorbehalte
A23: Vier Zahlen in diesem Modell sind Mittelwerte oder Schätzungen und als solche gekennzeichnet: die anwaltliche Gestaltung des Gesellschaftsvertrags (aus der Differenz zu Handbuch B abgeleitet), der IHK-Grundbeitrag (kammerabhängig), die Gewerbeanmeldung (kommunal) und die Kosten des Jahresabschlusses (Spanne). Alle vier sind vor der Gründung durch eine konkrete Auskunft ersetzbar — bei Notar, Kammer, Gemeinde und Steuerberater. Zusammen bewegen sie weniger als die vier Schalterfragen auf dem Blatt „Ergebnis“. Nicht enthalten sind: Körperschaft- und Gewerbesteuer (fallen ohne Gewinn nicht an), Umsatzsteuervoranmeldungen (im Steuerberaterhonorar enthalten), Gründungsberatung durch Dritte, und sämtliche Kosten der Produktentwicklung — die stehen im Finanzmodell A-13.
